{
  "type": "Feature",
  "properties": {
    "gn:admin1_code":"10096138.0",
    "gn:admin2_code":"3.0",
    "gn:asciiname":"Trn",
    "gn:country_code":"XK",
    "gn:dem":549,
    "gn:feature_class":"P",
    "gn:feature_code":"PPL",
    "gn:name":"Trn",
    "gn:population":0,
    "gn:timezone":"Europe/Belgrade",
    "iso:country":"XK",
    "name:bos_x_preferred":[
        "Trn"
    ],
    "name:ceb_x_preferred":[
        "Trn"
    ],
    "name:ces_x_preferred":[
        "Trn"
    ],
    "name:fra_x_preferred":[
        "Trn"
    ],
    "name:hrv_x_preferred":[
        "Trn"
    ],
    "name:hun_x_preferred":[
        "Trn"
    ],
    "name:pol_x_preferred":[
        "Trn"
    ],
    "name:rus_x_preferred":[
        "\u0422\u0440\u043d"
    ],
    "name:slv_x_preferred":[
        "Trn"
    ],
    "name:sqi_x_preferred":[
        "T\u00ebrrn"
    ],
    "name:sqi_x_variant":[
        "T\u00ebrn",
        "T\u00ebrna"
    ],
    "name:srp_x_preferred":[
        "Trn"
    ],
    "name:srp_x_variant":[
        "\u0422\u0440\u043d"
    ],
    "name:swe_x_preferred":[
        "Trn"
    ],
    "wof:name":"Trn",
    "wof:placetype":"locality"
},
  "geometry": {"coordinates":[21.12944,42.44278],"type":"Point"}
}