{
  "type": "Feature",
  "properties": {
    "gn:admin1_code":"10097357.0",
    "gn:admin2_code":"6.0",
    "gn:asciiname":"Donji Muhadzeri",
    "gn:country_code":"XK",
    "gn:dem":519,
    "gn:feature_class":"P",
    "gn:feature_code":"PPL",
    "gn:name":"Donji Muhad\u017eeri",
    "gn:population":0,
    "gn:timezone":"Europe/Belgrade",
    "iso:country":"XK",
    "name:srp_x_preferred":[
        "Donji Muhad\u017eeri"
    ],
    "wof:name":"Donji Muhadzeri",
    "wof:placetype":"locality"
},
  "geometry": {"coordinates":[21.44028,42.43972],"type":"Point"}
}