{
  "type": "Feature",
  "properties": {
    "gn:admin1_code":"10097357.0",
    "gn:admin2_code":"10.0",
    "gn:asciiname":"Donje Recane",
    "gn:country_code":"XK",
    "gn:dem":488,
    "gn:feature_class":"P",
    "gn:feature_code":"PPL",
    "gn:name":"Donje Re\u010dane",
    "gn:population":0,
    "gn:timezone":"Europe/Belgrade",
    "iso:country":"XK",
    "name:srp_x_preferred":[
        "Donje Re\u010dane"
    ],
    "wof:name":"Donje Recane",
    "wof:placetype":"locality"
},
  "geometry": {"coordinates":[21.55722,42.60417],"type":"Point"}
}