{
  "type": "Feature",
  "properties": {
    "gn:admin1_code":"10097359.0",
    "gn:admin2_code":"8.0",
    "gn:asciiname":"Banja",
    "gn:country_code":"XK",
    "gn:dem":520,
    "gn:feature_class":"P",
    "gn:feature_code":"PPL",
    "gn:name":"Banja",
    "gn:population":0,
    "gn:timezone":"Europe/Belgrade",
    "iso:country":"XK",
    "name:bos_x_preferred":[
        "Banja"
    ],
    "name:ceb_x_preferred":[
        "Banja"
    ],
    "name:fra_x_preferred":[
        "Banja"
    ],
    "name:hrv_x_preferred":[
        "Banja"
    ],
    "name:hun_x_preferred":[
        "Banja"
    ],
    "name:ita_x_preferred":[
        "Banja"
    ],
    "name:nld_x_preferred":[
        "Banja"
    ],
    "name:por_x_preferred":[
        "Banja"
    ],
    "name:slv_x_preferred":[
        "Banja"
    ],
    "name:sqi_x_preferred":[
        "Banj\u00eb"
    ],
    "name:sqi_x_variant":[
        "Banja e K\u00ebrnjin\u00ebs",
        "Baja e Pej\u00ebs",
        "Baj\u00eb"
    ],
    "name:srp_x_preferred":[
        "\u0411\u0430\u045a\u0430"
    ],
    "name:srp_x_variant":[
        "Banja",
        "Pe\u0107ka Banja",
        "Pe\u0107ska Banja"
    ],
    "name:swe_x_preferred":[
        "Banja"
    ],
    "name:und_x_variant":[
        "Baja"
    ],
    "wof:name":"Banja",
    "wof:placetype":"locality"
},
  "geometry": {"coordinates":[20.39139,42.72694],"type":"Point"}
}