{
  "type": "Feature",
  "properties": {
    "gn:admin1_code":"10097360.0",
    "gn:admin2_code":"7.0",
    "gn:asciiname":"Prenk Mahala",
    "gn:country_code":"XK",
    "gn:dem":604,
    "gn:feature_class":"P",
    "gn:feature_code":"PPL",
    "gn:name":"Prenk Mahala",
    "gn:population":0,
    "gn:timezone":"Europe/Belgrade",
    "iso:country":"XK",
    "name:srp_x_preferred":[
        "Prenk Mahala"
    ],
    "wof:name":"Prenk Mahala",
    "wof:placetype":"locality"
},
  "geometry": {"coordinates":[20.95111,42.65861],"type":"Point"}
}