{
  "type": "Feature",
  "properties": {
    "gn:asciiname":"Tofaj",
    "gn:country_code":"XK",
    "gn:dem":599,
    "gn:feature_class":"P",
    "gn:feature_code":"PPL",
    "gn:name":"Tofaj",
    "gn:population":0,
    "gn:timezone":"Europe/Belgrade",
    "iso:country":"XK",
    "wof:name":"Tofaj",
    "wof:placetype":"locality"
},
  "geometry": {"coordinates":[20.26585,42.48295],"type":"Point"}
}