{
  "type": "Feature",
  "properties": {
    "gn:admin1_code":"10097357.0",
    "gn:admin2_code":"27.0",
    "gn:asciiname":"Gjylekar",
    "gn:country_code":"XK",
    "gn:dem":520,
    "gn:feature_class":"P",
    "gn:feature_code":"PPL",
    "gn:name":"Gjylekar",
    "gn:population":0,
    "gn:timezone":"Europe/Belgrade",
    "iso:country":"XK",
    "name:sqi_x_preferred":[
        "Gjylekar\u00eb"
    ],
    "name:sqi_x_variant":[
        "Skifteraj",
        "Gjylekar"
    ],
    "name:srp_x_preferred":[
        "\u00d0elekare"
    ],
    "name:srp_x_variant":[
        "\u0402\u0435\u043b\u0435\u043a\u0430\u0440\u0435"
    ],
    "wof:name":"Gjylekar",
    "wof:placetype":"locality"
},
  "geometry": {"coordinates":[21.42778,42.34778],"type":"Point"}
}