{
  "type": "Feature",
  "properties": {
    "gn:admin1_code":"10097358.0",
    "gn:admin2_code":"29.0",
    "gn:asciiname":"Klecke",
    "gn:country_code":"XK",
    "gn:dem":934,
    "gn:feature_class":"P",
    "gn:feature_code":"PPL",
    "gn:name":"Kle\u010dke",
    "gn:population":0,
    "gn:timezone":"Europe/Belgrade",
    "iso:country":"XK",
    "name:sqi_x_preferred":[
        "Kle\u00e7k\u00eb"
    ],
    "name:srp_x_preferred":[
        "Kle\u010dke"
    ],
    "name:srp_x_variant":[
        "\u041a\u043b\u0435\u0447\u043a\u0435",
        "\u041a\u043b\u0435\u0447\u0430\u043a",
        "Kle\u010dak"
    ],
    "name:und_x_variant":[
        "Kle\u010dak"
    ],
    "wof:name":"Klecke",
    "wof:placetype":"locality"
},
  "geometry": {"coordinates":[20.56944,42.975],"type":"Point"}
}