{
  "type": "Feature",
  "properties": {
    "gn:admin1_code":"10096138.0",
    "gn:admin2_code":"3.0",
    "gn:asciiname":"Saraiste",
    "gn:country_code":"XK",
    "gn:dem":576,
    "gn:feature_class":"P",
    "gn:feature_code":"PPL",
    "gn:name":"Sarai\u0161te",
    "gn:population":0,
    "gn:timezone":"Europe/Belgrade",
    "iso:country":"XK",
    "name:srp_x_preferred":[
        "Sarai\u0161te"
    ],
    "wof:name":"Saraiste",
    "wof:placetype":"locality"
},
  "geometry": {"coordinates":[21.13278,42.39278],"type":"Point"}
}