{
  "type": "Feature",
  "properties": {
    "gn:admin1_code":"10097360.0",
    "gn:admin2_code":"19.0",
    "gn:asciiname":"Balovac",
    "gn:country_code":"XK",
    "gn:dem":618,
    "gn:feature_class":"P",
    "gn:feature_code":"PPL",
    "gn:name":"Balovac",
    "gn:population":0,
    "gn:timezone":"Europe/Belgrade",
    "iso:country":"XK",
    "name:sqi_x_preferred":[
        "Balloc"
    ],
    "name:sqi_x_variant":[
        "Ballovc",
        "Ballofc",
        "Ballofci",
        "Ballsh",
        "Ballshi"
    ],
    "name:srp_x_preferred":[
        "Balovac"
    ],
    "name:srp_x_variant":[
        "\u0411\u0430\u043b\u043e\u0432\u0430\u0446"
    ],
    "name:und_x_variant":[
        "Ballofci",
        "Ballshi",
        "Ballsh",
        "Ballofc",
        "Balovce"
    ],
    "wof:name":"Balovac",
    "wof:placetype":"locality"
},
  "geometry": {"coordinates":[21.23407000000001,42.89462],"type":"Point"}
}