{
  "type": "Feature",
  "properties": {
    "gn:admin1_code":"10097358.0",
    "gn:admin2_code":"29.0",
    "gn:asciiname":"Sipovo",
    "gn:country_code":"XK",
    "gn:dem":922,
    "gn:feature_class":"P",
    "gn:feature_code":"PPL",
    "gn:name":"\u0160ipovo",
    "gn:population":0,
    "gn:timezone":"Europe/Belgrade",
    "iso:country":"XK",
    "name:sqi_x_preferred":[
        "Shipov\u00eb"
    ],
    "name:srp_x_preferred":[
        "\u0428\u0438\u043f\u043e\u0432\u043e"
    ],
    "name:srp_x_variant":[
        "\u0160ipovo"
    ],
    "wof:name":"Sipovo",
    "wof:placetype":"locality"
},
  "geometry": {"coordinates":[20.67222000000001,43.01722],"type":"Point"}
}