{
  "type": "Feature",
  "properties": {
    "gn:admin1_code":"10097360.0",
    "gn:admin2_code":"13.0",
    "gn:asciiname":"Popova Livada",
    "gn:country_code":"XK",
    "gn:dem":929,
    "gn:feature_class":"P",
    "gn:feature_code":"PPL",
    "gn:name":"Popova Livada",
    "gn:population":0,
    "gn:timezone":"Europe/Belgrade",
    "iso:country":"XK",
    "name:srp_x_preferred":[
        "\u041f\u043e\u043f\u043e\u0432\u0430 \u041b\u0438\u0432\u0430\u0434\u0430"
    ],
    "name:srp_x_variant":[
        "Popova Livada"
    ],
    "wof:name":"Popova Livada",
    "wof:placetype":"locality"
},
  "geometry": {"coordinates":[21.31564,42.57546],"type":"Point"}
}