{
  "type": "Feature",
  "properties": {
    "gn:admin1_code":"10097360.0",
    "gn:admin2_code":"7.0",
    "gn:asciiname":"Orlate",
    "gn:country_code":"XK",
    "gn:dem":696,
    "gn:feature_class":"P",
    "gn:feature_code":"PPLL",
    "gn:name":"Orlate",
    "gn:population":0,
    "gn:timezone":"Europe/Belgrade",
    "iso:country":"XK",
    "name:sqi_x_preferred":[
        "Arllat"
    ],
    "name:sqi_x_variant":[
        "Orlash",
        "Arllati"
    ],
    "name:srp_x_preferred":[
        "\u041e\u0440\u043b\u0430\u0442\u0435"
    ],
    "name:srp_x_variant":[
        "Orlate"
    ],
    "name:und_x_variant":[
        "Orlatti",
        "Arlat",
        "Orlat"
    ],
    "wof:name":"Orlate",
    "wof:placetype":"locality"
},
  "geometry": {"coordinates":[20.83528,42.55139000000001],"type":"Point"}
}