{
  "type": "Feature",
  "properties": {
    "gn:admin1_code":"10097358.0",
    "gn:admin2_code":"30.0",
    "gn:asciiname":"Meki Dio",
    "gn:country_code":"XK",
    "gn:dem":802,
    "gn:feature_class":"P",
    "gn:feature_code":"PPL",
    "gn:name":"Meki Dio",
    "gn:population":0,
    "gn:timezone":"Europe/Belgrade",
    "iso:country":"XK",
    "name:sqi_x_preferred":[
        "Mekidoll"
    ],
    "name:srp_x_preferred":[
        "Meki Dio"
    ],
    "name:srp_x_variant":[
        "\u041c\u0435\u043a\u0438 \u0414\u0438\u043e",
        "\u041c\u0435\u043a\u0438 \u0414\u043e",
        "Meki Do"
    ],
    "wof:name":"Meki Dio",
    "wof:placetype":"locality"
},
  "geometry": {"coordinates":[20.78444,43.00972],"type":"Point"}
}