{
  "type": "Feature",
  "properties": {
    "gn:admin1_code":"10096859.0",
    "gn:admin2_code":"5.0",
    "gn:asciiname":"Mazrek",
    "gn:country_code":"XK",
    "gn:dem":480,
    "gn:feature_class":"P",
    "gn:feature_code":"PPL",
    "gn:name":"Mazrek",
    "gn:population":0,
    "gn:timezone":"Europe/Belgrade",
    "iso:country":"XK",
    "name:ceb_x_preferred":[
        "Mazrek"
    ],
    "name:sqi_x_preferred":[
        "Mazrek"
    ],
    "name:srp_x_preferred":[
        "Mazrek"
    ],
    "name:swe_x_preferred":[
        "Mazrek"
    ],
    "wof:name":"Mazrek",
    "wof:placetype":"locality"
},
  "geometry": {"coordinates":[20.30222,42.37694000000001],"type":"Point"}
}