{
  "type": "Feature",
  "properties": {
    "gn:admin1_code":"10096859.0",
    "gn:admin2_code":"1.0",
    "gn:asciiname":"Dubovik",
    "gn:country_code":"XK",
    "gn:dem":535,
    "gn:feature_class":"P",
    "gn:feature_code":"PPL",
    "gn:name":"Dubovik",
    "gn:population":0,
    "gn:timezone":"Europe/Belgrade",
    "iso:country":"XK",
    "name:sqi_x_preferred":[
        "Duboviku"
    ],
    "name:sqi_x_variant":[
        "Burr\u00ebmadh",
        "Burr\u00ebmadhi"
    ],
    "name:srp_x_preferred":[
        "Dubovik"
    ],
    "name:srp_x_variant":[
        "\u0414\u0443\u0431\u043e\u0432\u0438\u043a"
    ],
    "name:und_x_variant":[
        "Burr\u00ebmadh",
        "Duboviku",
        "Burr\u00ebmadhi"
    ],
    "wof:name":"Dubovik",
    "wof:placetype":"locality"
},
  "geometry": {"coordinates":[20.33667,42.57361],"type":"Point"}
}