{
  "type": "Feature",
  "properties": {
    "gn:admin1_code":"10097358.0",
    "gn:admin2_code":"12.0",
    "gn:asciiname":"Ivanje",
    "gn:country_code":"XK",
    "gn:dem":638,
    "gn:feature_class":"P",
    "gn:feature_code":"PPL",
    "gn:name":"Ivanje",
    "gn:population":0,
    "gn:timezone":"Europe/Belgrade",
    "iso:country":"XK",
    "name:srp_x_preferred":[
        "Ivanje"
    ],
    "wof:name":"Ivanje",
    "wof:placetype":"locality"
},
  "geometry": {"coordinates":[20.77306,43.06833],"type":"Point"}
}