{
  "type": "Feature",
  "properties": {
    "gn:admin1_code":"10097360.0",
    "gn:admin2_code":"16.0",
    "gn:asciiname":"Dorgovci",
    "gn:country_code":"XK",
    "gn:dem":815,
    "gn:feature_class":"P",
    "gn:feature_code":"PPL",
    "gn:name":"Dorgovci",
    "gn:population":0,
    "gn:timezone":"Europe/Belgrade",
    "iso:country":"XK",
    "name:srp_x_preferred":[
        "Dorgovci"
    ],
    "wof:name":"Dorgovci",
    "wof:placetype":"locality"
},
  "geometry": {"coordinates":[21.35966,42.57309],"type":"Point"}
}