{
  "type": "Feature",
  "properties": {
    "gn:admin1_code":"10096138.0",
    "gn:admin2_code":"24.0",
    "gn:asciiname":"Gjurkoc",
    "gn:country_code":"XK",
    "gn:dem":556,
    "gn:feature_class":"P",
    "gn:feature_code":"PPL",
    "gn:name":"Gjurkoc",
    "gn:population":0,
    "gn:timezone":"Europe/Belgrade",
    "iso:country":"XK",
    "name:sqi_x_preferred":[
        "Gjurkovc"
    ],
    "name:sqi_x_variant":[
        "Durkovce",
        "Gjurkoc",
        "Gjurakofc"
    ],
    "name:srp_x_preferred":[
        "\u00d0urkovce"
    ],
    "name:srp_x_variant":[
        "\u0402\u0443\u0440\u043a\u043e\u0432\u0446\u0435"
    ],
    "name:und_x_variant":[
        "Gjurakofc"
    ],
    "wof:name":"Gjurkoc",
    "wof:placetype":"locality"
},
  "geometry": {"coordinates":[21.08944,42.46861],"type":"Point"}
}