{
  "type": "Feature",
  "properties": {
    "gn:admin1_code":"10097358.0",
    "gn:admin2_code":"15.0",
    "gn:asciiname":"Prvi Tunel",
    "gn:country_code":"XK",
    "gn:dem":600,
    "gn:feature_class":"P",
    "gn:feature_code":"PPL",
    "gn:name":"Prvi Tunel",
    "gn:population":0,
    "gn:timezone":"Europe/Belgrade",
    "iso:country":"XK",
    "name:fra_x_preferred":[
        "Prvi Tunel"
    ],
    "name:sqi_x_preferred":[
        "Tunel i Par\u00eb"
    ],
    "name:srp_x_preferred":[
        "\u041f\u0440\u0432\u0438 \u0422\u0443\u043d\u0435\u043b"
    ],
    "name:srp_x_variant":[
        "Prvi Tunel",
        "Kolonija Prvi Tunel"
    ],
    "wof:name":"Prvi Tunel",
    "wof:placetype":"locality"
},
  "geometry": {"coordinates":[20.89833,42.92222],"type":"Point"}
}