{
  "type": "Feature",
  "properties": {
    "gn:admin1_code":"10097361.0",
    "gn:admin2_code":"21.0",
    "gn:asciiname":"Shpenadi",
    "gn:country_code":"XK",
    "gn:dem":381,
    "gn:feature_class":"P",
    "gn:feature_code":"PPL",
    "gn:name":"Shpenadi",
    "gn:population":0,
    "gn:timezone":"Europe/Belgrade",
    "iso:country":"XK",
    "name:sqi_x_preferred":[
        "Shpenadi"
    ],
    "name:sqi_x_variant":[
        "Shpinadi",
        "Shpinadij\u00eb",
        "Shipandije"
    ],
    "name:srp_x_preferred":[
        "\u0428\u043f\u0438\u043d\u0430\u0434\u0438\u0458\u0430"
    ],
    "name:srp_x_variant":[
        "\u0160pinadija"
    ],
    "name:und_x_variant":[
        "Shipandije"
    ],
    "wof:name":"Shpenadi",
    "wof:placetype":"locality"
},
  "geometry": {"coordinates":[20.76,42.2725],"type":"Point"}
}