{
  "type": "Feature",
  "properties": {
    "gn:admin1_code":"10097359.0",
    "gn:admin2_code":"18.0",
    "gn:asciiname":"Koshutan",
    "gn:country_code":"XK",
    "gn:dem":1401,
    "gn:feature_class":"P",
    "gn:feature_code":"PPLL",
    "gn:name":"Koshutan",
    "gn:population":0,
    "gn:timezone":"Europe/Belgrade",
    "iso:country":"XK",
    "name:sqi_x_preferred":[
        "Koshutan"
    ],
    "name:sqi_x_variant":[
        "Koshutanc\u00eb",
        "Gjekajt",
        "Koshutani"
    ],
    "name:srp_x_preferred":[
        "Ko\u0161utane"
    ],
    "name:srp_x_variant":[
        "\u041a\u043e\u0448\u0443\u0442\u0430\u043d\u0435"
    ],
    "name:und_x_variant":[
        "Gjekajt",
        "Koshutanc\u00eb",
        "Koshutani"
    ],
    "wof:name":"Koshutan",
    "wof:placetype":"locality"
},
  "geometry": {"coordinates":[20.10111,42.73889000000001],"type":"Point"}
}