{
  "type": "Feature",
  "properties": {
    "gn:admin1_code":"10097360.0",
    "gn:admin2_code":"7.0",
    "gn:asciiname":"Globare",
    "gn:country_code":"XK",
    "gn:dem":618,
    "gn:feature_class":"P",
    "gn:feature_code":"PPL",
    "gn:name":"Globare",
    "gn:population":0,
    "gn:timezone":"Europe/Belgrade",
    "iso:country":"XK",
    "name:deu_x_preferred":[
        "Globare"
    ],
    "name:fra_x_preferred":[
        "Globare"
    ],
    "name:msa_x_preferred":[
        "Globare"
    ],
    "name:por_x_preferred":[
        "Globare"
    ],
    "name:slv_x_preferred":[
        "Globare"
    ],
    "name:sqi_x_preferred":[
        "Gllobar"
    ],
    "name:sqi_x_variant":[
        "Globar\u00eb",
        "Glabar",
        "Globar",
        "Gllabar",
        "Gllobare",
        "Gllabari",
        "Bletar",
        "Bletari"
    ],
    "name:srp_x_preferred":[
        "\u0413\u043b\u043e\u0431\u0430\u0440\u0435"
    ],
    "name:srp_x_variant":[
        "Globare"
    ],
    "wof:name":"Globare",
    "wof:placetype":"locality"
},
  "geometry": {"coordinates":[20.87056,42.64583],"type":"Point"}
}