{
  "type": "Feature",
  "properties": {
    "gn:admin1_code":"10096138.0",
    "gn:admin2_code":"3.0",
    "gn:asciiname":"Prelez i Muhaxher",
    "gn:country_code":"XK",
    "gn:dem":565,
    "gn:feature_class":"P",
    "gn:feature_code":"PPL",
    "gn:name":"Prelez i Muhaxher",
    "gn:population":0,
    "gn:timezone":"Europe/Belgrade",
    "iso:country":"XK",
    "name:sqi_x_preferred":[
        "Prelezi Muhaxher"
    ],
    "name:sqi_x_variant":[
        "Prelez i Muhaxher\u00ebve",
        "Prelez i Muhaxher",
        "Prelez i Muhaxherve"
    ],
    "name:srp_x_preferred":[
        "Muhad\u017eer Prelez"
    ],
    "name:srp_x_variant":[
        "\u041c\u0443\u0445\u0430\u045f\u0435\u0440 \u041f\u0440\u0435\u043b\u0435\u0437"
    ],
    "name:und_x_variant":[
        "Prelez i Muhaxherve"
    ],
    "wof:name":"Prelez i Muhaxher",
    "wof:placetype":"locality"
},
  "geometry": {"coordinates":[21.16694,42.43417],"type":"Point"}
}