{
  "type": "Feature",
  "properties": {
    "gn:admin1_code":"10097357.0",
    "gn:admin2_code":"6.0",
    "gn:asciiname":"Podgrage",
    "gn:country_code":"XK",
    "gn:dem":458,
    "gn:feature_class":"P",
    "gn:feature_code":"PPL",
    "gn:name":"Podgra\u0111e",
    "gn:population":0,
    "gn:timezone":"Europe/Belgrade",
    "iso:country":"XK",
    "name:sqi_x_preferred":[
        "Pogragj\u00eb"
    ],
    "name:sqi_x_variant":[
        "Pograxha",
        "Pograxh\u00eb",
        "Gjytet-i"
    ],
    "name:srp_x_preferred":[
        "Podgra\u0111e"
    ],
    "name:srp_x_variant":[
        "\u041f\u043e\u0434\u0433\u0440\u0430\u0452\u0435"
    ],
    "name:und_x_variant":[
        "Gjytet-i",
        "Pograxha",
        "Pograxh\u00eb"
    ],
    "wof:name":"Podgrage",
    "wof:placetype":"locality"
},
  "geometry": {"coordinates":[21.58278,42.42917],"type":"Point"}
}