{
  "type": "Feature",
  "properties": {
    "gn:admin1_code":"10097358.0",
    "gn:admin2_code":"28.0",
    "gn:asciiname":"Slatina",
    "gn:country_code":"XK",
    "gn:dem":543,
    "gn:feature_class":"P",
    "gn:feature_code":"PPL",
    "gn:name":"Slatina",
    "gn:population":0,
    "gn:timezone":"Europe/Belgrade",
    "iso:country":"XK",
    "name:fin_x_preferred":[
        "Slatina"
    ],
    "name:pol_x_preferred":[
        "Slatina"
    ],
    "name:sqi_x_preferred":[
        "Sllatin\u00eb"
    ],
    "name:sqi_x_variant":[
        "Sllatina"
    ],
    "name:srp_x_preferred":[
        "\u0421\u043b\u0430\u0442\u0438\u043d\u0430"
    ],
    "name:srp_x_variant":[
        "Slatina"
    ],
    "name:ukr_x_preferred":[
        "\u0421\u043b\u0430\u0442\u0438\u043d\u0430"
    ],
    "name:und_x_variant":[
        "Sllatina"
    ],
    "wof:name":"Slatina",
    "wof:placetype":"locality"
},
  "geometry": {"coordinates":[20.96944,42.85306],"type":"Point"}
}