{
  "type": "Feature",
  "properties": {
    "gn:admin1_code":"10097358.0",
    "gn:admin2_code":"28.0",
    "gn:asciiname":"Slatina",
    "gn:country_code":"XK",
    "gn:dem":543,
    "gn:feature_class":"P",
    "gn:feature_code":"PPL",
    "gn:name":"Slatina",
    "gn:population":0,
    "gn:timezone":"Europe/Belgrade",
    "iso:country":"XK",
    "name:azb_x_preferred":[
        "\u0633\u062a\u06cc\u0626\u0627"
    ],
    "name:bos_x_preferred":[
        "Slatina"
    ],
    "name:bul_x_preferred":[
        "\u0421\u043b\u0430\u0442\u0438\u043d\u0430"
    ],
    "name:ceb_x_preferred":[
        "Slatina"
    ],
    "name:ces_x_preferred":[
        "Slatina"
    ],
    "name:deu_x_preferred":[
        "Slatina"
    ],
    "name:epo_x_preferred":[
        "Slatina"
    ],
    "name:eus_x_preferred":[
        "Slatina"
    ],
    "name:fin_x_preferred":[
        "Slatina"
    ],
    "name:fra_x_preferred":[
        "Slatina"
    ],
    "name:heb_x_preferred":[
        "\u05e1\u05dc\u05d0\u05d8\u05d9\u05e0\u05d4"
    ],
    "name:hrv_x_preferred":[
        "Slatina"
    ],
    "name:hun_x_preferred":[
        "Slatina"
    ],
    "name:ita_x_preferred":[
        "Slatina"
    ],
    "name:jpn_x_preferred":[
        "\u30b9\u30e9\u30c6\u30a3\u30ca"
    ],
    "name:min_x_preferred":[
        "Slatina"
    ],
    "name:mkd_x_preferred":[
        "\u0421\u043b\u0430\u0442\u0438\u043d\u0430"
    ],
    "name:nld_x_preferred":[
        "Slatina"
    ],
    "name:pol_x_preferred":[
        "Slatina"
    ],
    "name:ron_x_preferred":[
        "Slatina"
    ],
    "name:rus_x_preferred":[
        "\u0421\u043b\u0430\u0442\u0438\u043d\u0430"
    ],
    "name:slk_x_preferred":[
        "Slatina"
    ],
    "name:slv_x_preferred":[
        "Slatina"
    ],
    "name:spa_x_preferred":[
        "Slatina"
    ],
    "name:sqi_x_preferred":[
        "Sllatin\u00eb"
    ],
    "name:sqi_x_variant":[
        "Sllatina"
    ],
    "name:srp_x_preferred":[
        "\u0421\u043b\u0430\u0442\u0438\u043d\u0430"
    ],
    "name:srp_x_variant":[
        "Slatina"
    ],
    "name:swe_x_preferred":[
        "Slatina"
    ],
    "name:tat_x_preferred":[
        "\u0421\u043b\u0430\u0442\u0438\u043d\u0430"
    ],
    "name:ukr_x_preferred":[
        "\u0421\u043b\u0430\u0442\u0438\u043d\u0430"
    ],
    "name:und_x_variant":[
        "Sllatina"
    ],
    "wof:name":"Slatina",
    "wof:placetype":"locality"
},
  "geometry": {"coordinates":[20.96944,42.85306],"type":"Point"}
}