{
  "type": "Feature",
  "properties": {
    "gn:admin1_code":"10096138.0",
    "gn:admin2_code":"9.0",
    "gn:asciiname":"Cafka Mahala",
    "gn:country_code":"XK",
    "gn:dem":707,
    "gn:feature_class":"P",
    "gn:feature_code":"PPL",
    "gn:name":"\u010cafka Mahala",
    "gn:population":0,
    "gn:timezone":"Europe/Belgrade",
    "iso:country":"XK",
    "name:srp_x_preferred":[
        "\u010cafka Mahala"
    ],
    "wof:name":"Cafka Mahala",
    "wof:placetype":"locality"
},
  "geometry": {"coordinates":[21.26806,42.26833],"type":"Point"}
}