{
  "type": "Feature",
  "properties": {
    "gn:asciiname":"Qestaj",
    "gn:country_code":"XK",
    "gn:dem":532,
    "gn:feature_class":"P",
    "gn:feature_code":"PPL",
    "gn:name":"Qestaj",
    "gn:population":0,
    "gn:timezone":"Europe/Belgrade",
    "iso:country":"XK",
    "wof:name":"Qestaj",
    "wof:placetype":"locality"
},
  "geometry": {"coordinates":[20.27461,42.46995],"type":"Point"}
}