{
  "type": "Feature",
  "properties": {
    "gn:admin1_code":"10097361.0",
    "gn:admin2_code":"26.0",
    "gn:asciiname":"Semetiste",
    "gn:country_code":"XK",
    "gn:dem":411,
    "gn:feature_class":"P",
    "gn:feature_code":"PPL",
    "gn:name":"Semeti\u0161te",
    "gn:population":0,
    "gn:timezone":"Europe/Belgrade",
    "iso:country":"XK",
    "name:sqi_x_preferred":[
        "Semetisht"
    ],
    "name:sqi_x_variant":[
        "Semetisht\u00eb",
        "Semetish\u00eb"
    ],
    "name:srp_x_preferred":[
        "Semeti\u0161te"
    ],
    "name:srp_x_variant":[
        "\u0421\u0435\u043c\u0435\u0442\u0438\u0448\u0442\u0435"
    ],
    "name:und_x_variant":[
        "Semetish\u00eb"
    ],
    "wof:name":"Semetiste",
    "wof:placetype":"locality"
},
  "geometry": {"coordinates":[20.80444,42.39194000000001],"type":"Point"}
}