{
  "type": "Feature",
  "properties": {
    "gn:admin1_code":"10097360.0",
    "gn:admin2_code":"19.0",
    "gn:asciiname":"Vukufska Mahala",
    "gn:country_code":"XK",
    "gn:dem":660,
    "gn:feature_class":"P",
    "gn:feature_code":"PPL",
    "gn:name":"Vukufska Mahala",
    "gn:population":0,
    "gn:timezone":"Europe/Belgrade",
    "iso:country":"XK",
    "name:srp_x_preferred":[
        "Vukufska Mahala"
    ],
    "wof:name":"Vukufska Mahala",
    "wof:placetype":"locality"
},
  "geometry": {"coordinates":[21.16458,42.96047],"type":"Point"}
}