{
  "type": "Feature",
  "properties": {
    "gn:admin1_code":"10097360.0",
    "gn:admin2_code":"20.0",
    "gn:asciiname":"Suljinar",
    "gn:country_code":"XK",
    "gn:dem":870,
    "gn:feature_class":"P",
    "gn:feature_code":"PPL",
    "gn:name":"Suljinar",
    "gn:population":0,
    "gn:timezone":"Europe/Belgrade",
    "iso:country":"XK",
    "name:srp_x_preferred":[
        "Suljinar"
    ],
    "name:srp_x_variant":[
        "Mahala Sjulinar"
    ],
    "wof:name":"Suljinar",
    "wof:placetype":"locality"
},
  "geometry": {"coordinates":[21.43778,42.66306],"type":"Point"}
}