{
  "type": "Feature",
  "properties": {
    "gn:admin1_code":"10097360.0",
    "gn:admin2_code":"16.0",
    "gn:asciiname":"Sumaci",
    "gn:country_code":"XK",
    "gn:dem":867,
    "gn:feature_class":"P",
    "gn:feature_code":"PPL",
    "gn:name":"\u0160umaci",
    "gn:population":0,
    "gn:timezone":"Europe/Belgrade",
    "iso:country":"XK",
    "name:srp_x_preferred":[
        "\u0160umaci"
    ],
    "wof:name":"Sumaci",
    "wof:placetype":"locality"
},
  "geometry": {"coordinates":[21.45113,42.59243],"type":"Point"}
}