{
  "type": "Feature",
  "properties": {
    "gn:admin1_code":"10097358.0",
    "gn:admin2_code":"30.0",
    "gn:asciiname":"Han Grizani",
    "gn:country_code":"XK",
    "gn:dem":1121,
    "gn:feature_class":"P",
    "gn:feature_code":"PPL",
    "gn:name":"Han Gri\u017eani",
    "gn:population":0,
    "gn:timezone":"Europe/Belgrade",
    "iso:country":"XK",
    "name:sqi_x_preferred":[
        "Han-Grizhani"
    ],
    "name:srp_x_preferred":[
        "Han Gri\u017eani"
    ],
    "wof:name":"Han Grizani",
    "wof:placetype":"locality"
},
  "geometry": {"coordinates":[20.71278,43.035],"type":"Point"}
}