{
  "type": "Feature",
  "properties": {
    "gn:admin1_code":"10097360.0",
    "gn:admin2_code":"20.0",
    "gn:asciiname":"Mahala Mesovic",
    "gn:country_code":"XK",
    "gn:dem":730,
    "gn:feature_class":"P",
    "gn:feature_code":"PPL",
    "gn:name":"Mahala Mesovi\u0107",
    "gn:population":0,
    "gn:timezone":"Europe/Belgrade",
    "iso:country":"XK",
    "name:srp_x_preferred":[
        "Mahala Mesovi\u0107"
    ],
    "wof:name":"Mahala Mesovic",
    "wof:placetype":"locality"
},
  "geometry": {"coordinates":[21.385,42.68056],"type":"Point"}
}