{
  "type": "Feature",
  "properties": {
    "gn:admin1_code":"10096138.0",
    "gn:admin2_code":"3.0",
    "gn:asciiname":"Donja Mahala",
    "gn:country_code":"XK",
    "gn:dem":561,
    "gn:feature_class":"P",
    "gn:feature_code":"PPL",
    "gn:name":"Donja Mahala",
    "gn:population":0,
    "gn:timezone":"Europe/Belgrade",
    "iso:country":"XK",
    "name:srp_x_preferred":[
        "Donja Mahala"
    ],
    "name:swe_x_preferred":[
        "Donja Mahala"
    ],
    "wof:name":"Donja Mahala",
    "wof:placetype":"locality"
},
  "geometry": {"coordinates":[21.14778,42.41194],"type":"Point"}
}