{
  "type": "Feature",
  "properties": {
    "gn:admin1_code":"10097361.0",
    "gn:admin2_code":"14.0",
    "gn:asciiname":"Stepenice",
    "gn:country_code":"XK",
    "gn:dem":579,
    "gn:feature_class":"P",
    "gn:feature_code":"PPL",
    "gn:name":"Stepenice",
    "gn:population":0,
    "gn:timezone":"Europe/Belgrade",
    "iso:country":"XK",
    "name:srp_x_preferred":[
        "\u0421\u0442\u0435\u043f\u0435\u043d\u0438\u0446\u0435"
    ],
    "name:srp_x_variant":[
        "Stepenice"
    ],
    "name:und_x_variant":[
        "Stepanica"
    ],
    "wof:name":"Stepenice",
    "wof:placetype":"locality"
},
  "geometry": {"coordinates":[20.70444,42.57861],"type":"Point"}
}