{
  "type": "Feature",
  "properties": {
    "gn:admin1_code":"10097361.0",
    "gn:admin2_code":"26.0",
    "gn:asciiname":"Toplicane",
    "gn:country_code":"XK",
    "gn:dem":407,
    "gn:feature_class":"P",
    "gn:feature_code":"PPL",
    "gn:name":"Topli\u010dane",
    "gn:population":0,
    "gn:timezone":"Europe/Belgrade",
    "iso:country":"XK",
    "name:srp_x_preferred":[
        "Topli\u010dane"
    ],
    "name:srp_x_variant":[
        "\u0422\u043e\u043f\u043b\u0438\u0447\u0430\u043d\u0435"
    ],
    "wof:name":"Toplicane",
    "wof:placetype":"locality"
},
  "geometry": {"coordinates":[20.8025,42.325],"type":"Point"}
}