{
  "type": "Feature",
  "properties": {
    "gn:admin1_code":"10097360.0",
    "gn:admin2_code":"20.0",
    "gn:asciiname":"Pod Mahala",
    "gn:country_code":"XK",
    "gn:dem":877,
    "gn:feature_class":"P",
    "gn:feature_code":"PPL",
    "gn:name":"Pod Mahala",
    "gn:population":0,
    "gn:timezone":"Europe/Belgrade",
    "iso:country":"XK",
    "name:srp_x_preferred":[
        "Pod Mahala"
    ],
    "wof:name":"Pod Mahala",
    "wof:placetype":"locality"
},
  "geometry": {"coordinates":[21.28443,42.80546],"type":"Point"}
}