{
  "type": "Feature",
  "properties": {
    "gn:admin1_code":"10097357.0",
    "gn:admin2_code":"10.0",
    "gn:asciiname":"Mesina",
    "gn:country_code":"XK",
    "gn:dem":557,
    "gn:feature_class":"P",
    "gn:feature_code":"PPLL",
    "gn:name":"Me\u0161ina",
    "gn:population":0,
    "gn:timezone":"Europe/Belgrade",
    "iso:country":"XK",
    "name:sqi_x_preferred":[
        "Meshin\u00eb"
    ],
    "name:sqi_x_variant":[
        "Meshina"
    ],
    "name:srp_x_preferred":[
        "Me\u0161ina"
    ],
    "name:srp_x_variant":[
        "\u041c\u0435\u0448\u0438\u043d\u0430"
    ],
    "name:und_x_variant":[
        "Meshina"
    ],
    "wof:name":"Mesina",
    "wof:placetype":"locality"
},
  "geometry": {"coordinates":[21.54556,42.64972],"type":"Point"}
}