{
  "type": "Feature",
  "properties": {
    "gn:admin1_code":"10097357.0",
    "gn:admin2_code":"6.0",
    "gn:asciiname":"Zheger",
    "gn:country_code":"XK",
    "gn:dem":774,
    "gn:feature_class":"P",
    "gn:feature_code":"PPLL",
    "gn:name":"Zheg\u00ebr",
    "gn:population":0,
    "gn:timezone":"Europe/Belgrade",
    "iso:country":"XK",
    "name:sqi_x_preferred":[
        "Zheg\u00ebr"
    ],
    "name:sqi_x_variant":[
        "Zhegra"
    ],
    "name:srp_x_preferred":[
        "\u0416\u0435\u0433\u0440\u0430"
    ],
    "name:srp_x_variant":[
        "\u017degra"
    ],
    "wof:name":"Zheger",
    "wof:placetype":"locality"
},
  "geometry": {"coordinates":[21.51306,42.35389],"type":"Point"}
}