{
  "type": "Feature",
  "properties": {
    "gn:admin1_code":"10097357.0",
    "gn:admin2_code":"37.0",
    "gn:asciiname":"Stara Mahala",
    "gn:country_code":"XK",
    "gn:dem":727,
    "gn:feature_class":"P",
    "gn:feature_code":"PPL",
    "gn:name":"Stara Mahala",
    "gn:population":0,
    "gn:timezone":"Europe/Belgrade",
    "iso:country":"XK",
    "name:srp_x_preferred":[
        "Stara Mahala"
    ],
    "wof:name":"Stara Mahala",
    "wof:placetype":"locality"
},
  "geometry": {"coordinates":[21.54333,42.55028],"type":"Point"}
}