{
  "type": "Feature",
  "properties": {
    "gn:admin1_code":"10097359.0",
    "gn:admin2_code":"18.0",
    "gn:asciiname":"Dreshaj",
    "gn:country_code":"XK",
    "gn:dem":1464,
    "gn:feature_class":"P",
    "gn:feature_code":"PPL",
    "gn:name":"Dreshaj",
    "gn:population":0,
    "gn:timezone":"Europe/Belgrade",
    "iso:country":"XK",
    "wof:name":"Dreshaj",
    "wof:placetype":"locality"
},
  "geometry": {"coordinates":[20.06222,42.73361],"type":"Point"}
}