{
  "type": "Feature",
  "properties": {
    "gn:admin1_code":"10097359.0",
    "gn:admin2_code":"8.0",
    "gn:asciiname":"Novi Tucep",
    "gn:country_code":"XK",
    "gn:dem":558,
    "gn:feature_class":"P",
    "gn:feature_code":"PPL",
    "gn:name":"Novi Tu\u010dep",
    "gn:population":0,
    "gn:timezone":"Europe/Belgrade",
    "iso:country":"XK",
    "name:srp_x_preferred":[
        "Novi Tu\u010dep"
    ],
    "wof:name":"Novi Tucep",
    "wof:placetype":"locality"
},
  "geometry": {"coordinates":[20.58083,42.75611],"type":"Point"}
}