{
  "type": "Feature",
  "properties": {
    "gn:admin1_code":"10097359.0",
    "gn:admin2_code":"18.0",
    "gn:asciiname":"Kerstec",
    "gn:country_code":"XK",
    "gn:dem":433,
    "gn:feature_class":"P",
    "gn:feature_code":"PPL",
    "gn:name":"K\u00ebrstec",
    "gn:population":0,
    "gn:timezone":"Europe/Belgrade",
    "iso:country":"XK",
    "name:und_x_variant":[
        "K\u00ebrstovc"
    ],
    "wof:name":"Kerstec",
    "wof:placetype":"locality"
},
  "geometry": {"coordinates":[20.43694,42.6225],"type":"Point"}
}