{
  "type": "Feature",
  "properties": {
    "gn:admin1_code":"10097359.0",
    "gn:admin2_code":"11.0",
    "gn:asciiname":"Grabc",
    "gn:country_code":"XK",
    "gn:dem":539,
    "gn:feature_class":"P",
    "gn:feature_code":"PPL",
    "gn:name":"Grabc",
    "gn:population":0,
    "gn:timezone":"Europe/Belgrade",
    "iso:country":"XK",
    "name:sqi_x_preferred":[
        "Grabc"
    ],
    "name:sqi_x_variant":[
        "Bingj\u00eb",
        "Biq\u00eb"
    ],
    "name:srp_x_preferred":[
        "Grabac"
    ],
    "name:srp_x_variant":[
        "\u0413\u0440\u0430\u0431\u0430\u0446"
    ],
    "name:und_x_variant":[
        "Bingj\u00eb",
        "Grabos",
        "Biq\u00eb",
        "Grabosi",
        "Grabci"
    ],
    "wof:name":"Grabc",
    "wof:placetype":"locality"
},
  "geometry": {"coordinates":[20.61861,42.67806],"type":"Point"}
}