{
  "type": "Feature",
  "properties": {
    "gn:admin1_code":"10097358.0",
    "gn:admin2_code":"12.0",
    "gn:asciiname":"Voznik",
    "gn:country_code":"XK",
    "gn:dem":626,
    "gn:feature_class":"P",
    "gn:feature_code":"PPL",
    "gn:name":"Voznik",
    "gn:population":0,
    "gn:timezone":"Europe/Belgrade",
    "iso:country":"XK",
    "name:srp_x_preferred":[
        "Voznik"
    ],
    "name:und_x_variant":[
        "Ivanica"
    ],
    "wof:name":"Voznik",
    "wof:placetype":"locality"
},
  "geometry": {"coordinates":[20.78306,43.05639],"type":"Point"}
}