{
  "type": "Feature",
  "properties": {
    "gn:admin1_code":"10097357.0",
    "gn:admin2_code":"6.0",
    "gn:asciiname":"Mejir Mala",
    "gn:country_code":"XK",
    "gn:dem":606,
    "gn:feature_class":"P",
    "gn:feature_code":"PPL",
    "gn:name":"Mejir Mala",
    "gn:population":0,
    "gn:timezone":"Europe/Belgrade",
    "iso:country":"XK",
    "name:srp_x_preferred":[
        "Mejir Mala"
    ],
    "wof:name":"Mejir Mala",
    "wof:placetype":"locality"
},
  "geometry": {"coordinates":[21.40028,42.48056],"type":"Point"}
}