{
  "type": "Feature",
  "properties": {
    "gn:admin1_code":"10097361.0",
    "gn:admin2_code":"21.0",
    "gn:asciiname":"Gornja Mala",
    "gn:country_code":"XK",
    "gn:dem":1203,
    "gn:feature_class":"P",
    "gn:feature_code":"PPL",
    "gn:name":"Gornja Mala",
    "gn:population":0,
    "gn:timezone":"Europe/Belgrade",
    "iso:country":"XK",
    "name:fra_x_preferred":[
        "Kni\u0107"
    ],
    "name:ita_x_preferred":[
        "Kni\u0107"
    ],
    "name:nld_x_preferred":[
        "Kni\u0107"
    ],
    "name:srp_x_preferred":[
        "Gornja Mala"
    ],
    "name:srp_x_variant":[
        "Gornje Mali",
        "\u041a\u043d\u0438\u045b"
    ],
    "wof:name":"Gornja Mala",
    "wof:placetype":"locality"
},
  "geometry": {"coordinates":[20.93611,42.17278],"type":"Point"}
}