{
  "type": "Feature",
  "properties": {
    "gn:admin1_code":"10097361.0",
    "gn:admin2_code":"21.0",
    "gn:asciiname":"Karavidaj",
    "gn:country_code":"XK",
    "gn:dem":518,
    "gn:feature_class":"P",
    "gn:feature_code":"PPL",
    "gn:name":"Karavidaj",
    "gn:population":0,
    "gn:timezone":"Europe/Belgrade",
    "iso:country":"XK",
    "name:srp_x_preferred":[
        "Karavidaj"
    ],
    "wof:name":"Karavidaj",
    "wof:placetype":"locality"
},
  "geometry": {"coordinates":[20.61,42.23556],"type":"Point"}
}