{
  "type": "Feature",
  "properties": {
    "gn:admin1_code":"10097359.0",
    "gn:admin2_code":"8.0",
    "gn:asciiname":"Banjica",
    "gn:country_code":"XK",
    "gn:dem":488,
    "gn:feature_class":"P",
    "gn:feature_code":"PPL",
    "gn:name":"Banjica",
    "gn:population":0,
    "gn:timezone":"Europe/Belgrade",
    "iso:country":"XK",
    "name:ceb_x_preferred":[
        "Banjica"
    ],
    "name:ces_x_preferred":[
        "Banjica"
    ],
    "name:fra_x_preferred":[
        "Banjica"
    ],
    "name:pol_x_preferred":[
        "Banjica"
    ],
    "name:sqi_x_preferred":[
        "Banjic\u00eb"
    ],
    "name:sqi_x_variant":[
        "Llixh\u00eb e Pej\u00ebs",
        "Baic\u00eb",
        "Baj\u00ebz",
        "Baj\u00ebza"
    ],
    "name:srp_x_preferred":[
        "\u0411\u0430\u045a\u0438\u0446\u0430"
    ],
    "name:srp_x_variant":[
        "Banjica"
    ],
    "name:swe_x_preferred":[
        "Banjica"
    ],
    "name:und_x_variant":[
        "Baica"
    ],
    "wof:name":"Banjica",
    "wof:placetype":"locality"
},
  "geometry": {"coordinates":[20.38917,42.71667],"type":"Point"}
}