{
  "type": "Feature",
  "properties": {
    "gn:admin1_code":"10097359.0",
    "gn:admin2_code":"11.0",
    "gn:asciiname":"Duricic",
    "gn:country_code":"XK",
    "gn:dem":370,
    "gn:feature_class":"P",
    "gn:feature_code":"PPL",
    "gn:name":"\u00d0uri\u010di\u0107",
    "gn:population":0,
    "gn:timezone":"Europe/Belgrade",
    "iso:country":"XK",
    "name:srp_x_preferred":[
        "\u00d0uri\u010di\u0107"
    ],
    "wof:name":"Duricic",
    "wof:placetype":"locality"
},
  "geometry": {"coordinates":[20.56222,42.58139],"type":"Point"}
}