{
  "type": "Feature",
  "properties": {
    "gn:admin1_code":"10096138.0",
    "gn:admin2_code":"24.0",
    "gn:asciiname":"Rance",
    "gn:country_code":"XK",
    "gn:dem":921,
    "gn:feature_class":"P",
    "gn:feature_code":"PPL",
    "gn:name":"Rance",
    "gn:population":0,
    "gn:timezone":"Europe/Belgrade",
    "iso:country":"XK",
    "name:sqi_x_preferred":[
        "Ranc\u00eb"
    ],
    "name:sqi_x_variant":[
        "Rranc\u00eb"
    ],
    "name:srp_x_preferred":[
        "\u0420\u0430\u043d\u0446\u0435"
    ],
    "name:srp_x_variant":[
        "Rance"
    ],
    "name:und_x_variant":[
        "Ronce",
        "Rranc\u00eb",
        "Rorice"
    ],
    "wof:name":"Rance",
    "wof:placetype":"locality"
},
  "geometry": {"coordinates":[20.97056,42.43278],"type":"Point"}
}