{
  "type": "Feature",
  "properties": {
    "gn:admin1_code":"10097359.0",
    "gn:admin2_code":"18.0",
    "gn:asciiname":"Dobeljas",
    "gn:country_code":"XK",
    "gn:dem":459,
    "gn:feature_class":"P",
    "gn:feature_code":"PPL",
    "gn:name":"Dobelja\u0161",
    "gn:population":0,
    "gn:timezone":"Europe/Belgrade",
    "iso:country":"XK",
    "name:srp_x_preferred":[
        "Dobelja\u0161"
    ],
    "wof:name":"Dobeljas",
    "wof:placetype":"locality"
},
  "geometry": {"coordinates":[20.41694,42.64389],"type":"Point"}
}