{
  "type": "Feature",
  "properties": {
    "gn:admin1_code":"10097359.0",
    "gn:admin2_code":"18.0",
    "gn:asciiname":"Labljane",
    "gn:country_code":"XK",
    "gn:dem":461,
    "gn:feature_class":"P",
    "gn:feature_code":"PPL",
    "gn:name":"Labljane",
    "gn:population":0,
    "gn:timezone":"Europe/Belgrade",
    "iso:country":"XK",
    "name:srp_x_preferred":[
        "\u041b\u0430\u0431\u0459\u0430\u043d\u0435"
    ],
    "name:srp_x_variant":[
        "Labljane"
    ],
    "wof:name":"Labljane",
    "wof:placetype":"locality"
},
  "geometry": {"coordinates":[20.40694,42.65611],"type":"Point"}
}