{
  "type": "Feature",
  "properties": {
    "gn:admin1_code":"10097361.0",
    "gn:admin2_code":"21.0",
    "gn:asciiname":"Pousko",
    "gn:country_code":"XK",
    "gn:dem":504,
    "gn:feature_class":"P",
    "gn:feature_code":"PPL",
    "gn:name":"Pousko",
    "gn:population":0,
    "gn:timezone":"Europe/Belgrade",
    "iso:country":"XK",
    "name:und_x_variant":[
        "Topusko"
    ],
    "wof:name":"Pousko",
    "wof:placetype":"locality"
},
  "geometry": {"coordinates":[20.76141,42.2008],"type":"Point"}
}