{
  "type": "Feature",
  "properties": {
    "gn:admin1_code":"10097358.0",
    "gn:admin2_code":"12.0",
    "gn:asciiname":"Kosutica",
    "gn:country_code":"XK",
    "gn:dem":487,
    "gn:feature_class":"P",
    "gn:feature_code":"PPL",
    "gn:name":"Ko\u0161utica",
    "gn:population":0,
    "gn:timezone":"Europe/Belgrade",
    "iso:country":"XK",
    "name:sqi_x_preferred":[
        "Koshutic\u00eb"
    ],
    "name:sqi_x_variant":[
        "Koshutica"
    ],
    "name:srp_x_preferred":[
        "Ko\u0161utica"
    ],
    "name:srp_x_variant":[
        "\u041a\u043e\u0448\u0443\u0442\u0438\u0446\u0430"
    ],
    "wof:name":"Kosutica",
    "wof:placetype":"locality"
},
  "geometry": {"coordinates":[20.69,43.21111],"type":"Point"}
}