{
  "type": "Feature",
  "properties": {
    "gn:admin1_code":"10096859.0",
    "gn:admin2_code":"5.0",
    "gn:asciiname":"Cerim",
    "gn:country_code":"XK",
    "gn:dem":392,
    "gn:feature_class":"P",
    "gn:feature_code":"PPL",
    "gn:name":"\u00c7erim",
    "gn:population":0,
    "gn:timezone":"Europe/Belgrade",
    "iso:country":"XK",
    "name:srp_x_preferred":[
        "\u040b\u0435\u0440\u0438\u043c"
    ],
    "name:srp_x_variant":[
        "\u0106erim"
    ],
    "name:und_x_variant":[
        "Qerim"
    ],
    "wof:name":"Cerim",
    "wof:placetype":"locality"
},
  "geometry": {"coordinates":[20.43583,42.40583],"type":"Point"}
}