{
  "type": "Feature",
  "properties": {
    "gn:admin1_code":"10097360.0",
    "gn:admin2_code":"31.0",
    "gn:asciiname":"Gornja Gusterica",
    "gn:country_code":"XK",
    "gn:dem":605,
    "gn:feature_class":"P",
    "gn:feature_code":"PPL",
    "gn:name":"Gornja Gu\u0161terica",
    "gn:population":0,
    "gn:timezone":"Europe/Belgrade",
    "iso:country":"XK",
    "name:sqi_x_preferred":[
        "Gushteric\u00eb e Ep\u00ebrme"
    ],
    "name:sqi_x_variant":[
        "Shapc i Ep\u00ebrm"
    ],
    "name:srp_x_preferred":[
        "\u0413\u043e\u0440\u045a\u0430 \u0413\u0443\u0448\u0442\u0435\u0440\u0438\u0446\u0430"
    ],
    "name:srp_x_variant":[
        "Gornja Gu\u0161terica"
    ],
    "wof:name":"Gornja Gusterica",
    "wof:placetype":"locality"
},
  "geometry": {"coordinates":[21.20861,42.55111],"type":"Point"}
}