{
  "type": "Feature",
  "properties": {
    "gn:admin1_code":"10097358.0",
    "gn:admin2_code":"25.0",
    "gn:asciiname":"Kosutan Mahala",
    "gn:country_code":"XK",
    "gn:dem":742,
    "gn:feature_class":"P",
    "gn:feature_code":"PPL",
    "gn:name":"Ko\u0161utan Mahala",
    "gn:population":0,
    "gn:timezone":"Europe/Belgrade",
    "iso:country":"XK",
    "name:srp_x_preferred":[
        "Ko\u0161utan Mahala"
    ],
    "wof:name":"Kosutan Mahala",
    "wof:placetype":"locality"
},
  "geometry": {"coordinates":[20.74833,42.77833],"type":"Point"}
}