{
  "type": "Feature",
  "properties": {
    "gn:admin1_code":"10097361.0",
    "gn:admin2_code":"26.0",
    "gn:asciiname":"Tafoli Mahala",
    "gn:country_code":"XK",
    "gn:dem":795,
    "gn:feature_class":"P",
    "gn:feature_code":"PPL",
    "gn:name":"Tafoli Mahala",
    "gn:population":0,
    "gn:timezone":"Europe/Belgrade",
    "iso:country":"XK",
    "name:srp_x_preferred":[
        "Tafoli Mahala"
    ],
    "wof:name":"Tafoli Mahala",
    "wof:placetype":"locality"
},
  "geometry": {"coordinates":[20.92083,42.40639],"type":"Point"}
}