{
  "type": "Feature",
  "properties": {
    "gn:admin1_code":"10097360.0",
    "gn:admin2_code":"20.0",
    "gn:asciiname":"Slivovo",
    "gn:country_code":"XK",
    "gn:dem":839,
    "gn:feature_class":"P",
    "gn:feature_code":"PPL",
    "gn:name":"Slivovo",
    "gn:population":0,
    "gn:timezone":"Europe/Belgrade",
    "iso:country":"XK",
    "name:deu_x_preferred":[
        "Slivova"
    ],
    "name:nds_x_preferred":[
        "Slivova"
    ],
    "name:pol_x_preferred":[
        "Sliwowo"
    ],
    "name:rus_x_preferred":[
        "\u0421\u043b\u0438\u0432\u043e\u0432\u043e"
    ],
    "name:sqi_x_preferred":[
        "Slivov\u00eb"
    ],
    "name:srp_x_preferred":[
        "Slivovo"
    ],
    "name:srp_x_variant":[
        "\u0421\u043b\u0438\u0432\u043e\u0432\u043e"
    ],
    "name:ukr_x_preferred":[
        "\u0421\u043b\u0438\u0432\u043e\u0432\u043e"
    ],
    "wof:name":"Slivovo",
    "wof:placetype":"locality"
},
  "geometry": {"coordinates":[21.33444,42.62278],"type":"Point"}
}