{
  "type": "Feature",
  "properties": {
    "gn:admin1_code":"10097358.0",
    "gn:admin2_code":"12.0",
    "gn:asciiname":"Jezerine",
    "gn:country_code":"XK",
    "gn:dem":635,
    "gn:feature_class":"P",
    "gn:feature_code":"PPL",
    "gn:name":"Jezerine",
    "gn:population":0,
    "gn:timezone":"Europe/Belgrade",
    "iso:country":"XK",
    "name:srp_x_preferred":[
        "Jezerine"
    ],
    "wof:name":"Jezerine",
    "wof:placetype":"locality"
},
  "geometry": {"coordinates":[20.73917,43.14917],"type":"Point"}
}