{
  "type": "Feature",
  "properties": {
    "gn:admin1_code":"10097359.0",
    "gn:admin2_code":"18.0",
    "gn:asciiname":"Lulaj",
    "gn:country_code":"XK",
    "gn:dem":1425,
    "gn:feature_class":"P",
    "gn:feature_code":"PPL",
    "gn:name":"Lulaj",
    "gn:population":0,
    "gn:timezone":"Europe/Belgrade",
    "iso:country":"XK",
    "wof:name":"Lulaj",
    "wof:placetype":"locality"
},
  "geometry": {"coordinates":[20.03917,42.71524],"type":"Point"}
}