{
  "type": "Feature",
  "properties": {
    "gn:admin1_code":"10096138.0",
    "gn:admin2_code":"9.0",
    "gn:asciiname":"Kotlina",
    "gn:country_code":"XK",
    "gn:dem":816,
    "gn:feature_class":"P",
    "gn:feature_code":"PPLL",
    "gn:name":"Kotlina",
    "gn:population":0,
    "gn:timezone":"Europe/Belgrade",
    "iso:country":"XK",
    "name:sqi_x_preferred":[
        "Kotlin\u00eb"
    ],
    "name:srp_x_preferred":[
        "\u041a\u043e\u0442\u043b\u0438\u043d\u0430"
    ],
    "name:srp_x_variant":[
        "Kotlina"
    ],
    "name:swe_x_preferred":[
        "Kotlina"
    ],
    "wof:name":"Kotlina",
    "wof:placetype":"locality"
},
  "geometry": {"coordinates":[21.23083,42.17611],"type":"Point"}
}