{
  "type": "Feature",
  "properties": {
    "gn:admin1_code":"10097358.0",
    "gn:admin2_code":"28.0",
    "gn:asciiname":"Zenic Mahala",
    "gn:country_code":"XK",
    "gn:dem":555,
    "gn:feature_class":"P",
    "gn:feature_code":"PPL",
    "gn:name":"Zeni\u0107 Mahala",
    "gn:population":0,
    "gn:timezone":"Europe/Belgrade",
    "iso:country":"XK",
    "name:srp_x_preferred":[
        "Zeni\u0107 Mahala"
    ],
    "wof:name":"Zenic Mahala",
    "wof:placetype":"locality"
},
  "geometry": {"coordinates":[21.03028,42.77361],"type":"Point"}
}