{
  "type": "Feature",
  "properties": {
    "gn:admin1_code":"10096138.0",
    "gn:admin2_code":"3.0",
    "gn:asciiname":"Musovic-Mahala",
    "gn:country_code":"XK",
    "gn:dem":556,
    "gn:feature_class":"P",
    "gn:feature_code":"PPL",
    "gn:name":"Musovi\u0107-Mahala",
    "gn:population":0,
    "gn:timezone":"Europe/Belgrade",
    "iso:country":"XK",
    "name:srp_x_preferred":[
        "Musovi\u0107-Mahala"
    ],
    "name:und_x_variant":[
        "Manastirce"
    ],
    "wof:name":"Musovic-Mahala",
    "wof:placetype":"locality"
},
  "geometry": {"coordinates":[21.16111,42.34556],"type":"Point"}
}