{
  "type": "Feature",
  "properties": {
    "gn:admin1_code":"10097361.0",
    "gn:admin2_code":"26.0",
    "gn:asciiname":"Grekovce",
    "gn:country_code":"XK",
    "gn:dem":579,
    "gn:feature_class":"P",
    "gn:feature_code":"PPL",
    "gn:name":"Grekovce",
    "gn:population":0,
    "gn:timezone":"Europe/Belgrade",
    "iso:country":"XK",
    "wof:name":"Grekovce",
    "wof:placetype":"locality"
},
  "geometry": {"coordinates":[20.82639,42.27861],"type":"Point"}
}