{
  "type": "Feature",
  "properties": {
    "gn:admin1_code":"10097360.0",
    "gn:admin2_code":"16.0",
    "gn:asciiname":"Muhadzeri",
    "gn:country_code":"XK",
    "gn:dem":867,
    "gn:feature_class":"P",
    "gn:feature_code":"PPL",
    "gn:name":"Muhad\u017eeri",
    "gn:population":0,
    "gn:timezone":"Europe/Belgrade",
    "iso:country":"XK",
    "name:srp_x_preferred":[
        "Muhad\u017eeri"
    ],
    "name:und_x_variant":[
        "Muhagjer"
    ],
    "wof:name":"Muhadzeri",
    "wof:placetype":"locality"
},
  "geometry": {"coordinates":[21.36278,42.59444000000001],"type":"Point"}
}