{
  "type": "Feature",
  "properties": {
    "gn:admin1_code":"10097358.0",
    "gn:admin2_code":"30.0",
    "gn:asciiname":"Kadijaca Han Kadijaca",
    "gn:country_code":"XK",
    "gn:dem":969,
    "gn:feature_class":"P",
    "gn:feature_code":"PPL",
    "gn:name":"Kadija\u010da Han Kadija\u010da",
    "gn:population":0,
    "gn:timezone":"Europe/Belgrade",
    "iso:country":"XK",
    "name:srp_x_preferred":[
        "Kadija\u010da Han Kadija\u010da"
    ],
    "wof:name":"Kadijaca Han Kadijaca",
    "wof:placetype":"locality"
},
  "geometry": {"coordinates":[20.75583,43.00944000000001],"type":"Point"}
}