{
  "type": "Feature",
  "properties": {
    "gn:admin1_code":"10097360.0",
    "gn:admin2_code":"16.0",
    "gn:asciiname":"Zabeljce",
    "gn:country_code":"XK",
    "gn:dem":820,
    "gn:feature_class":"P",
    "gn:feature_code":"PPL",
    "gn:name":"Zabeljce",
    "gn:population":0,
    "gn:timezone":"Europe/Belgrade",
    "iso:country":"XK",
    "name:srp_x_preferred":[
        "Zabeljce"
    ],
    "wof:name":"Zabeljce",
    "wof:placetype":"locality"
},
  "geometry": {"coordinates":[21.39583,42.58556],"type":"Point"}
}