{
  "type": "Feature",
  "properties": {
    "gn:admin1_code":"10097359.0",
    "gn:admin2_code":"18.0",
    "gn:asciiname":"Tamnik",
    "gn:country_code":"XK",
    "gn:dem":422,
    "gn:feature_class":"P",
    "gn:feature_code":"PPL",
    "gn:name":"Tamnik",
    "gn:population":0,
    "gn:timezone":"Europe/Belgrade",
    "iso:country":"XK",
    "name:srp_x_preferred":[
        "Tamnik"
    ],
    "wof:name":"Tamnik",
    "wof:placetype":"locality"
},
  "geometry": {"coordinates":[20.475,42.57583],"type":"Point"}
}