{
  "type": "Feature",
  "properties": {
    "gn:admin1_code":"10096859.0",
    "gn:admin2_code":"1.0",
    "gn:asciiname":"Letovaciste",
    "gn:country_code":"XK",
    "gn:dem":704,
    "gn:feature_class":"P",
    "gn:feature_code":"PPL",
    "gn:name":"Letova\u010di\u0161te",
    "gn:population":0,
    "gn:timezone":"Europe/Belgrade",
    "iso:country":"XK",
    "name:sqi_x_preferred":[
        "Pushimore"
    ],
    "name:srp_x_preferred":[
        "Letova\u010di\u0161te"
    ],
    "name:und_x_variant":[
        "Pushimore",
        "Letovaliste"
    ],
    "wof:name":"Letovaciste",
    "wof:placetype":"locality"
},
  "geometry": {"coordinates":[20.2675,42.54472],"type":"Point"}
}