{
  "type": "Feature",
  "properties": {
    "gn:admin1_code":"10097361.0",
    "gn:admin2_code":"26.0",
    "gn:asciiname":"Gornja Krusica",
    "gn:country_code":"XK",
    "gn:dem":985,
    "gn:feature_class":"P",
    "gn:feature_code":"PPL",
    "gn:name":"Gornja Kru\u0161ica",
    "gn:population":0,
    "gn:timezone":"Europe/Belgrade",
    "iso:country":"XK",
    "name:sqi_x_preferred":[
        "Krushic\u00eb e Ep\u00ebrme"
    ],
    "name:sqi_x_variant":[
        "Krushica e Ep\u00ebrme",
        "Kryshic\u00eb",
        "Krushica"
    ],
    "name:srp_x_preferred":[
        "\u0413\u043e\u0440\u045a\u0430 \u041a\u0440\u0443\u0448\u0438\u0446\u0430"
    ],
    "name:srp_x_variant":[
        "Gornja Kru\u0161ica",
        "Kru\u0161ica"
    ],
    "name:und_x_variant":[
        "Kryshic\u00eb",
        "Kru\u0161ica",
        "Krushica",
        "Krushica e Ep\u00ebrme"
    ],
    "wof:name":"Gornja Krusica",
    "wof:placetype":"locality"
},
  "geometry": {"coordinates":[20.935,42.36361],"type":"Point"}
}