{
  "type": "Feature",
  "properties": {
    "gn:admin1_code":"10097360.0",
    "gn:admin2_code":"16.0",
    "gn:asciiname":"Mirkovci",
    "gn:country_code":"XK",
    "gn:dem":822,
    "gn:feature_class":"P",
    "gn:feature_code":"PPL",
    "gn:name":"Mirkovci",
    "gn:population":0,
    "gn:timezone":"Europe/Belgrade",
    "iso:country":"XK",
    "name:srp_x_preferred":[
        "Mirkovci"
    ],
    "wof:name":"Mirkovci",
    "wof:placetype":"locality"
},
  "geometry": {"coordinates":[21.39045,42.60444],"type":"Point"}
}