{
  "type": "Feature",
  "properties": {
    "gn:admin1_code":"10097358.0",
    "gn:admin2_code":"15.0",
    "gn:asciiname":"Ukovic Mahala",
    "gn:country_code":"XK",
    "gn:dem":1314,
    "gn:feature_class":"P",
    "gn:feature_code":"PPL",
    "gn:name":"Ukovi\u0107 Mahala",
    "gn:population":0,
    "gn:timezone":"Europe/Belgrade",
    "iso:country":"XK",
    "name:srp_x_preferred":[
        "Ukovi\u0107 Mahala"
    ],
    "wof:name":"Ukovic Mahala",
    "wof:placetype":"locality"
},
  "geometry": {"coordinates":[21.00392,42.96924],"type":"Point"}
}