{
  "type": "Feature",
  "properties": {
    "gn:admin1_code":"10097357.0",
    "gn:admin2_code":"10.0",
    "gn:asciiname":"Pireva",
    "gn:country_code":"XK",
    "gn:dem":804,
    "gn:feature_class":"P",
    "gn:feature_code":"PPL",
    "gn:name":"Pireva",
    "gn:population":0,
    "gn:timezone":"Europe/Belgrade",
    "iso:country":"XK",
    "name:srp_x_preferred":[
        "Pireva"
    ],
    "name:srp_x_variant":[
        "Mahala Pirevo"
    ],
    "wof:name":"Pireva",
    "wof:placetype":"locality"
},
  "geometry": {"coordinates":[21.55111,42.6725],"type":"Point"}
}