{
  "type": "Feature",
  "properties": {
    "gn:admin1_code":"10097360.0",
    "gn:admin2_code":"19.0",
    "gn:asciiname":"Orlane",
    "gn:country_code":"XK",
    "gn:dem":640,
    "gn:feature_class":"P",
    "gn:feature_code":"PPL",
    "gn:name":"Orlane",
    "gn:population":0,
    "gn:timezone":"Europe/Belgrade",
    "iso:country":"XK",
    "name:sqi_x_preferred":[
        "Orllan"
    ],
    "name:sqi_x_variant":[
        "Orllani",
        "Gallab",
        "Gallabi"
    ],
    "name:srp_x_preferred":[
        "\u041e\u0440\u043b\u0430\u043d\u0435"
    ],
    "name:srp_x_variant":[
        "Orlane"
    ],
    "name:und_x_variant":[
        "Orljane",
        "Orljani"
    ],
    "wof:name":"Orlane",
    "wof:placetype":"locality"
},
  "geometry": {"coordinates":[21.34333,42.81778],"type":"Point"}
}