{
  "type": "Feature",
  "properties": {
    "gn:admin1_code":"10097361.0",
    "gn:admin2_code":"14.0",
    "gn:asciiname":"Magare",
    "gn:country_code":"XK",
    "gn:dem":566,
    "gn:feature_class":"P",
    "gn:feature_code":"PPL",
    "gn:name":"Ma\u0111are",
    "gn:population":0,
    "gn:timezone":"Europe/Belgrade",
    "iso:country":"XK",
    "name:sqi_x_preferred":[
        "Madajr\u00eb"
    ],
    "name:sqi_x_variant":[
        "Maxhar\u00eb",
        "Maxhar",
        "Maxharre"
    ],
    "name:srp_x_preferred":[
        "Ma\u0111are"
    ],
    "name:srp_x_variant":[
        "\u041c\u0430\u0452\u0430\u0440\u0435"
    ],
    "name:und_x_variant":[
        "Maxhar",
        "Maxharre"
    ],
    "wof:name":"Magare",
    "wof:placetype":"locality"
},
  "geometry": {"coordinates":[20.71889,42.44778],"type":"Point"}
}