{
  "type": "Feature",
  "properties": {
    "gn:admin1_code":"10097358.0",
    "gn:admin2_code":"28.0",
    "gn:asciiname":"Grace",
    "gn:country_code":"XK",
    "gn:dem":561,
    "gn:feature_class":"P",
    "gn:feature_code":"PPL",
    "gn:name":"Grace",
    "gn:population":0,
    "gn:timezone":"Europe/Belgrade",
    "iso:country":"XK",
    "name:sqi_x_preferred":[
        "Grac\u00eb"
    ],
    "name:sqi_x_variant":[
        "Grec\u00eb"
    ],
    "name:srp_x_preferred":[
        "Grace"
    ],
    "name:srp_x_variant":[
        "\u0413\u0440\u0430\u0446\u0435"
    ],
    "name:und_x_variant":[
        "Grec\u00eb"
    ],
    "wof:name":"Grace",
    "wof:placetype":"locality"
},
  "geometry": {"coordinates":[21.05883,42.74553],"type":"Point"}
}