{
  "type": "Feature",
  "properties": {
    "gn:admin1_code":"10097360.0",
    "gn:admin2_code":"7.0",
    "gn:asciiname":"Vasiljevo",
    "gn:country_code":"XK",
    "gn:dem":645,
    "gn:feature_class":"P",
    "gn:feature_code":"PPL",
    "gn:name":"Vasiljevo",
    "gn:population":0,
    "gn:timezone":"Europe/Belgrade",
    "iso:country":"XK",
    "name:sqi_x_preferred":[
        "Vasilev\u00eb"
    ],
    "name:sqi_x_variant":[
        "Blerimi"
    ],
    "name:srp_x_preferred":[
        "\u0412\u0430\u0441\u0438\u0459\u0435\u0432\u043e"
    ],
    "name:srp_x_variant":[
        "Vasiljevo"
    ],
    "name:und_x_variant":[
        "Blerimi",
        "Vasilev\u00eb",
        "Blerim",
        "Vasileva"
    ],
    "wof:name":"Vasiljevo",
    "wof:placetype":"locality"
},
  "geometry": {"coordinates":[20.93639,42.63111],"type":"Point"}
}