{
  "type": "Feature",
  "properties": {
    "gn:admin1_code":"10097358.0",
    "gn:admin2_code":"29.0",
    "gn:asciiname":"Basca",
    "gn:country_code":"XK",
    "gn:dem":949,
    "gn:feature_class":"P",
    "gn:feature_code":"PPL",
    "gn:name":"Ba\u0161\u0107a",
    "gn:population":0,
    "gn:timezone":"Europe/Belgrade",
    "iso:country":"XK",
    "name:srp_x_preferred":[
        "Ba\u0161\u0107a"
    ],
    "wof:name":"Basca",
    "wof:placetype":"locality"
},
  "geometry": {"coordinates":[20.54944,42.94417],"type":"Point"}
}