{
  "type": "Feature",
  "properties": {
    "gn:admin1_code":"10097360.0",
    "gn:admin2_code":"20.0",
    "gn:asciiname":"Murtovic Mahala",
    "gn:country_code":"XK",
    "gn:dem":827,
    "gn:feature_class":"P",
    "gn:feature_code":"PPL",
    "gn:name":"Murtovi\u0107 Mahala",
    "gn:population":0,
    "gn:timezone":"Europe/Belgrade",
    "iso:country":"XK",
    "name:srp_x_preferred":[
        "Murtovi\u0107 Mahala"
    ],
    "name:und_x_variant":[
        "Nezirovic"
    ],
    "wof:name":"Murtovic Mahala",
    "wof:placetype":"locality"
},
  "geometry": {"coordinates":[21.31472,42.65611],"type":"Point"}
}