{
  "type": "Feature",
  "properties": {
    "gn:admin1_code":"10096138.0",
    "gn:admin2_code":"23.0",
    "gn:asciiname":"Sevc",
    "gn:country_code":"XK",
    "gn:dem":1002,
    "gn:feature_class":"P",
    "gn:feature_code":"PPL",
    "gn:name":"Sevc",
    "gn:population":0,
    "gn:timezone":"Europe/Belgrade",
    "iso:country":"XK",
    "name:fra_x_preferred":[
        "Sevce"
    ],
    "name:sqi_x_preferred":[
        "Sevc\u00eb"
    ],
    "name:sqi_x_variant":[
        "Sevc",
        "Sevca"
    ],
    "name:srp_x_preferred":[
        "Sevce"
    ],
    "name:srp_x_variant":[
        "\u0421\u0435\u0432\u0446\u0435"
    ],
    "name:und_x_variant":[
        "Sjevce"
    ],
    "wof:name":"Sevc",
    "wof:placetype":"locality"
},
  "geometry": {"coordinates":[20.95667000000001,42.20972],"type":"Point"}
}