{
  "type": "Feature",
  "properties": {
    "gn:admin1_code":"10096138.0",
    "gn:admin2_code":"23.0",
    "gn:asciiname":"Mark Mahala",
    "gn:country_code":"XK",
    "gn:dem":844,
    "gn:feature_class":"P",
    "gn:feature_code":"PPL",
    "gn:name":"Mark Mahala",
    "gn:population":0,
    "gn:timezone":"Europe/Belgrade",
    "iso:country":"XK",
    "name:srp_x_preferred":[
        "Mark Mahala"
    ],
    "wof:name":"Mark Mahala",
    "wof:placetype":"locality"
},
  "geometry": {"coordinates":[21.11139,42.25639],"type":"Point"}
}