{
  "type": "Feature",
  "properties": {
    "gn:admin1_code":"10097359.0",
    "gn:admin2_code":"18.0",
    "gn:asciiname":"Vragoc",
    "gn:country_code":"XK",
    "gn:dem":447,
    "gn:feature_class":"P",
    "gn:feature_code":"PPL",
    "gn:name":"Vragoc",
    "gn:population":0,
    "gn:timezone":"Europe/Belgrade",
    "iso:country":"XK",
    "name:sqi_x_preferred":[
        "Vragoc"
    ],
    "name:sqi_x_variant":[
        "Vragovc"
    ],
    "name:und_x_variant":[
        "Vragovac",
        "Vraovc"
    ],
    "wof:name":"Vragoc",
    "wof:placetype":"locality"
},
  "geometry": {"coordinates":[20.41278,42.62917],"type":"Point"}
}