{
  "type": "Feature",
  "properties": {
    "gn:admin1_code":"10097358.0",
    "gn:admin2_code":"25.0",
    "gn:asciiname":"Dragaj",
    "gn:country_code":"XK",
    "gn:dem":694,
    "gn:feature_class":"P",
    "gn:feature_code":"PPL",
    "gn:name":"Dragaj",
    "gn:population":0,
    "gn:timezone":"Europe/Belgrade",
    "iso:country":"XK",
    "name:srp_x_preferred":[
        "Dragaj"
    ],
    "wof:name":"Dragaj",
    "wof:placetype":"locality"
},
  "geometry": {"coordinates":[20.66417,42.76278],"type":"Point"}
}