{
  "type": "Feature",
  "properties": {
    "gn:admin1_code":"10097361.0",
    "gn:admin2_code":"14.0",
    "gn:asciiname":"Minol",
    "gn:country_code":"XK",
    "gn:dem":549,
    "gn:feature_class":"P",
    "gn:feature_code":"PPL",
    "gn:name":"Minol",
    "gn:population":0,
    "gn:timezone":"Europe/Belgrade",
    "iso:country":"XK",
    "name:deu_x_preferred":[
        "Minol"
    ],
    "name:srp_x_preferred":[
        "\u041c\u0438\u043d\u043e\u043b"
    ],
    "name:srp_x_variant":[
        "Minol"
    ],
    "wof:name":"Minol",
    "wof:placetype":"locality"
},
  "geometry": {"coordinates":[20.74056,42.48833],"type":"Point"}
}