{
  "type": "Feature",
  "properties": {
    "gn:admin1_code":"10097358.0",
    "gn:admin2_code":"12.0",
    "gn:asciiname":"Mijalovici",
    "gn:country_code":"XK",
    "gn:dem":699,
    "gn:feature_class":"P",
    "gn:feature_code":"PPL",
    "gn:name":"Mijalovi\u0107i",
    "gn:population":0,
    "gn:timezone":"Europe/Belgrade",
    "iso:country":"XK",
    "name:srp_x_preferred":[
        "Mijalovi\u0107i"
    ],
    "wof:name":"Mijalovici",
    "wof:placetype":"locality"
},
  "geometry": {"coordinates":[20.7275,43.20583],"type":"Point"}
}