{
  "type": "Feature",
  "properties": {
    "gn:admin1_code":"10097360.0",
    "gn:admin2_code":"7.0",
    "gn:asciiname":"Novi Poklek",
    "gn:country_code":"XK",
    "gn:dem":591,
    "gn:feature_class":"P",
    "gn:feature_code":"PPL",
    "gn:name":"Novi Poklek",
    "gn:population":0,
    "gn:timezone":"Europe/Belgrade",
    "iso:country":"XK",
    "name:srp_x_preferred":[
        "Novi Poklek"
    ],
    "wof:name":"Novi Poklek",
    "wof:placetype":"locality"
},
  "geometry": {"coordinates":[20.90361,42.61056],"type":"Point"}
}