{
  "type": "Feature",
  "properties": {
    "gn:admin1_code":"10097360.0",
    "gn:admin2_code":"19.0",
    "gn:asciiname":"Metohija",
    "gn:country_code":"XK",
    "gn:dem":719,
    "gn:feature_class":"P",
    "gn:feature_code":"PPL",
    "gn:name":"Metohija",
    "gn:population":0,
    "gn:timezone":"Europe/Belgrade",
    "iso:country":"XK",
    "name:bel_x_preferred":[
        "\u041c\u0435\u0442\u043e\u0445\u0456\u044f"
    ],
    "name:bul_x_preferred":[
        "\u041c\u0435\u0442\u043e\u0445\u0438\u044f"
    ],
    "name:cat_x_preferred":[
        "Met\u00f2khia"
    ],
    "name:ces_x_preferred":[
        "Metochie"
    ],
    "name:deu_x_preferred":[
        "Metochien"
    ],
    "name:ell_x_preferred":[
        "\u039c\u03b5\u03c4\u03cc\u03c7\u03b9\u03b1"
    ],
    "name:eus_x_preferred":[
        "Metohia"
    ],
    "name:fin_x_preferred":[
        "Metohija"
    ],
    "name:fra_x_preferred":[
        "M\u00e9tochie"
    ],
    "name:hrv_x_preferred":[
        "Metohija"
    ],
    "name:ind_x_preferred":[
        "Metohija"
    ],
    "name:ita_x_preferred":[
        "Metochia"
    ],
    "name:jpn_x_preferred":[
        "\u30e1\u30c8\u30d2\u30e4"
    ],
    "name:kor_x_preferred":[
        "\uba54\ud1a0\ud788\uc57c"
    ],
    "name:lit_x_preferred":[
        "Metohija"
    ],
    "name:mkd_x_preferred":[
        "\u041c\u0435\u0442\u043e\u0445\u0438\u0458\u0430"
    ],
    "name:nor_x_preferred":[
        "Metohija"
    ],
    "name:pol_x_preferred":[
        "Kosowo#Metochia"
    ],
    "name:por_x_preferred":[
        "Metohija"
    ],
    "name:ron_x_preferred":[
        "Metohia"
    ],
    "name:rus_x_preferred":[
        "\u041c\u0435\u0442\u043e\u0445\u0438\u044f"
    ],
    "name:spa_x_preferred":[
        "Metojia"
    ],
    "name:sqi_x_preferred":[
        "Metohi"
    ],
    "name:srp_x_preferred":[
        "\u041c\u0435\u0442\u043e\u0445\u0438\u0458\u0430"
    ],
    "name:srp_x_variant":[
        "Metohija"
    ],
    "name:swe_x_preferred":[
        "Metohija"
    ],
    "name:ukr_x_preferred":[
        "\u041c\u0435\u0442\u043e\u0445\u0456\u044f"
    ],
    "name:und_x_variant":[
        "Metehia",
        "Metehi"
    ],
    "name:zho_x_preferred":[
        "\u6885\u6258\u5e0c\u4e9a"
    ],
    "wof:name":"Metohija",
    "wof:placetype":"locality"
},
  "geometry": {"coordinates":[21.14833,43.01389],"type":"Point"}
}