{
  "type": "Feature",
  "properties": {
    "gn:admin1_code":"10097360.0",
    "gn:admin2_code":"19.0",
    "gn:asciiname":"Metohija",
    "gn:country_code":"XK",
    "gn:dem":719,
    "gn:feature_class":"P",
    "gn:feature_code":"PPL",
    "gn:name":"Metohija",
    "gn:population":0,
    "gn:timezone":"Europe/Belgrade",
    "iso:country":"XK",
    "name:sqi_x_preferred":[
        "Metohi"
    ],
    "name:srp_x_preferred":[
        "\u041c\u0435\u0442\u043e\u0445\u0438\u0458\u0430"
    ],
    "name:srp_x_variant":[
        "Metohija"
    ],
    "name:und_x_variant":[
        "Metohi",
        "Metehia",
        "Metehi"
    ],
    "wof:name":"Metohija",
    "wof:placetype":"locality"
},
  "geometry": {"coordinates":[21.14833,43.01389],"type":"Point"}
}