{
  "type": "Feature",
  "properties": {
    "gn:admin1_code":"10097359.0",
    "gn:admin2_code":"11.0",
    "gn:asciiname":"Starica",
    "gn:country_code":"XK",
    "gn:dem":451,
    "gn:feature_class":"P",
    "gn:feature_code":"PPL",
    "gn:name":"\u0160tarica",
    "gn:population":0,
    "gn:timezone":"Europe/Belgrade",
    "iso:country":"XK",
    "name:srp_x_preferred":[
        "\u0160tarica"
    ],
    "wof:name":"Starica",
    "wof:placetype":"locality"
},
  "geometry": {"coordinates":[20.68361,42.62389],"type":"Point"}
}