{
  "type": "Feature",
  "properties": {
    "gn:admin1_code":"10097359.0",
    "gn:admin2_code":"8.0",
    "gn:asciiname":"Zvecan",
    "gn:country_code":"XK",
    "gn:dem":460,
    "gn:feature_class":"P",
    "gn:feature_code":"PPL",
    "gn:name":"Zve\u010dan",
    "gn:population":0,
    "gn:timezone":"Europe/Belgrade",
    "iso:country":"XK",
    "name:srp_x_preferred":[
        "Zve\u010dan"
    ],
    "wof:name":"Zvecan",
    "wof:placetype":"locality"
},
  "geometry": {"coordinates":[20.55028,42.72333],"type":"Point"}
}