{
  "type": "Feature",
  "properties": {
    "gn:admin1_code":"10097357.0",
    "gn:admin2_code":"6.0",
    "gn:asciiname":"Jusufovce-Mahala",
    "gn:country_code":"XK",
    "gn:dem":554,
    "gn:feature_class":"P",
    "gn:feature_code":"PPL",
    "gn:name":"Jusufovce-Mahala",
    "gn:population":0,
    "gn:timezone":"Europe/Belgrade",
    "iso:country":"XK",
    "name:srp_x_preferred":[
        "Jusufovce-Mahala"
    ],
    "wof:name":"Jusufovce-Mahala",
    "wof:placetype":"locality"
},
  "geometry": {"coordinates":[21.5175,42.33139],"type":"Point"}
}