{
  "type": "Feature",
  "properties": {
    "gn:admin1_code":"10097359.0",
    "gn:admin2_code":"18.0",
    "gn:asciiname":"Zllapek",
    "gn:country_code":"XK",
    "gn:dem":479,
    "gn:feature_class":"P",
    "gn:feature_code":"PPLL",
    "gn:name":"Zllapek",
    "gn:population":0,
    "gn:timezone":"Europe/Belgrade",
    "iso:country":"XK",
    "name:sqi_x_preferred":[
        "Zllapek"
    ],
    "name:sqi_x_variant":[
        "Zllopek",
        "Qellopek",
        "Zallpeku",
        "Zllapeku"
    ],
    "name:und_x_variant":[
        "Qellopek",
        "Zllopek",
        "Zllapek",
        "Zllapeku",
        "Zallpeku"
    ],
    "wof:name":"Zllapek",
    "wof:placetype":"locality"
},
  "geometry": {"coordinates":[20.34833,42.6125],"type":"Point"}
}