{
  "type": "Feature",
  "properties": {
    "gn:admin1_code":"10096859.0",
    "gn:admin2_code":"1.0",
    "gn:asciiname":"Babaloc",
    "gn:country_code":"XK",
    "gn:dem":488,
    "gn:feature_class":"P",
    "gn:feature_code":"PPL",
    "gn:name":"Babalo\u00e7",
    "gn:population":0,
    "gn:timezone":"Europe/Belgrade",
    "iso:country":"XK",
    "name:sqi_x_preferred":[
        "Baballoq"
    ],
    "name:srp_x_preferred":[
        "Babalo\u0107"
    ],
    "name:srp_x_variant":[
        "\u0411\u0430\u0431\u0430\u043b\u043e\u045b"
    ],
    "name:und_x_variant":[
        "Babajlo\u0107",
        "Babaj-La\u00e7"
    ],
    "wof:name":"Babaloc",
    "wof:placetype":"locality"
},
  "geometry": {"coordinates":[20.34889,42.48611],"type":"Point"}
}