{
  "type": "Feature",
  "properties": {
    "gn:admin1_code":"10096859.0",
    "gn:admin2_code":"5.0",
    "gn:asciiname":"Janosh",
    "gn:country_code":"XK",
    "gn:dem":427,
    "gn:feature_class":"P",
    "gn:feature_code":"PPL",
    "gn:name":"Janosh",
    "gn:population":0,
    "gn:timezone":"Europe/Belgrade",
    "iso:country":"XK",
    "name:sqi_x_preferred":[
        "Janosh"
    ],
    "name:srp_x_preferred":[
        "Jano\u0161"
    ],
    "name:srp_x_variant":[
        "\u0408\u0430\u043d\u043e\u0448"
    ],
    "wof:name":"Janosh",
    "wof:placetype":"locality"
},
  "geometry": {"coordinates":[20.41694,42.45167],"type":"Point"}
}