{
  "type": "Feature",
  "properties": {
    "gn:admin1_code":"10096138.0",
    "gn:admin2_code":"3.0",
    "gn:asciiname":"Grebno",
    "gn:country_code":"XK",
    "gn:dem":567,
    "gn:feature_class":"P",
    "gn:feature_code":"PPLL",
    "gn:name":"Grebno",
    "gn:population":0,
    "gn:timezone":"Europe/Belgrade",
    "iso:country":"XK",
    "name:fra_x_preferred":[
        "Grebno"
    ],
    "name:sqi_x_preferred":[
        "Greme"
    ],
    "name:sqi_x_variant":[
        "Grem\u00eb",
        "Grema"
    ],
    "name:srp_x_preferred":[
        "\u0413\u0440\u0435\u0431\u043d\u043e"
    ],
    "name:srp_x_variant":[
        "Grebno"
    ],
    "name:swe_x_preferred":[
        "Grema"
    ],
    "name:und_x_variant":[
        "Grem\u00eb"
    ],
    "wof:name":"Grebno",
    "wof:placetype":"locality"
},
  "geometry": {"coordinates":[21.15722,42.31833],"type":"Point"}
}