{
  "type": "Feature",
  "properties": {
    "gn:admin1_code":"10097361.0",
    "gn:admin2_code":"2.0",
    "gn:asciiname":"Buzec",
    "gn:country_code":"XK",
    "gn:dem":1085,
    "gn:feature_class":"P",
    "gn:feature_code":"PPL",
    "gn:name":"Buzec",
    "gn:population":0,
    "gn:timezone":"Europe/Belgrade",
    "iso:country":"XK",
    "name:sqi_x_preferred":[
        "Buzez"
    ],
    "name:sqi_x_variant":[
        "Buz\u00ebs"
    ],
    "name:srp_x_preferred":[
        "\u0411\u0443\u0437\u0435\u0446"
    ],
    "name:srp_x_variant":[
        "Buzec"
    ],
    "wof:name":"Buzec",
    "wof:placetype":"locality"
},
  "geometry": {"coordinates":[20.70333,42.11111],"type":"Point"}
}