{
  "type": "Feature",
  "properties": {
    "gn:admin1_code":"10096859.0",
    "gn:admin2_code":"22.0",
    "gn:asciiname":"Petkoviq",
    "gn:country_code":"XK",
    "gn:dem":485,
    "gn:feature_class":"P",
    "gn:feature_code":"PPL",
    "gn:name":"Petkoviq",
    "gn:population":0,
    "gn:timezone":"Europe/Belgrade",
    "iso:country":"XK",
    "name:sqi_x_preferred":[
        "Petroviq"
    ],
    "name:sqi_x_variant":[
        "Petkoviq",
        "Guri i Kuq",
        "Petkofc"
    ],
    "name:srp_x_preferred":[
        "Petkovi\u0107"
    ],
    "name:srp_x_variant":[
        "\u041f\u0435\u0442\u043a\u043e\u0432\u0438\u045b",
        "\u041f\u0435\u0442\u043a\u043e\u0432\u0438\u045b\u0435",
        "Petkovi\u0107e"
    ],
    "name:und_x_variant":[
        "Guri i Kuq",
        "Petkofc",
        "Petkovi\u0107e"
    ],
    "wof:name":"Petkoviq",
    "wof:placetype":"locality"
},
  "geometry": {"coordinates":[20.55611,42.47278],"type":"Point"}
}