{
  "type": "Feature",
  "properties": {
    "gn:admin1_code":"10097357.0",
    "gn:admin2_code":"10.0",
    "gn:asciiname":"Caroliska Mahala",
    "gn:country_code":"XK",
    "gn:dem":978,
    "gn:feature_class":"P",
    "gn:feature_code":"PPL",
    "gn:name":"Caroliska Mahala",
    "gn:population":0,
    "gn:timezone":"Europe/Belgrade",
    "iso:country":"XK",
    "name:srp_x_preferred":[
        "Caroliska Mahala"
    ],
    "wof:name":"Caroliska Mahala",
    "wof:placetype":"locality"
},
  "geometry": {"coordinates":[21.68611,42.67833],"type":"Point"}
}