{
  "type": "Feature",
  "properties": {
    "gn:admin1_code":"10097358.0",
    "gn:admin2_code":"15.0",
    "gn:asciiname":"Kopriva",
    "gn:country_code":"XK",
    "gn:dem":684,
    "gn:feature_class":"P",
    "gn:feature_code":"PPL",
    "gn:name":"Kopriva",
    "gn:population":0,
    "gn:timezone":"Europe/Belgrade",
    "iso:country":"XK",
    "name:sqi_x_preferred":[
        "Kopriv\u00eb"
    ],
    "name:srp_x_preferred":[
        "Kopriva"
    ],
    "name:srp_x_variant":[
        "\u041a\u043e\u043f\u0440\u0438\u0432\u0430"
    ],
    "name:swe_x_preferred":[
        "Kopriva"
    ],
    "wof:name":"Kopriva",
    "wof:placetype":"locality"
},
  "geometry": {"coordinates":[20.79194,42.85417],"type":"Point"}
}