{
  "type": "Feature",
  "properties": {
    "gn:admin1_code":"10097361.0",
    "gn:admin2_code":"21.0",
    "gn:asciiname":"Planeja",
    "gn:country_code":"XK",
    "gn:dem":693,
    "gn:feature_class":"P",
    "gn:feature_code":"PPL",
    "gn:name":"Planeja",
    "gn:population":0,
    "gn:timezone":"Europe/Belgrade",
    "iso:country":"XK",
    "name:sqi_x_preferred":[
        "Pllanej\u00eb"
    ],
    "name:sqi_x_variant":[
        "Planej\u00eb"
    ],
    "name:srp_x_preferred":[
        "Planeja"
    ],
    "name:srp_x_variant":[
        "\u041f\u043b\u0430\u043d\u0435\u0458\u0430"
    ],
    "name:und_x_variant":[
        "Plane",
        "Planej\u00eb",
        "Pljaneja"
    ],
    "wof:name":"Planeja",
    "wof:placetype":"locality"
},
  "geometry": {"coordinates":[20.57806,42.21333],"type":"Point"}
}