{
  "type": "Feature",
  "properties": {
    "gn:admin1_code":"10096859.0",
    "gn:admin2_code":"5.0",
    "gn:asciiname":"Zhdrella",
    "gn:country_code":"XK",
    "gn:dem":383,
    "gn:feature_class":"P",
    "gn:feature_code":"PPLL",
    "gn:name":"Zhdrella",
    "gn:population":0,
    "gn:timezone":"Europe/Belgrade",
    "iso:country":"XK",
    "name:sqi_x_preferred":[
        "Zhdredh\u00eb"
    ],
    "name:sqi_x_variant":[
        "Zhdrell\u00eb",
        "Zhdrella"
    ],
    "name:srp_x_preferred":[
        "\u017ddrelo"
    ],
    "name:srp_x_variant":[
        "\u0416\u0434\u0440\u0435\u043b\u043e",
        "\u017ddrela"
    ],
    "name:und_x_variant":[
        "\u017ddrela",
        "Zhdrella",
        "Zhdrell\u00eb"
    ],
    "wof:name":"Zhdrella",
    "wof:placetype":"locality"
},
  "geometry": {"coordinates":[20.4325,42.46472],"type":"Point"}
}