{
  "type": "Feature",
  "properties": {
    "gn:admin1_code":"10096138.0",
    "gn:admin2_code":"9.0",
    "gn:asciiname":"Semanje",
    "gn:country_code":"XK",
    "gn:dem":741,
    "gn:feature_class":"P",
    "gn:feature_code":"PPL",
    "gn:name":"Semanje",
    "gn:population":0,
    "gn:timezone":"Europe/Belgrade",
    "iso:country":"XK",
    "name:sqi_x_preferred":[
        "Semanj"
    ],
    "name:sqi_x_variant":[
        "Semaj\u00eb",
        "Daic\u00eb"
    ],
    "name:srp_x_preferred":[
        "Semanje"
    ],
    "name:srp_x_variant":[
        "\u0421\u0435\u043c\u0430\u045a\u0435",
        "Donja Semanja"
    ],
    "name:und_x_variant":[
        "Donja Semanja",
        "Daic\u00eb"
    ],
    "wof:name":"Semanje",
    "wof:placetype":"locality"
},
  "geometry": {"coordinates":[21.13333,42.28806],"type":"Point"}
}