{
  "type": "Feature",
  "properties": {
    "gn:admin1_code":"10097358.0",
    "gn:admin2_code":"28.0",
    "gn:asciiname":"Ziljivoda",
    "gn:country_code":"XK",
    "gn:dem":634,
    "gn:feature_class":"P",
    "gn:feature_code":"PPL",
    "gn:name":"\u017diljivoda",
    "gn:population":0,
    "gn:timezone":"Europe/Belgrade",
    "iso:country":"XK",
    "name:sqi_x_preferred":[
        "Zhilivod\u00eb"
    ],
    "name:srp_x_preferred":[
        "\u0416\u0438\u043b\u0438\u0432\u043e\u0434\u0430"
    ],
    "name:srp_x_variant":[
        "\u017diljivoda",
        "\u017dilivoda",
        "\u017deli Voda"
    ],
    "name:und_x_variant":[
        "\u017dilivoda",
        "\u017deli Voda",
        "Zhilivod\u00eb"
    ],
    "wof:name":"Ziljivoda",
    "wof:placetype":"locality"
},
  "geometry": {"coordinates":[20.99,42.69778],"type":"Point"}
}