{
  "type": "Feature",
  "properties": {
    "gn:admin1_code":"10096859.0",
    "gn:admin2_code":"5.0",
    "gn:asciiname":"Kushavec",
    "gn:country_code":"XK",
    "gn:dem":357,
    "gn:feature_class":"P",
    "gn:feature_code":"PPL",
    "gn:name":"Kushavec",
    "gn:population":0,
    "gn:timezone":"Europe/Belgrade",
    "iso:country":"XK",
    "name:sqi_x_preferred":[
        "Kushavec"
    ],
    "name:sqi_x_variant":[
        "Kushova"
    ],
    "name:srp_x_preferred":[
        "Ku\u0161evac"
    ],
    "name:srp_x_variant":[
        "\u041a\u0443\u0448\u0435\u0432\u0430\u0446",
        "Ku\u0161avac"
    ],
    "wof:name":"Kushavec",
    "wof:placetype":"locality"
},
  "geometry": {"coordinates":[20.47472,42.34167],"type":"Point"}
}