{
  "type": "Feature",
  "properties": {
    "gn:admin1_code":"10097359.0",
    "gn:admin2_code":"18.0",
    "gn:asciiname":"Llugaxhi",
    "gn:country_code":"XK",
    "gn:dem":421,
    "gn:feature_class":"P",
    "gn:feature_code":"PPL",
    "gn:name":"Llugaxhi",
    "gn:population":0,
    "gn:timezone":"Europe/Belgrade",
    "iso:country":"XK",
    "name:fra_x_preferred":[
        "Lugad\u017eija"
    ],
    "name:sqi_x_preferred":[
        "Llugaxhi"
    ],
    "name:sqi_x_variant":[
        "Llugaxhia"
    ],
    "name:srp_x_preferred":[
        "Luga\u0111ija"
    ],
    "name:srp_x_variant":[
        "\u041b\u0443\u0433\u0430\u0452\u0438\u0458\u0430",
        "\u041b\u0443\u0433\u0430\u045f\u0438\u0458\u0430",
        "Lugad\u017eija"
    ],
    "wof:name":"Llugaxhi",
    "wof:placetype":"locality"
},
  "geometry": {"coordinates":[20.43944,42.63306],"type":"Point"}
}