{
  "type": "Feature",
  "properties": {
    "gn:admin1_code":"10097358.0",
    "gn:admin2_code":"28.0",
    "gn:asciiname":"Gornja Mahala",
    "gn:country_code":"XK",
    "gn:dem":606,
    "gn:feature_class":"P",
    "gn:feature_code":"PPL",
    "gn:name":"Gornja Mahala",
    "gn:population":0,
    "gn:timezone":"Europe/Belgrade",
    "iso:country":"XK",
    "name:sqi_x_preferred":[
        "Mahalla e Ep\u00ebrme"
    ],
    "name:srp_x_preferred":[
        "Gornja Mahala"
    ],
    "wof:name":"Gornja Mahala",
    "wof:placetype":"locality"
},
  "geometry": {"coordinates":[21.00155,42.82999],"type":"Point"}
}