{
  "type": "Feature",
  "properties": {
    "gn:admin1_code":"10097360.0",
    "gn:admin2_code":"20.0",
    "gn:asciiname":"Balaban",
    "gn:country_code":"XK",
    "gn:dem":665,
    "gn:feature_class":"P",
    "gn:feature_code":"PPLL",
    "gn:name":"Balaban",
    "gn:population":0,
    "gn:timezone":"Europe/Belgrade",
    "iso:country":"XK",
    "name:bel_x_preferred":[
        "\u0411\u0430\u043b\u0430\u0431\u0430\u043d"
    ],
    "name:ceb_x_preferred":[
        "Balaban"
    ],
    "name:deu_x_preferred":[
        "Balaban"
    ],
    "name:fra_x_preferred":[
        "Balaban"
    ],
    "name:heb_x_preferred":[
        "\u05d1\u05dc\u05d1\u05df"
    ],
    "name:hye_x_preferred":[
        "\u0532\u0561\u056c\u0561\u0562\u0561\u0576"
    ],
    "name:ita_x_preferred":[
        "Balaban"
    ],
    "name:pol_x_preferred":[
        "Ba\u0142aban"
    ],
    "name:rus_x_preferred":[
        "\u0411\u0430\u043b\u0430\u0431\u0430\u043d"
    ],
    "name:sqi_x_preferred":[
        "Ballaban"
    ],
    "name:sqi_x_variant":[
        "Ballabani"
    ],
    "name:srp_x_preferred":[
        "Balaban"
    ],
    "name:srp_x_variant":[
        "\u0411\u0430\u043b\u0430\u0431\u0430\u043d",
        "\u0411\u0430\u043b\u0430\u0431\u0430\u043d\u0435"
    ],
    "name:swe_x_preferred":[
        "Balaban"
    ],
    "name:tat_x_preferred":[
        "\u0411\u0430\u043b\u0430\u0431\u0430\u043d"
    ],
    "name:tur_x_preferred":[
        "Balaban"
    ],
    "name:und_x_variant":[
        "Balabane"
    ],
    "wof:name":"Balaban",
    "wof:placetype":"locality"
},
  "geometry": {"coordinates":[21.32194,42.79222],"type":"Point"}
}