{
  "type": "Feature",
  "properties": {
    "gn:admin1_code":"10097361.0",
    "gn:admin2_code":"21.0",
    "gn:asciiname":"Donja Srbica",
    "gn:country_code":"XK",
    "gn:dem":331,
    "gn:feature_class":"P",
    "gn:feature_code":"PPL",
    "gn:name":"Donja Srbica",
    "gn:population":0,
    "gn:timezone":"Europe/Belgrade",
    "iso:country":"XK",
    "name:sqi_x_preferred":[
        "S\u00ebrbic\u00eb e Poshtme"
    ],
    "name:sqi_x_variant":[
        "S\u00ebrbica e Ult\u00eb",
        "Serbic\u00eb e Poshtme",
        "S\u00ebrbic\u00eb"
    ],
    "name:srp_x_preferred":[
        "\u0414\u043e\u045a\u0430 \u0421\u0440\u0431\u0438\u0446\u0430"
    ],
    "name:srp_x_variant":[
        "Donja Srbica"
    ],
    "name:und_x_variant":[
        "Arbanas",
        "Serbica"
    ],
    "wof:name":"Donja Srbica",
    "wof:placetype":"locality"
},
  "geometry": {"coordinates":[20.69806,42.28667],"type":"Point"}
}