{
  "type": "Feature",
  "properties": {
    "gn:admin1_code":"10096859.0",
    "gn:admin2_code":"5.0",
    "gn:asciiname":"Ponoshec",
    "gn:country_code":"XK",
    "gn:dem":424,
    "gn:feature_class":"P",
    "gn:feature_code":"PPL",
    "gn:name":"Ponoshec",
    "gn:population":0,
    "gn:timezone":"Europe/Belgrade",
    "iso:country":"XK",
    "name:sqi_x_preferred":[
        "Ponoshec"
    ],
    "name:srp_x_preferred":[
        "\u041f\u043e\u043d\u043e\u0448\u0435\u0432\u0430\u0446"
    ],
    "name:srp_x_variant":[
        "Pono\u0161evac"
    ],
    "wof:name":"Ponoshec",
    "wof:placetype":"locality"
},
  "geometry": {"coordinates":[20.28361,42.40694000000001],"type":"Point"}
}