{
  "type": "Feature",
  "properties": {
    "gn:admin1_code":"10096138.0",
    "gn:admin2_code":"3.0",
    "gn:asciiname":"Muhovce",
    "gn:country_code":"XK",
    "gn:dem":573,
    "gn:feature_class":"P",
    "gn:feature_code":"PPL",
    "gn:name":"Muhovce",
    "gn:population":0,
    "gn:timezone":"Europe/Belgrade",
    "iso:country":"XK",
    "name:sqi_x_preferred":[
        "Muhoc"
    ],
    "name:srp_x_preferred":[
        "Muhovce"
    ],
    "name:srp_x_variant":[
        "\u041c\u0443\u0445\u043e\u0432\u0446\u0435"
    ],
    "wof:name":"Muhovce",
    "wof:placetype":"locality"
},
  "geometry": {"coordinates":[21.15028,42.39444],"type":"Point"}
}