{
  "type": "Feature",
  "properties": {
    "gn:admin1_code":"10097360.0",
    "gn:admin2_code":"19.0",
    "gn:asciiname":"Perane",
    "gn:country_code":"XK",
    "gn:dem":629,
    "gn:feature_class":"P",
    "gn:feature_code":"PPL",
    "gn:name":"Perane",
    "gn:population":0,
    "gn:timezone":"Europe/Belgrade",
    "iso:country":"XK",
    "name:sqi_x_preferred":[
        "Peran"
    ],
    "name:sqi_x_variant":[
        "Lkenasi"
    ],
    "name:srp_x_preferred":[
        "\u041f\u0435\u0440\u0430\u043d\u0435"
    ],
    "name:srp_x_variant":[
        "Perane"
    ],
    "name:und_x_variant":[
        "Lkenasi",
        "Perani",
        "Lkenas",
        "Peran"
    ],
    "wof:name":"Perane",
    "wof:placetype":"locality"
},
  "geometry": {"coordinates":[21.16515,42.92867],"type":"Point"}
}