{
  "type": "Feature",
  "properties": {
    "gn:admin1_code":"10096138.0",
    "gn:admin2_code":"23.0",
    "gn:asciiname":"Agus Mahala",
    "gn:country_code":"XK",
    "gn:dem":811,
    "gn:feature_class":"P",
    "gn:feature_code":"PPL",
    "gn:name":"Agu\u0161 Mahala",
    "gn:population":0,
    "gn:timezone":"Europe/Belgrade",
    "iso:country":"XK",
    "name:srp_x_preferred":[
        "Agu\u0161 Mahala"
    ],
    "name:srp_x_variant":[
        "Ogu\u0161aj",
        "Mahala Agu\u0161"
    ],
    "wof:name":"Agus Mahala",
    "wof:placetype":"locality"
},
  "geometry": {"coordinates":[21.11417,42.25944000000001],"type":"Point"}
}