{
  "type": "Feature",
  "properties": {
    "gn:admin1_code":"10097360.0",
    "gn:admin2_code":"20.0",
    "gn:asciiname":"Golema Livada",
    "gn:country_code":"XK",
    "gn:dem":822,
    "gn:feature_class":"P",
    "gn:feature_code":"PPL",
    "gn:name":"Golema Livada",
    "gn:population":0,
    "gn:timezone":"Europe/Belgrade",
    "iso:country":"XK",
    "name:srp_x_preferred":[
        "Golema Livada"
    ],
    "name:srp_x_variant":[
        "Mahala Goleme Livada"
    ],
    "wof:name":"Golema Livada",
    "wof:placetype":"locality"
},
  "geometry": {"coordinates":[21.37532,42.6275],"type":"Point"}
}