{
  "type": "Feature",
  "properties": {
    "gn:admin1_code":"10096138.0",
    "gn:admin2_code":"3.0",
    "gn:asciiname":"Macitevo",
    "gn:country_code":"XK",
    "gn:dem":903,
    "gn:feature_class":"P",
    "gn:feature_code":"PPLL",
    "gn:name":"Ma\u010ditevo",
    "gn:population":0,
    "gn:timezone":"Europe/Belgrade",
    "iso:country":"XK",
    "name:srp_x_preferred":[
        "Ma\u010ditevo"
    ],
    "wof:name":"Macitevo",
    "wof:placetype":"locality"
},
  "geometry": {"coordinates":[21.01472,42.34611],"type":"Point"}
}