{
  "type": "Feature",
  "properties": {
    "gn:admin1_code":"10097357.0",
    "gn:admin2_code":"10.0",
    "gn:asciiname":"Petrovce",
    "gn:country_code":"XK",
    "gn:dem":440,
    "gn:feature_class":"P",
    "gn:feature_code":"PPL",
    "gn:name":"Petrovce",
    "gn:population":0,
    "gn:timezone":"Europe/Belgrade",
    "iso:country":"XK",
    "name:sqi_x_preferred":[
        "Petrovc"
    ],
    "name:sqi_x_variant":[
        "Petroc"
    ],
    "name:srp_x_preferred":[
        "Petrovce"
    ],
    "name:srp_x_variant":[
        "\u041f\u0435\u0442\u0440\u043e\u0432\u0446\u0435"
    ],
    "name:und_x_variant":[
        "Petriti",
        "Petroci"
    ],
    "wof:name":"Petrovce",
    "wof:placetype":"locality"
},
  "geometry": {"coordinates":[21.57917,42.48667],"type":"Point"}
}