{
  "type": "Feature",
  "properties": {
    "gn:admin1_code":"10096138.0",
    "gn:admin2_code":"9.0",
    "gn:asciiname":"Dinarica",
    "gn:country_code":"XK",
    "gn:dem":826,
    "gn:feature_class":"P",
    "gn:feature_code":"PPL",
    "gn:name":"Dinarica",
    "gn:population":0,
    "gn:timezone":"Europe/Belgrade",
    "iso:country":"XK",
    "name:srp_x_preferred":[
        "Dinarica"
    ],
    "wof:name":"Dinarica",
    "wof:placetype":"locality"
},
  "geometry": {"coordinates":[21.34722,42.24417],"type":"Point"}
}