{
  "type": "Feature",
  "properties": {
    "gn:admin1_code":"10097360.0",
    "gn:admin2_code":"17.0",
    "gn:asciiname":"Koskovik Mahala",
    "gn:country_code":"XK",
    "gn:dem":633,
    "gn:feature_class":"P",
    "gn:feature_code":"PPL",
    "gn:name":"Koskovik Mahala",
    "gn:population":0,
    "gn:timezone":"Europe/Belgrade",
    "iso:country":"XK",
    "name:srp_x_preferred":[
        "Koskovik Mahala"
    ],
    "wof:name":"Koskovik Mahala",
    "wof:placetype":"locality"
},
  "geometry": {"coordinates":[21.10111,42.76944],"type":"Point"}
}