{
  "type": "Feature",
  "properties": {
    "gn:admin1_code":"10096859.0",
    "gn:admin2_code":"22.0",
    "gn:asciiname":"Kaznik",
    "gn:country_code":"XK",
    "gn:dem":650,
    "gn:feature_class":"P",
    "gn:feature_code":"PPL",
    "gn:name":"Kaznik",
    "gn:population":0,
    "gn:timezone":"Europe/Belgrade",
    "iso:country":"XK",
    "name:sqi_x_preferred":[
        "Kaznik"
    ],
    "name:srp_x_preferred":[
        "Koznik"
    ],
    "name:srp_x_variant":[
        "\u041a\u043e\u0437\u043d\u0438\u043a"
    ],
    "name:und_x_variant":[
        "Kozanik",
        "Kasnik"
    ],
    "wof:name":"Kaznik",
    "wof:placetype":"locality"
},
  "geometry": {"coordinates":[20.59389,42.47306],"type":"Point"}
}