{
  "type": "Feature",
  "properties": {
    "gn:country":"XK",
    "gn:fcode":"PPL",
    "gn:pop":0,
    "iso:country":"XK",
    "name:ceb_x_preferred":[
        "Laplje Selo"
    ],
    "name:eng_x_preferred":[
        "Laplje Selo"
    ],
    "name:fra_x_preferred":[
        "Laplje Selo"
    ],
    "name:nld_x_preferred":[
        "Laplje Selo"
    ],
    "name:sqi_x_preferred":[
        "Llapje Sell\u00eb"
    ],
    "name:sqi_x_variant":[
        "Llapllasell\u00eb",
        "Fshati Llap",
        "Llapllasella"
    ],
    "name:srp_x_preferred":[
        "Laplje Selo"
    ],
    "name:srp_x_variant":[
        "\u041b\u0430\u043f\u0459\u0435 \u0421\u0435\u043b\u043e"
    ],
    "name:swe_x_preferred":[
        "Laplje Selo"
    ],
    "name:unk_x_variant":[
        "Kadikej"
    ],
    "name:urd_x_preferred":[
        "\u0644\u0627\u067e\u0644\u062c\u06cc \u0633\u06cc\u0644\u0648"
    ],
    "qs:name":"Laplje Selo",
    "qs:name_adm0":"Serbia",
    "qs:name_adm1":"Kosovo",
    "qs:photos":51,
    "qs:photos_1k":10,
    "qs:photos_9k":1,
    "qs:photos_9r":2,
    "qs:photos_all":51,
    "qs:photos_sr":2,
    "qs:placetype":"Town",
    "qs:pop_sr":"0",
    "wd:wordcount":255,
    "wof:name":"Laplje Selo",
    "wof:placetype":"locality",
    "wof:population":0
},
  "geometry": {"coordinates":[21.14083,42.59667],"type":"Point"}
}