{
  "type": "Feature",
  "properties": {
    "gn:admin1_code":"10096138.0",
    "gn:admin2_code":"23.0",
    "gn:asciiname":"Radanova Mala",
    "gn:country_code":"XK",
    "gn:dem":931,
    "gn:feature_class":"P",
    "gn:feature_code":"PPL",
    "gn:name":"Radanova Mala",
    "gn:population":0,
    "gn:timezone":"Europe/Belgrade",
    "iso:country":"XK",
    "name:srp_x_preferred":[
        "Radanova Mala"
    ],
    "wof:name":"Radanova Mala",
    "wof:placetype":"locality"
},
  "geometry": {"coordinates":[20.98778,42.23167],"type":"Point"}
}