{
  "type": "Feature",
  "properties": {
    "gn:admin1_code":"10097358.0",
    "gn:admin2_code":"12.0",
    "gn:asciiname":"Bistrica",
    "gn:country_code":"XK",
    "gn:dem":569,
    "gn:feature_class":"P",
    "gn:feature_code":"PPL",
    "gn:name":"Bistrica",
    "gn:population":0,
    "gn:timezone":"Europe/Belgrade",
    "iso:country":"XK",
    "name:bos_x_preferred":[
        "Bistrica"
    ],
    "name:bul_x_preferred":[
        "\u0411\u0438\u0441\u0442\u0440\u0438\u0446\u0430"
    ],
    "name:ceb_x_preferred":[
        "Bistrica"
    ],
    "name:deu_x_preferred":[
        "Bistrica"
    ],
    "name:ell_x_preferred":[
        "\u0392\u03af\u03c3\u03c4\u03c1\u03b9\u03c4\u03c3\u03b1"
    ],
    "name:fra_x_preferred":[
        "Bistrica"
    ],
    "name:hrv_x_preferred":[
        "Bistrica"
    ],
    "name:hun_x_preferred":[
        "Bistrica"
    ],
    "name:ita_x_preferred":[
        "Bistrica"
    ],
    "name:lat_x_preferred":[
        "Bistrica"
    ],
    "name:lit_x_preferred":[
        "Bistrica"
    ],
    "name:mkd_x_preferred":[
        "\u0411\u0438\u0441\u0442\u0440\u0438\u0446\u0430"
    ],
    "name:nld_x_preferred":[
        "Bistrica"
    ],
    "name:pol_x_preferred":[
        "Bistrica"
    ],
    "name:rus_x_preferred":[
        "\u0411\u0438\u0441\u0442\u0440\u0438\u0446\u0430"
    ],
    "name:slv_x_preferred":[
        "Bistrica"
    ],
    "name:sqi_x_preferred":[
        "Bistric\u00eb"
    ],
    "name:sqi_x_variant":[
        "Bistrica"
    ],
    "name:srp_x_preferred":[
        "\u0411\u0438\u0441\u0442\u0440\u0438\u0446\u0430"
    ],
    "name:srp_x_variant":[
        "Bistrica"
    ],
    "name:swe_x_preferred":[
        "Bistrica"
    ],
    "wof:name":"Bistrica",
    "wof:placetype":"locality"
},
  "geometry": {"coordinates":[20.71889,43.22528],"type":"Point"}
}