{
  "type": "Feature",
  "properties": {
    "gn:admin1_code":"10097358.0",
    "gn:admin2_code":"12.0",
    "gn:asciiname":"Bistrica",
    "gn:country_code":"XK",
    "gn:dem":569,
    "gn:feature_class":"P",
    "gn:feature_code":"PPL",
    "gn:name":"Bistrica",
    "gn:population":0,
    "gn:timezone":"Europe/Belgrade",
    "iso:country":"XK",
    "name:lat_x_preferred":[
        "Bistrica"
    ],
    "name:sqi_x_preferred":[
        "Bistric\u00eb"
    ],
    "name:srp_x_preferred":[
        "\u0411\u0438\u0441\u0442\u0440\u0438\u0446\u0430"
    ],
    "name:srp_x_variant":[
        "Bistrica"
    ],
    "name:swe_x_preferred":[
        "Bistrica"
    ],
    "name:und_x_variant":[
        "Bistric\u00eb"
    ],
    "wof:name":"Bistrica",
    "wof:placetype":"locality"
},
  "geometry": {"coordinates":[20.71889,43.22528],"type":"Point"}
}