{
  "type": "Feature",
  "properties": {
    "gn:admin1_code":"10097359.0",
    "gn:admin2_code":"8.0",
    "gn:asciiname":"Vrella",
    "gn:country_code":"XK",
    "gn:dem":491,
    "gn:feature_class":"P",
    "gn:feature_code":"PPL",
    "gn:name":"Vrella",
    "gn:population":0,
    "gn:timezone":"Europe/Belgrade",
    "iso:country":"XK",
    "name:sqi_x_preferred":[
        "Vrell\u00eb"
    ],
    "name:sqi_x_variant":[
        "Vrella",
        "Tedeli"
    ],
    "name:und_x_variant":[
        "Tedeli",
        "Vrella",
        "Tedel",
        "Vrell\u00eb"
    ],
    "wof:name":"Vrella",
    "wof:placetype":"locality"
},
  "geometry": {"coordinates":[20.40444,42.77056],"type":"Point"}
}