{
  "type": "Feature",
  "properties": {
    "gn:admin1_code":"10097361.0",
    "gn:admin2_code":"26.0",
    "gn:asciiname":"Javor",
    "gn:country_code":"XK",
    "gn:dem":875,
    "gn:feature_class":"P",
    "gn:feature_code":"PPLL",
    "gn:name":"Javor",
    "gn:population":0,
    "gn:timezone":"Europe/Belgrade",
    "iso:country":"XK",
    "name:srp_x_preferred":[
        "\u0408\u0430\u0432\u043e\u0440"
    ],
    "name:srp_x_variant":[
        "Javor"
    ],
    "wof:name":"Javor",
    "wof:placetype":"locality"
},
  "geometry": {"coordinates":[20.88139,42.47333],"type":"Point"}
}