{
  "type": "Feature",
  "properties": {
    "gn:admin1_code":"10097360.0",
    "gn:admin2_code":"19.0",
    "gn:asciiname":"Prnovicka Mahala",
    "gn:country_code":"XK",
    "gn:dem":727,
    "gn:feature_class":"P",
    "gn:feature_code":"PPL",
    "gn:name":"Prnovi\u010dka Mahala",
    "gn:population":0,
    "gn:timezone":"Europe/Belgrade",
    "iso:country":"XK",
    "name:srp_x_preferred":[
        "Prnovi\u010dka Mahala"
    ],
    "wof:name":"Prnovicka Mahala",
    "wof:placetype":"locality"
},
  "geometry": {"coordinates":[21.12208,42.97363],"type":"Point"}
}