{
  "type": "Feature",
  "properties": {
    "gn:admin1_code":"10097359.0",
    "gn:admin2_code":"18.0",
    "gn:asciiname":"Rashiq",
    "gn:country_code":"XK",
    "gn:dem":491,
    "gn:feature_class":"P",
    "gn:feature_code":"PPL",
    "gn:name":"Rashiq",
    "gn:population":0,
    "gn:timezone":"Europe/Belgrade",
    "iso:country":"XK",
    "name:sqi_x_preferred":[
        "Rashiq"
    ],
    "name:srp_x_preferred":[
        "Ra\u0161i\u0107"
    ],
    "name:srp_x_variant":[
        "\u0420\u0430\u0448\u0438\u045b"
    ],
    "wof:name":"Rashiq",
    "wof:placetype":"locality"
},
  "geometry": {"coordinates":[20.37694,42.57389000000001],"type":"Point"}
}