{
  "type": "Feature",
  "properties": {
    "gn:admin1_code":"10097358.0",
    "gn:admin2_code":"30.0",
    "gn:asciiname":"Banjska Reka",
    "gn:country_code":"XK",
    "gn:dem":599,
    "gn:feature_class":"P",
    "gn:feature_code":"PPL",
    "gn:name":"Banjska Reka",
    "gn:population":0,
    "gn:timezone":"Europe/Belgrade",
    "iso:country":"XK",
    "name:sqi_x_preferred":[
        "Rek\u00eb e Banjsk\u00ebs"
    ],
    "name:srp_x_preferred":[
        "Banjska Reka"
    ],
    "name:srp_x_variant":[
        "\u0411\u0430\u045a\u0441\u043a\u0430 \u0420\u0435\u043a\u0430",
        "\u0411\u0438\u0448\u0442\u0430\u043d\u0441\u043a\u0430 \u0420\u0435\u043a\u0430",
        "Bastanska Reka",
        "Bi\u0161tanska Reka"
    ],
    "wof:name":"Banjska Reka",
    "wof:placetype":"locality"
},
  "geometry": {"coordinates":[20.75556,42.98722],"type":"Point"}
}