{
  "type": "Feature",
  "properties": {
    "gn:admin1_code":"10096138.0",
    "gn:admin2_code":"24.0",
    "gn:asciiname":"Ljug Mahala",
    "gn:country_code":"XK",
    "gn:dem":1028,
    "gn:feature_class":"P",
    "gn:feature_code":"PPL",
    "gn:name":"Ljug Mahala",
    "gn:population":0,
    "gn:timezone":"Europe/Belgrade",
    "iso:country":"XK",
    "name:srp_x_preferred":[
        "Ljug Mahala"
    ],
    "wof:name":"Ljug Mahala",
    "wof:placetype":"locality"
},
  "geometry": {"coordinates":[20.95389,42.405],"type":"Point"}
}