{
  "type": "Feature",
  "properties": {
    "gn:admin1_code":"10096859.0",
    "gn:admin2_code":"33.0",
    "gn:asciiname":"Sac",
    "gn:country_code":"XK",
    "gn:dem":531,
    "gn:feature_class":"P",
    "gn:feature_code":"PPL",
    "gn:name":"Sa\u0107",
    "gn:population":0,
    "gn:timezone":"Europe/Belgrade",
    "iso:country":"XK",
    "name:srp_x_preferred":[
        "\u0421\u0430\u045b"
    ],
    "name:srp_x_variant":[
        "Sa\u0107"
    ],
    "wof:name":"Sac",
    "wof:placetype":"locality"
},
  "geometry": {"coordinates":[20.29028,42.47972],"type":"Point"}
}