{
  "type": "Feature",
  "properties": {
    "gn:admin1_code":"10097358.0",
    "gn:admin2_code":"12.0",
    "gn:asciiname":"Grebna",
    "gn:country_code":"XK",
    "gn:dem":805,
    "gn:feature_class":"P",
    "gn:feature_code":"PPL",
    "gn:name":"Grebna",
    "gn:population":0,
    "gn:timezone":"Europe/Belgrade",
    "iso:country":"XK",
    "name:srp_x_preferred":[
        "Grebna"
    ],
    "wof:name":"Grebna",
    "wof:placetype":"locality"
},
  "geometry": {"coordinates":[20.73083,43.07167000000001],"type":"Point"}
}