{
  "type": "Feature",
  "properties": {
    "gn:admin1_code":"10097360.0",
    "gn:admin2_code":"17.0",
    "gn:asciiname":"Pipersk Mahala",
    "gn:country_code":"XK",
    "gn:dem":618,
    "gn:feature_class":"P",
    "gn:feature_code":"PPL",
    "gn:name":"Pipersk Mahala",
    "gn:population":0,
    "gn:timezone":"Europe/Belgrade",
    "iso:country":"XK",
    "name:srp_x_preferred":[
        "Pipersk Mahala"
    ],
    "wof:name":"Pipersk Mahala",
    "wof:placetype":"locality"
},
  "geometry": {"coordinates":[21.07862,42.76849],"type":"Point"}
}