{
  "type": "Feature",
  "properties": {
    "gn:admin1_code":"10097359.0",
    "gn:admin2_code":"11.0",
    "gn:asciiname":"Kuciste",
    "gn:country_code":"XK",
    "gn:dem":415,
    "gn:feature_class":"P",
    "gn:feature_code":"PPL",
    "gn:name":"Ku\u0107i\u0161te",
    "gn:population":0,
    "gn:timezone":"Europe/Belgrade",
    "iso:country":"XK",
    "name:srp_x_preferred":[
        "Ku\u0107i\u0161te"
    ],
    "wof:name":"Kuciste",
    "wof:placetype":"locality"
},
  "geometry": {"coordinates":[20.47222,42.67944],"type":"Point"}
}