{
  "type": "Feature",
  "properties": {
    "gn:admin1_code":"10097360.0",
    "gn:admin2_code":"19.0",
    "gn:asciiname":"Gornja Zakut",
    "gn:country_code":"XK",
    "gn:dem":671,
    "gn:feature_class":"P",
    "gn:feature_code":"PPL",
    "gn:name":"Gornja Zakut",
    "gn:population":0,
    "gn:timezone":"Europe/Belgrade",
    "iso:country":"XK",
    "wof:name":"Gornja Zakut",
    "wof:placetype":"locality"
},
  "geometry": {"coordinates":[21.14694,42.98472],"type":"Point"}
}