{
  "type": "Feature",
  "properties": {
    "gn:admin1_code":"10097358.0",
    "gn:admin2_code":"15.0",
    "gn:asciiname":"Tairovici",
    "gn:country_code":"XK",
    "gn:dem":923,
    "gn:feature_class":"P",
    "gn:feature_code":"PPL",
    "gn:name":"Tairovici",
    "gn:population":0,
    "gn:timezone":"Europe/Belgrade",
    "iso:country":"XK",
    "name:srp_x_preferred":[
        "Tairovici"
    ],
    "wof:name":"Tairovici",
    "wof:placetype":"locality"
},
  "geometry": {"coordinates":[20.95306,43.0025],"type":"Point"}
}