{
  "type": "Feature",
  "properties": {
    "gn:country":"XK",
    "gn:fcode":"PPLL",
    "gn:population":4,
    "iso:country":"XK",
    "name:und_x_variant":[
        "Fusha"
    ],
    "qs:name":"Tropoviq",
    "qs:photos_9r":0,
    "qs:photos_sr":0,
    "qs:pop_sr":"1",
    "wof:name":"Tropoviq",
    "wof:placetype":"locality",
    "wof:population":4
},
  "geometry": {"coordinates":[20.35278,42.67361],"type":"Point"}
}