{
  "type": "Feature",
  "properties": {
    "gn:admin1_code":"10097358.0",
    "gn:admin2_code":"12.0",
    "gn:asciiname":"Mekiniqe",
    "gn:country_code":"XK",
    "gn:dem":663,
    "gn:feature_class":"P",
    "gn:feature_code":"PPL",
    "gn:name":"Mekiniqe",
    "gn:population":0,
    "gn:timezone":"Europe/Belgrade",
    "iso:country":"XK",
    "name:sqi_x_preferred":[
        "Mekiniqe"
    ],
    "name:srp_x_preferred":[
        "Mekini\u0107e"
    ],
    "name:srp_x_variant":[
        "\u041c\u0435\u043a\u0438\u043d\u0438\u045b\u0435",
        "Mekini\u0107"
    ],
    "name:und_x_variant":[
        "Drenska"
    ],
    "wof:name":"Mekiniqe",
    "wof:placetype":"locality"
},
  "geometry": {"coordinates":[20.78333,43.15278],"type":"Point"}
}