{
  "type": "Feature",
  "properties": {
    "gn:admin1_code":"10097360.0",
    "gn:admin2_code":"19.0",
    "gn:asciiname":"Siljevica",
    "gn:country_code":"XK",
    "gn:dem":1027,
    "gn:feature_class":"P",
    "gn:feature_code":"PPL",
    "gn:name":"Siljevica",
    "gn:population":0,
    "gn:timezone":"Europe/Belgrade",
    "iso:country":"XK",
    "name:ceb_x_preferred":[
        "Siljevica"
    ],
    "name:fra_x_preferred":[
        "Siljevica"
    ],
    "name:msa_x_preferred":[
        "Siljevica"
    ],
    "name:por_x_preferred":[
        "Siljevica"
    ],
    "name:slv_x_preferred":[
        "Siljevica"
    ],
    "name:sqi_x_preferred":[
        "Sylevic\u00eb"
    ],
    "name:sqi_x_variant":[
        "Silevic",
        "Silefc",
        "Sllavic\u00eb",
        "Sylevica",
        "Fierisht\u00eb",
        "Fierishta"
    ],
    "name:srp_x_preferred":[
        "\u0421\u0438\u0459\u0435\u0432\u0438\u0446\u0430"
    ],
    "name:srp_x_variant":[
        "Siljevica"
    ],
    "name:und_x_variant":[
        "Fierisht\u00eb",
        "Sllavic\u00eb",
        "Fierishta",
        "Silefc",
        "Sylevica"
    ],
    "wof:name":"Siljevica",
    "wof:placetype":"locality"
},
  "geometry": {"coordinates":[21.08111,43.03833],"type":"Point"}
}