{
  "type": "Feature",
  "properties": {
    "gn:admin1_code":"10097358.0",
    "gn:admin2_code":"30.0",
    "gn:asciiname":"Loziste",
    "gn:country_code":"XK",
    "gn:dem":516,
    "gn:feature_class":"P",
    "gn:feature_code":"PPL",
    "gn:name":"Lozi\u0161te",
    "gn:population":0,
    "gn:timezone":"Europe/Belgrade",
    "iso:country":"XK",
    "name:sqi_x_preferred":[
        "Llozisht\u00eb"
    ],
    "name:sqi_x_variant":[
        "Lozishte"
    ],
    "name:srp_x_preferred":[
        "\u041b\u043e\u0437\u0438\u0448\u0442\u0435"
    ],
    "name:srp_x_variant":[
        "Lozi\u0161te"
    ],
    "wof:name":"Loziste",
    "wof:placetype":"locality"
},
  "geometry": {"coordinates":[20.81889,42.97694],"type":"Point"}
}