{
  "type": "Feature",
  "properties": {
    "gn:admin1_code":"10097358.0",
    "gn:admin2_code":"29.0",
    "gn:asciiname":"Vidgrica",
    "gn:country_code":"XK",
    "gn:dem":722,
    "gn:feature_class":"P",
    "gn:feature_code":"PPL",
    "gn:name":"Vidgrica",
    "gn:population":0,
    "gn:timezone":"Europe/Belgrade",
    "iso:country":"XK",
    "name:srp_x_preferred":[
        "Vidgrica"
    ],
    "wof:name":"Vidgrica",
    "wof:placetype":"locality"
},
  "geometry": {"coordinates":[20.78333,42.91583],"type":"Point"}
}