{
  "type": "Feature",
  "properties": {
    "gn:admin1_code":"10097360.0",
    "gn:admin2_code":"4.0",
    "gn:asciiname":"Novo Selo",
    "gn:country_code":"XK",
    "gn:dem":537,
    "gn:feature_class":"P",
    "gn:feature_code":"PPL",
    "gn:name":"Novo Selo",
    "gn:population":0,
    "gn:timezone":"Europe/Belgrade",
    "iso:country":"XK",
    "name:srp_x_preferred":[
        "Novo Selo"
    ],
    "wof:name":"Novo Selo",
    "wof:placetype":"locality"
},
  "geometry": {"coordinates":[21.08512,42.6515],"type":"Point"}
}