{
  "type": "Feature",
  "properties": {
    "gn:admin1_code":"10097360.0",
    "gn:admin2_code":"4.0",
    "gn:asciiname":"Novo Selo",
    "gn:country_code":"XK",
    "gn:dem":537,
    "gn:feature_class":"P",
    "gn:feature_code":"PPL",
    "gn:name":"Novo Selo",
    "gn:population":0,
    "gn:timezone":"Europe/Belgrade",
    "iso:country":"XK",
    "name:bos_x_preferred":[
        "Novo Selo"
    ],
    "name:bul_x_preferred":[
        "\u041d\u043e\u0432\u043e \u0441\u0435\u043b\u043e"
    ],
    "name:ceb_x_preferred":[
        "Novo Selo"
    ],
    "name:deu_x_preferred":[
        "Novo Selo"
    ],
    "name:epo_x_preferred":[
        "Novo Selo"
    ],
    "name:fra_x_preferred":[
        "Novo Selo"
    ],
    "name:hrv_x_preferred":[
        "Novo Selo"
    ],
    "name:hun_x_preferred":[
        "Novo Selo"
    ],
    "name:ita_x_preferred":[
        "Novo Selo"
    ],
    "name:jpn_x_preferred":[
        "\u30ce\u30f4\u30a9\u30fb\u30bb\u30ed"
    ],
    "name:mkd_x_preferred":[
        "\u041d\u043e\u0432\u043e \u0421\u0435\u043b\u043e"
    ],
    "name:nld_x_preferred":[
        "Novo Selo"
    ],
    "name:pol_x_preferred":[
        "Novo Selo"
    ],
    "name:por_x_preferred":[
        "Novo Selo"
    ],
    "name:ron_x_preferred":[
        "Novo Selo"
    ],
    "name:rus_x_preferred":[
        "\u041d\u043e\u0432\u043e-\u0421\u0435\u043b\u043e"
    ],
    "name:slk_x_preferred":[
        "Novo Selo"
    ],
    "name:slv_x_preferred":[
        "Novo Selo"
    ],
    "name:spa_x_preferred":[
        "Novo Selo"
    ],
    "name:srp_x_preferred":[
        "Novo Selo"
    ],
    "name:srp_x_variant":[
        "\u041d\u043e\u0432\u043e \u0421\u0435\u043b\u043e"
    ],
    "name:swe_x_preferred":[
        "Novo Selo"
    ],
    "name:ukr_x_preferred":[
        "\u041d\u043e\u0432\u043e-\u0421\u0435\u043b\u043e"
    ],
    "wof:name":"Novo Selo",
    "wof:placetype":"locality"
},
  "geometry": {"coordinates":[21.08512,42.6515],"type":"Point"}
}