{
  "type": "Feature",
  "properties": {
    "gn:admin1_code":"10097358.0",
    "gn:admin2_code":"28.0",
    "gn:asciiname":"Velika Reka",
    "gn:country_code":"XK",
    "gn:dem":525,
    "gn:feature_class":"P",
    "gn:feature_code":"PPL",
    "gn:name":"Velika Reka",
    "gn:population":0,
    "gn:timezone":"Europe/Belgrade",
    "iso:country":"XK",
    "name:ceb_x_preferred":[
        "Velika Reka"
    ],
    "name:fas_x_preferred":[
        "\u0648\u0644\u06cc\u06a9\u0627 \u0631\u06a9\u0627"
    ],
    "name:fra_x_preferred":[
        "Velika Reka"
    ],
    "name:msa_x_preferred":[
        "Velika Reka"
    ],
    "name:nld_x_preferred":[
        "Velika Reka"
    ],
    "name:por_x_preferred":[
        "Velika Reka"
    ],
    "name:slv_x_preferred":[
        "Velika Reka"
    ],
    "name:sqi_x_preferred":[
        "Velikorek\u00eb"
    ],
    "name:sqi_x_variant":[
        "Lumadh",
        "Velikarek\u00eb",
        "Lum\u00ebmadh"
    ],
    "name:srp_x_preferred":[
        "Velika Reka"
    ],
    "name:srp_x_variant":[
        "\u0412\u0435\u043b\u0438\u043a\u0430 \u0420\u0435\u043a\u0430"
    ],
    "wof:name":"Velika Reka",
    "wof:placetype":"locality"
},
  "geometry": {"coordinates":[21.02593,42.75655],"type":"Point"}
}