{
  "type": "Feature",
  "properties": {
    "gn:country":"XK",
    "gn:fcode":"PPL",
    "gn:population":4,
    "iso:country":"XK",
    "name:sqi_x_preferred":[
        "Raushiq"
    ],
    "name:sqi_x_variant":[
        "Rrafshi",
        "Raushiqi",
        "Raush",
        "Raushi"
    ],
    "name:srp_x_preferred":[
        "Rau\u0161i\u0107"
    ],
    "name:srp_x_variant":[
        "\u0420\u0430\u0443\u0448\u0438\u045b",
        "Stari Rau\u0161i\u0107"
    ],
    "qs:name":"Raushiq",
    "qs:photos_9r":0,
    "qs:photos_sr":0,
    "qs:pop_sr":"1",
    "wof:name":"Raushiq",
    "wof:placetype":"locality",
    "wof:population":4
},
  "geometry": {"coordinates":[20.31167,42.615],"type":"Point"}
}