{
  "type": "Feature",
  "properties": {
    "gn:admin1_code":"10097360.0",
    "gn:admin2_code":"7.0",
    "gn:asciiname":"Stankovc",
    "gn:country_code":"XK",
    "gn:dem":663,
    "gn:feature_class":"P",
    "gn:feature_code":"PPL",
    "gn:name":"Stankovc",
    "gn:population":0,
    "gn:timezone":"Europe/Belgrade",
    "iso:country":"XK",
    "name:sqi_x_preferred":[
        "Stankoc"
    ],
    "name:sqi_x_variant":[
        "Sankoc",
        "Stankovc",
        "Stankofc",
        "Sankofci",
        "K\u00ebshtjell\u00eb",
        "K\u00ebshtjella"
    ],
    "name:srp_x_preferred":[
        "Stankovce"
    ],
    "name:srp_x_variant":[
        "\u0421\u0442\u0430\u043d\u043a\u043e\u0432\u0446\u0435"
    ],
    "name:und_x_variant":[
        "K\u00ebshtjell\u00eb",
        "Sankofci",
        "K\u00ebshtjella",
        "Stankofc",
        "Stankovci"
    ],
    "wof:name":"Stankovc",
    "wof:placetype":"locality"
},
  "geometry": {"coordinates":[20.93611,42.57194000000001],"type":"Point"}
}