{
  "type": "Feature",
  "properties": {
    "gn:admin1_code":"10097359.0",
    "gn:admin2_code":"11.0",
    "gn:asciiname":"Leskoc",
    "gn:country_code":"XK",
    "gn:dem":516,
    "gn:feature_class":"P",
    "gn:feature_code":"PPLL",
    "gn:name":"Leskoc",
    "gn:population":0,
    "gn:timezone":"Europe/Belgrade",
    "iso:country":"XK",
    "name:sqi_x_preferred":[
        "Leskoc"
    ],
    "name:srp_x_preferred":[
        "Leskovac"
    ],
    "name:srp_x_variant":[
        "\u041b\u0435\u0441\u043a\u043e\u0432\u0430\u0446"
    ],
    "name:und_x_variant":[
        "Loskovac"
    ],
    "wof:name":"Leskoc",
    "wof:placetype":"locality"
},
  "geometry": {"coordinates":[20.59101,42.69114],"type":"Point"}
}