{
  "type": "Feature",
  "properties": {
    "gn:admin1_code":"10097360.0",
    "gn:admin2_code":"20.0",
    "gn:asciiname":"Rimaniste",
    "gn:country_code":"XK",
    "gn:dem":687,
    "gn:feature_class":"P",
    "gn:feature_code":"PPLL",
    "gn:name":"Rimani\u0161te",
    "gn:population":0,
    "gn:timezone":"Europe/Belgrade",
    "iso:country":"XK",
    "name:sqi_x_preferred":[
        "Rimanisht\u00eb"
    ],
    "name:srp_x_preferred":[
        "\u0420\u0438\u043c\u0430\u043d\u0438\u0448\u0442\u0435"
    ],
    "name:srp_x_variant":[
        "Rimani\u0161te"
    ],
    "wof:name":"Rimaniste",
    "wof:placetype":"locality"
},
  "geometry": {"coordinates":[21.19833,42.76722],"type":"Point"}
}