{
  "type": "Feature",
  "properties": {
    "gn:admin1_code":"10097360.0",
    "gn:admin2_code":"20.0",
    "gn:asciiname":"Grbes",
    "gn:country_code":"XK",
    "gn:dem":887,
    "gn:feature_class":"P",
    "gn:feature_code":"PPL",
    "gn:name":"Grbe\u0161",
    "gn:population":0,
    "gn:timezone":"Europe/Belgrade",
    "iso:country":"XK",
    "name:srp_x_preferred":[
        "Grbe\u0161"
    ],
    "name:srp_x_variant":[
        "Mahala Grbe\u0161"
    ],
    "name:und_x_variant":[
        "Mahala Grbe\u0161"
    ],
    "wof:name":"Grbes",
    "wof:placetype":"locality"
},
  "geometry": {"coordinates":[21.37611,42.64333],"type":"Point"}
}