{
  "type": "Feature",
  "properties": {
    "gn:admin1_code":"10097360.0",
    "gn:admin2_code":"7.0",
    "gn:asciiname":"Gladno Selo",
    "gn:country_code":"XK",
    "gn:dem":619,
    "gn:feature_class":"P",
    "gn:feature_code":"PPL",
    "gn:name":"Gladno Selo",
    "gn:population":0,
    "gn:timezone":"Europe/Belgrade",
    "iso:country":"XK",
    "name:sqi_x_preferred":[
        "Glladnasell\u00eb"
    ],
    "name:sqi_x_variant":[
        "Gllanasell\u00eb",
        "Gllanasella",
        "Shkab\u00eb",
        "Shkaba"
    ],
    "name:srp_x_preferred":[
        "\u0413\u043b\u0430\u0434\u043d\u043e \u0421\u0435\u043b\u043e"
    ],
    "name:srp_x_variant":[
        "Gladno Selo"
    ],
    "name:und_x_variant":[
        "Nika"
    ],
    "wof:name":"Gladno Selo",
    "wof:placetype":"locality"
},
  "geometry": {"coordinates":[20.91694,42.67028],"type":"Point"}
}