{
  "type": "Feature",
  "properties": {
    "gn:admin1_code":"10097361.0",
    "gn:admin2_code":"14.0",
    "gn:asciiname":"Regevic Mahala",
    "gn:country_code":"XK",
    "gn:dem":567,
    "gn:feature_class":"P",
    "gn:feature_code":"PPL",
    "gn:name":"Re\u0111evi\u0107 Mahala",
    "gn:population":0,
    "gn:timezone":"Europe/Belgrade",
    "iso:country":"XK",
    "name:srp_x_preferred":[
        "\u0420\u0435\u0452\u0435\u0432\u0438\u045b \u041c\u0430\u0445\u0430\u043b\u0430"
    ],
    "name:srp_x_variant":[
        "Re\u0111evi\u0107 Mahala"
    ],
    "wof:name":"Regevic Mahala",
    "wof:placetype":"locality"
},
  "geometry": {"coordinates":[20.74833,42.40861],"type":"Point"}
}