{
  "type": "Feature",
  "properties": {
    "gn:admin1_code":"10097357.0",
    "gn:admin2_code":"6.0",
    "gn:asciiname":"Bukovik",
    "gn:country_code":"XK",
    "gn:dem":708,
    "gn:feature_class":"P",
    "gn:feature_code":"PPL",
    "gn:name":"Bukovik",
    "gn:population":0,
    "gn:timezone":"Europe/Belgrade",
    "iso:country":"XK",
    "name:bos_x_preferred":[
        "Bukovik"
    ],
    "name:bul_x_preferred":[
        "\u0411\u0443\u043a\u043e\u0432\u0438\u043a"
    ],
    "name:ceb_x_preferred":[
        "Bukovik"
    ],
    "name:fra_x_preferred":[
        "Bukovik"
    ],
    "name:hrv_x_preferred":[
        "Bukovik"
    ],
    "name:nld_x_preferred":[
        "Bukovik"
    ],
    "name:slv_x_preferred":[
        "Bukovik"
    ],
    "name:sqi_x_preferred":[
        "Bukovik - Capar"
    ],
    "name:sqi_x_variant":[
        "Bukovik - Sapar",
        "Bukoviku",
        "Ahishte-a"
    ],
    "name:srp_x_preferred":[
        "\u0411\u0443\u043a\u043e\u0432\u0438\u043a"
    ],
    "name:srp_x_variant":[
        "\u0411\u0443\u043a\u043e\u0432\u0438\u043a - \u0421\u0430\u043f\u0430\u0440",
        "\u0411\u0443\u043a\u043e\u0432\u0438\u043a - \u0426\u0430\u043f\u0430\u0440",
        "Bukovik"
    ],
    "name:swe_x_preferred":[
        "Bukovik"
    ],
    "name:und_x_variant":[
        "Ahishte-a",
        "Bukoviku"
    ],
    "wof:name":"Bukovik",
    "wof:placetype":"locality"
},
  "geometry": {"coordinates":[21.56139,42.45444000000001],"type":"Point"}
}