{
  "type": "Feature",
  "properties": {
    "gn:admin1_code":"10097361.0",
    "gn:admin2_code":"14.0",
    "gn:asciiname":"Sejak",
    "gn:country_code":"XK",
    "gn:dem":609,
    "gn:feature_class":"P",
    "gn:feature_code":"PPL",
    "gn:name":"\u0160ejak",
    "gn:population":0,
    "gn:timezone":"Europe/Belgrade",
    "iso:country":"XK",
    "name:srp_x_preferred":[
        "\u0428\u0435\u0458\u0430\u043a"
    ],
    "name:srp_x_variant":[
        "\u0160ejak"
    ],
    "wof:name":"Sejak",
    "wof:placetype":"locality"
},
  "geometry": {"coordinates":[20.83222,42.44139000000001],"type":"Point"}
}