{
  "type": "Feature",
  "properties": {
    "gn:admin1_code":"10096859.0",
    "gn:admin2_code":"5.0",
    "gn:asciiname":"Llugagji",
    "gn:country_code":"XK",
    "gn:dem":428,
    "gn:feature_class":"P",
    "gn:feature_code":"PPL",
    "gn:name":"Llugagji",
    "gn:population":0,
    "gn:timezone":"Europe/Belgrade",
    "iso:country":"XK",
    "name:sqi_x_preferred":[
        "Llugaxhi"
    ],
    "name:sqi_x_variant":[
        "Llugagji"
    ],
    "name:srp_x_preferred":[
        "Luga\u0111ija"
    ],
    "name:srp_x_variant":[
        "\u041b\u0443\u0433\u0445\u0430\u0452\u0438\u0458\u0430",
        "Luka\u0107ija"
    ],
    "wof:name":"Llugagji",
    "wof:placetype":"locality"
},
  "geometry": {"coordinates":[20.47306,42.55667],"type":"Point"}
}