{
  "type": "Feature",
  "properties": {
    "gn:admin1_code":"10096859.0",
    "gn:admin2_code":"5.0",
    "gn:asciiname":"Bec",
    "gn:country_code":"XK",
    "gn:dem":359,
    "gn:feature_class":"P",
    "gn:feature_code":"PPLL",
    "gn:name":"Bec",
    "gn:population":0,
    "gn:timezone":"Europe/Belgrade",
    "iso:country":"XK",
    "name:srp_x_preferred":[
        "\u0411\u0435\u0446"
    ],
    "name:srp_x_variant":[
        "Bec"
    ],
    "wof:name":"Bec",
    "wof:placetype":"locality"
},
  "geometry": {"coordinates":[20.44944,42.44306],"type":"Point"}
}