{
  "type": "Feature",
  "properties": {
    "gn:admin1_code":"10097360.0",
    "gn:admin2_code":"19.0",
    "gn:asciiname":"Blac Mahala",
    "gn:country_code":"XK",
    "gn:dem":784,
    "gn:feature_class":"P",
    "gn:feature_code":"PPL",
    "gn:name":"Blac Mahala",
    "gn:population":0,
    "gn:timezone":"Europe/Belgrade",
    "iso:country":"XK",
    "name:srp_x_preferred":[
        "Blac Mahala"
    ],
    "wof:name":"Blac Mahala",
    "wof:placetype":"locality"
},
  "geometry": {"coordinates":[21.27544,42.81024],"type":"Point"}
}