{
  "type": "Feature",
  "properties": {
    "gn:admin1_code":"10097359.0",
    "gn:admin2_code":"11.0",
    "gn:asciiname":"Krivoc",
    "gn:country_code":"XK",
    "gn:dem":571,
    "gn:feature_class":"P",
    "gn:feature_code":"PPL",
    "gn:name":"Krivoc",
    "gn:population":0,
    "gn:timezone":"Europe/Belgrade",
    "iso:country":"XK",
    "name:srp_x_preferred":[
        "Krivoc"
    ],
    "wof:name":"Krivoc",
    "wof:placetype":"locality"
},
  "geometry": {"coordinates":[20.6625,42.58833],"type":"Point"}
}