{
  "type": "Feature",
  "properties": {
    "gn:admin1_code":"10097360.0",
    "gn:admin2_code":"19.0",
    "gn:asciiname":"Gornje Ljupce",
    "gn:country_code":"XK",
    "gn:dem":644,
    "gn:feature_class":"P",
    "gn:feature_code":"PPL",
    "gn:name":"Gornje Ljup\u010de",
    "gn:population":0,
    "gn:timezone":"Europe/Belgrade",
    "iso:country":"XK",
    "name:ceb_x_preferred":[
        "Gornje Ljup\u010de"
    ],
    "name:fra_x_preferred":[
        "Gornje Ljup\u010de"
    ],
    "name:sqi_x_preferred":[
        "Lup\u00e7 i Ep\u00ebrm"
    ],
    "name:sqi_x_variant":[
        "Gurisht\u00eb",
        "Gurishta",
        "Lup\u00e7i i Ep\u00ebrm"
    ],
    "name:srp_x_preferred":[
        "Gornje Ljup\u010de"
    ],
    "name:srp_x_variant":[
        "\u0413\u043e\u0440\u045a\u0435 \u0409\u0443\u043f\u0447\u0435"
    ],
    "name:swe_x_preferred":[
        "Gornje Ljup\u010de"
    ],
    "name:und_x_variant":[
        "Gurishta",
        "Lup\u00e7i i Ep\u00ebrm",
        "Gurisht\u00eb"
    ],
    "wof:name":"Gornje Ljupce",
    "wof:placetype":"locality"
},
  "geometry": {"coordinates":[21.09444,42.85417],"type":"Point"}
}