{
  "type": "Feature",
  "properties": {
    "gn:admin1_code":"10097360.0",
    "gn:admin2_code":"7.0",
    "gn:asciiname":"Kisna Reka",
    "gn:country_code":"XK",
    "gn:dem":613,
    "gn:feature_class":"P",
    "gn:feature_code":"PPL",
    "gn:name":"Ki\u0161na Reka",
    "gn:population":0,
    "gn:timezone":"Europe/Belgrade",
    "iso:country":"XK",
    "name:sqi_x_preferred":[
        "Kishnarek\u00eb"
    ],
    "name:sqi_x_variant":[
        "K\u00ebrzharek\u00eb",
        "Kisha e Nrek\u00ebs",
        "Kishna Reka",
        "Kizhareka",
        "Lumisht\u00eb",
        "Lumishta"
    ],
    "name:srp_x_preferred":[
        "\u041a\u0438\u0448\u043d\u0430 \u0420\u0435\u043a\u0430"
    ],
    "name:srp_x_variant":[
        "Ki\u0161na Reka",
        "Kr\u017ena Reka"
    ],
    "name:und_x_variant":[
        "Lumisht\u00eb",
        "Kishna Reka",
        "Lumishta",
        "Kizhareka",
        "Kr\u017ena Reka",
        "Kisha e Nrek\u00ebs"
    ],
    "wof:name":"Kisna Reka",
    "wof:placetype":"locality"
},
  "geometry": {"coordinates":[20.89083,42.55306],"type":"Point"}
}