{
  "type": "Feature",
  "properties": {
    "gn:admin1_code":"10096859.0",
    "gn:admin2_code":"5.0",
    "gn:asciiname":"Bardhaniq",
    "gn:country_code":"XK",
    "gn:dem":442,
    "gn:feature_class":"P",
    "gn:feature_code":"PPL",
    "gn:name":"Bardhaniq",
    "gn:population":0,
    "gn:timezone":"Europe/Belgrade",
    "iso:country":"XK",
    "name:sqi_x_preferred":[
        "Bardhaniq"
    ],
    "name:sqi_x_variant":[
        "Bordeni\u00e7"
    ],
    "name:srp_x_preferred":[
        "Bardoni\u0107"
    ],
    "name:srp_x_variant":[
        "\u0411\u0430\u0440\u0434\u043e\u043d\u0438\u045b"
    ],
    "wof:name":"Bardhaniq",
    "wof:placetype":"locality"
},
  "geometry": {"coordinates":[20.44778,42.52528],"type":"Point"}
}