{
  "type": "Feature",
  "properties": {
    "gn:admin1_code":"10097361.0",
    "gn:admin2_code":"26.0",
    "gn:asciiname":"Zekoli",
    "gn:country_code":"XK",
    "gn:dem":663,
    "gn:feature_class":"P",
    "gn:feature_code":"PPL",
    "gn:name":"Zekoli",
    "gn:population":0,
    "gn:timezone":"Europe/Belgrade",
    "iso:country":"XK",
    "name:srp_x_preferred":[
        "Zekoli"
    ],
    "name:srp_x_variant":[
        "Zekovi\u0107"
    ],
    "wof:name":"Zekoli",
    "wof:placetype":"locality"
},
  "geometry": {"coordinates":[20.86083,42.43444],"type":"Point"}
}