{
  "type": "Feature",
  "properties": {
    "gn:admin1_code":"10097359.0",
    "gn:admin2_code":"18.0",
    "gn:asciiname":"Glavicica",
    "gn:country_code":"XK",
    "gn:dem":435,
    "gn:feature_class":"P",
    "gn:feature_code":"PPL",
    "gn:name":"Glavi\u010dica",
    "gn:population":0,
    "gn:timezone":"Europe/Belgrade",
    "iso:country":"XK",
    "name:sqi_x_preferred":[
        "Gllavi\u00e7ic\u00eb"
    ],
    "name:sqi_x_variant":[
        "Gllavigjic\u00eb"
    ],
    "name:srp_x_preferred":[
        "Glavi\u010dica"
    ],
    "name:srp_x_variant":[
        "\u0413\u043b\u0430\u0432\u0438\u0447\u0438\u0446\u0430"
    ],
    "name:und_x_variant":[
        "Gllavigjic\u00eb"
    ],
    "wof:name":"Glavicica",
    "wof:placetype":"locality"
},
  "geometry": {"coordinates":[20.42444,42.63889],"type":"Point"}
}