{
  "type": "Feature",
  "properties": {
    "gn:admin1_code":"10097358.0",
    "gn:admin2_code":"25.0",
    "gn:asciiname":"Kostrc",
    "gn:country_code":"XK",
    "gn:dem":677,
    "gn:feature_class":"P",
    "gn:feature_code":"PPLL",
    "gn:name":"Kostrc",
    "gn:population":0,
    "gn:timezone":"Europe/Belgrade",
    "iso:country":"XK",
    "name:sqi_x_preferred":[
        "Kost\u00ebrc"
    ],
    "name:srp_x_preferred":[
        "\u041a\u043e\u0441\u0442\u0440\u0446"
    ],
    "name:srp_x_variant":[
        "Kostrc"
    ],
    "name:und_x_variant":[
        "Kost\u00ebrc"
    ],
    "wof:name":"Kostrc",
    "wof:placetype":"locality"
},
  "geometry": {"coordinates":[20.68861,42.78278],"type":"Point"}
}