{
  "type": "Feature",
  "properties": {
    "gn:admin1_code":"10097358.0",
    "gn:admin2_code":"28.0",
    "gn:asciiname":"Donji Svracak",
    "gn:country_code":"XK",
    "gn:dem":547,
    "gn:feature_class":"P",
    "gn:feature_code":"PPLL",
    "gn:name":"Donji Svra\u010dak",
    "gn:population":0,
    "gn:timezone":"Europe/Belgrade",
    "iso:country":"XK",
    "name:sqi_x_preferred":[
        "Svara\u00e7ak i Posht\u00ebm"
    ],
    "name:sqi_x_variant":[
        "Svara\u00e7aku i Posht\u00ebm",
        "Sfara\u00e7ak i Posht\u00ebm",
        "Sfaracaku i Posht\u00ebm"
    ],
    "name:srp_x_preferred":[
        "Donji Svra\u010dak"
    ],
    "name:srp_x_variant":[
        "\u0414\u043e\u045a\u0438 \u0421\u0432\u0440\u0430\u0447\u0430\u043a"
    ],
    "wof:name":"Donji Svracak",
    "wof:placetype":"locality"
},
  "geometry": {"coordinates":[21.00506,42.80442],"type":"Point"}
}