{
  "type": "Feature",
  "properties": {
    "gn:admin1_code":"10097359.0",
    "gn:admin2_code":"8.0",
    "gn:asciiname":"Paljevo",
    "gn:country_code":"XK",
    "gn:dem":564,
    "gn:feature_class":"P",
    "gn:feature_code":"PPL",
    "gn:name":"Paljevo",
    "gn:population":0,
    "gn:timezone":"Europe/Belgrade",
    "iso:country":"XK",
    "name:ceb_x_preferred":[
        "Paljevo"
    ],
    "name:slv_x_preferred":[
        "Paljevo"
    ],
    "name:srp_x_preferred":[
        "Paljevo"
    ],
    "name:swe_x_preferred":[
        "Paljevo"
    ],
    "wof:name":"Paljevo",
    "wof:placetype":"locality"
},
  "geometry": {"coordinates":[20.59028,42.70111],"type":"Point"}
}