{
  "type": "Feature",
  "properties": {
    "gn:admin1_code":"10097358.0",
    "gn:admin2_code":"30.0",
    "gn:asciiname":"Banovdoll",
    "gn:country_code":"XK",
    "gn:dem":619,
    "gn:feature_class":"P",
    "gn:feature_code":"PPL",
    "gn:name":"Banovdoll",
    "gn:population":0,
    "gn:timezone":"Europe/Belgrade",
    "iso:country":"XK",
    "name:sqi_x_preferred":[
        "Banovdo"
    ],
    "name:sqi_x_variant":[
        "Banovdoll",
        "Banovd\u00eb"
    ],
    "name:srp_x_preferred":[
        "Banov Do"
    ],
    "name:und_x_variant":[
        "Banovd\u00eb"
    ],
    "wof:name":"Banovdoll",
    "wof:placetype":"locality"
},
  "geometry": {"coordinates":[20.78889,42.93722],"type":"Point"}
}