{
  "type": "Feature",
  "properties": {
    "gn:admin1_code":"10097358.0",
    "gn:admin2_code":"29.0",
    "gn:asciiname":"Zagulje",
    "gn:country_code":"XK",
    "gn:dem":1052,
    "gn:feature_class":"P",
    "gn:feature_code":"PPL",
    "gn:name":"Zagulje",
    "gn:population":0,
    "gn:timezone":"Europe/Belgrade",
    "iso:country":"XK",
    "name:sqi_x_preferred":[
        "Zagul"
    ],
    "name:srp_x_preferred":[
        "\u0417\u0430\u0433\u0443\u0459\u0435"
    ],
    "name:srp_x_variant":[
        "Zagulje"
    ],
    "name:und_x_variant":[
        "Zagulj"
    ],
    "wof:name":"Zagulje",
    "wof:placetype":"locality"
},
  "geometry": {"coordinates":[20.65083,42.88222],"type":"Point"}
}