{
  "type": "Feature",
  "properties": {
    "gn:admin1_code":"10097358.0",
    "gn:admin2_code":"28.0",
    "gn:asciiname":"Dobra Luka",
    "gn:country_code":"XK",
    "gn:dem":524,
    "gn:feature_class":"P",
    "gn:feature_code":"PPL",
    "gn:name":"Dobra Luka",
    "gn:population":0,
    "gn:timezone":"Europe/Belgrade",
    "iso:country":"XK",
    "name:sqi_x_preferred":[
        "Dobrilluk"
    ],
    "name:sqi_x_variant":[
        "Dobr\u00eblluk",
        "Dob\u00ebrlluk\u00eb",
        "Dobrilluc"
    ],
    "name:srp_x_preferred":[
        "Dobra Luka"
    ],
    "name:srp_x_variant":[
        "\u0414\u043e\u0431\u0440\u0430 \u041b\u0443\u043a\u0430"
    ],
    "name:und_x_variant":[
        "Dobrilluc"
    ],
    "wof:name":"Dobra Luka",
    "wof:placetype":"locality"
},
  "geometry": {"coordinates":[20.94639,42.84472],"type":"Point"}
}