{
  "type": "Feature",
  "properties": {
    "gn:admin1_code":"10097357.0",
    "gn:admin2_code":"37.0",
    "gn:asciiname":"Pancelo",
    "gn:country_code":"XK",
    "gn:dem":476,
    "gn:feature_class":"P",
    "gn:feature_code":"PPL",
    "gn:name":"Pan\u010delo",
    "gn:population":0,
    "gn:timezone":"Europe/Belgrade",
    "iso:country":"XK",
    "name:sqi_x_preferred":[
        "Pan\u00e7ell\u00eb"
    ],
    "name:sqi_x_variant":[
        "Panqel\u00eb",
        "Panqela",
        "Pan\u00e7el\u00eb",
        "Pan\u00e7ela"
    ],
    "name:srp_x_preferred":[
        "\u041f\u0430\u043d\u0447\u0435\u043b\u043e"
    ],
    "name:srp_x_variant":[
        "Pan\u010delo"
    ],
    "wof:name":"Pancelo",
    "wof:placetype":"locality"
},
  "geometry": {"coordinates":[21.56806,42.50167],"type":"Point"}
}