{
  "type": "Feature",
  "properties": {
    "gn:admin1_code":"10096138.0",
    "gn:admin2_code":"23.0",
    "gn:asciiname":"Gotovusa",
    "gn:country_code":"XK",
    "gn:dem":858,
    "gn:feature_class":"P",
    "gn:feature_code":"PPL",
    "gn:name":"Gotovu\u0161a",
    "gn:population":0,
    "gn:timezone":"Europe/Belgrade",
    "iso:country":"XK",
    "name:ceb_x_preferred":[
        "Gotovu\u0161a"
    ],
    "name:fra_x_preferred":[
        "Gotovu\u0161a"
    ],
    "name:sqi_x_preferred":[
        "Gotovush\u00eb"
    ],
    "name:sqi_x_variant":[
        "G\u00ebtovush\u00eb",
        "Gotovusha"
    ],
    "name:srp_x_preferred":[
        "\u0413\u043e\u0442\u043e\u0432\u0443\u0448\u0430"
    ],
    "name:srp_x_variant":[
        "Gotovu\u0161a",
        "Gotovu\u0161e"
    ],
    "name:und_x_variant":[
        "Gotovu\u0161e",
        "G\u00ebtovush\u00eb"
    ],
    "wof:name":"Gotovusa",
    "wof:placetype":"locality"
},
  "geometry": {"coordinates":[21.07278,42.24861],"type":"Point"}
}