{
  "type": "Feature",
  "properties": {
    "gn:admin1_code":"10097361.0",
    "gn:admin2_code":"21.0",
    "gn:asciiname":"Lukanja",
    "gn:country_code":"XK",
    "gn:dem":331,
    "gn:feature_class":"P",
    "gn:feature_code":"PPL",
    "gn:name":"Lukanja",
    "gn:population":0,
    "gn:timezone":"Europe/Belgrade",
    "iso:country":"XK",
    "name:sqi_x_preferred":[
        "Lukinaj"
    ],
    "name:sqi_x_variant":[
        "Lukinjaj"
    ],
    "name:srp_x_preferred":[
        "Lukanja"
    ],
    "name:srp_x_variant":[
        "\u0409\u0443\u043a\u0438\u043d\u0430\u0458"
    ],
    "name:und_x_variant":[
        "Lukinjaj",
        "Ljukinaj",
        "Ljukinjaj",
        "Lukinje"
    ],
    "wof:name":"Lukanja",
    "wof:placetype":"locality"
},
  "geometry": {"coordinates":[20.61528,42.29417],"type":"Point"}
}