{
  "type": "Feature",
  "properties": {
    "gn:admin1_code":"10097360.0",
    "gn:admin2_code":"19.0",
    "gn:asciiname":"Ravnina",
    "gn:country_code":"XK",
    "gn:dem":659,
    "gn:feature_class":"P",
    "gn:feature_code":"PPLL",
    "gn:name":"Ravnina",
    "gn:population":0,
    "gn:timezone":"Europe/Belgrade",
    "iso:country":"XK",
    "name:srp_x_preferred":[
        "Ravnina"
    ],
    "wof:name":"Ravnina",
    "wof:placetype":"locality"
},
  "geometry": {"coordinates":[21.15502,42.96814000000001],"type":"Point"}
}