{
  "type": "Feature",
  "properties": {
    "gn:admin1_code":"10097359.0",
    "gn:admin2_code":"18.0",
    "gn:asciiname":"Doberdol",
    "gn:country_code":"XK",
    "gn:dem":476,
    "gn:feature_class":"P",
    "gn:feature_code":"PPLL",
    "gn:name":"Dob\u00ebrdol",
    "gn:population":0,
    "gn:timezone":"Europe/Belgrade",
    "iso:country":"XK",
    "name:und_x_variant":[
        "Dob\u00ebrdol"
    ],
    "wof:name":"Doberdol",
    "wof:placetype":"locality"
},
  "geometry": {"coordinates":[20.38194,42.6025],"type":"Point"}
}