{
  "type": "Feature",
  "properties": {
    "gn:admin1_code":"10097361.0",
    "gn:admin2_code":"2.0",
    "gn:asciiname":"Kosavce",
    "gn:country_code":"XK",
    "gn:dem":1203,
    "gn:feature_class":"P",
    "gn:feature_code":"PPL",
    "gn:name":"Kosavce",
    "gn:population":0,
    "gn:timezone":"Europe/Belgrade",
    "iso:country":"XK",
    "name:sqi_x_preferred":[
        "Kosav\u00eb"
    ],
    "name:sqi_x_variant":[
        "Kosav\u00e7i",
        "Kasafc"
    ],
    "name:srp_x_preferred":[
        "\u041a\u043e\u0441\u0430\u0432\u0446\u0435"
    ],
    "name:srp_x_variant":[
        "Kosavce"
    ],
    "name:und_x_variant":[
        "Kosovce",
        "Kosavc",
        "Kosovci"
    ],
    "wof:name":"Kosavce",
    "wof:placetype":"locality"
},
  "geometry": {"coordinates":[20.70222,42.08972],"type":"Point"}
}