{
  "type": "Feature",
  "properties": {
    "gn:admin1_code":"10097358.0",
    "gn:admin2_code":"25.0",
    "gn:asciiname":"Ozrim",
    "gn:country_code":"XK",
    "gn:dem":528,
    "gn:feature_class":"P",
    "gn:feature_code":"PPL",
    "gn:name":"Ozrim",
    "gn:population":0,
    "gn:timezone":"Europe/Belgrade",
    "iso:country":"XK",
    "name:srp_x_preferred":[
        "Ozrim"
    ],
    "wof:name":"Ozrim",
    "wof:placetype":"locality"
},
  "geometry": {"coordinates":[20.63472,42.70944],"type":"Point"}
}