{
  "type": "Feature",
  "properties": {
    "gn:admin1_code":"10097358.0",
    "gn:admin2_code":"12.0",
    "gn:asciiname":"Majdevo",
    "gn:country_code":"XK",
    "gn:dem":702,
    "gn:feature_class":"P",
    "gn:feature_code":"PPL",
    "gn:name":"Majdevo",
    "gn:population":0,
    "gn:timezone":"Europe/Belgrade",
    "iso:country":"XK",
    "name:sqi_x_preferred":[
        "Majdev\u00eb"
    ],
    "name:srp_x_preferred":[
        "\u041c\u0430\u0458\u0434\u0435\u0432\u043e"
    ],
    "name:srp_x_variant":[
        "Majdevo"
    ],
    "wof:name":"Majdevo",
    "wof:placetype":"locality"
},
  "geometry": {"coordinates":[20.83083,43.14],"type":"Point"}
}