{
  "type": "Feature",
  "properties": {
    "gn:admin1_code":"10097360.0",
    "gn:admin2_code":"17.0",
    "gn:asciiname":"Leshkoshiq",
    "gn:country_code":"XK",
    "gn:dem":597,
    "gn:feature_class":"P",
    "gn:feature_code":"PPL",
    "gn:name":"Leshkoshiq",
    "gn:population":0,
    "gn:timezone":"Europe/Belgrade",
    "iso:country":"XK",
    "name:sqi_x_preferred":[
        "Leskov\u00e7ic"
    ],
    "name:sqi_x_variant":[
        "Leshkoshiq",
        "L\u00ebskoshic"
    ],
    "name:srp_x_preferred":[
        "Leskov\u010di\u0107"
    ],
    "name:srp_x_variant":[
        "\u041b\u0435\u0441\u043a\u043e\u0432\u0447\u0438\u045b"
    ],
    "wof:name":"Leshkoshiq",
    "wof:placetype":"locality"
},
  "geometry": {"coordinates":[21.03569,42.68456],"type":"Point"}
}