{
  "type": "Feature",
  "properties": {
    "gn:admin1_code":"10097357.0",
    "gn:admin2_code":"27.0",
    "gn:asciiname":"Ribnik",
    "gn:country_code":"XK",
    "gn:dem":516,
    "gn:feature_class":"P",
    "gn:feature_code":"PPL",
    "gn:name":"Ribnik",
    "gn:population":0,
    "gn:timezone":"Europe/Belgrade",
    "iso:country":"XK",
    "name:bos_x_preferred":[
        "Ribnik"
    ],
    "name:bul_x_preferred":[
        "\u0420\u0438\u0431\u043d\u0438\u043a"
    ],
    "name:ceb_x_preferred":[
        "Ribnik"
    ],
    "name:deu_x_preferred":[
        "Ribnik"
    ],
    "name:fra_x_preferred":[
        "Ribnik"
    ],
    "name:hrv_x_preferred":[
        "Ribnik"
    ],
    "name:hye_x_preferred":[
        "\u054c\u056b\u0562\u0576\u056b\u056f"
    ],
    "name:ita_x_preferred":[
        "Ribnik"
    ],
    "name:nld_x_preferred":[
        "Ribnik"
    ],
    "name:ron_x_preferred":[
        "Ribnik"
    ],
    "name:rus_x_preferred":[
        "\u0420\u0438\u0431\u043d\u0438\u043a"
    ],
    "name:slv_x_preferred":[
        "Ribnik"
    ],
    "name:spa_x_preferred":[
        "Ribnik"
    ],
    "name:sqi_x_preferred":[
        "Remniku"
    ],
    "name:sqi_x_variant":[
        "Remnik"
    ],
    "name:srp_x_preferred":[
        "Ribnik"
    ],
    "name:srp_x_variant":[
        "\u0420\u0438\u0431\u043d\u0438\u043a"
    ],
    "name:swe_x_preferred":[
        "Ribnik"
    ],
    "wof:name":"Ribnik",
    "wof:placetype":"locality"
},
  "geometry": {"coordinates":[21.44222,42.36],"type":"Point"}
}