{
  "type": "Feature",
  "properties": {
    "gn:admin1_code":"10097357.0",
    "gn:admin2_code":"6.0",
    "gn:asciiname":"Burince",
    "gn:country_code":"XK",
    "gn:dem":786,
    "gn:feature_class":"P",
    "gn:feature_code":"PPL",
    "gn:name":"Burince",
    "gn:population":0,
    "gn:timezone":"Europe/Belgrade",
    "iso:country":"XK",
    "name:sqi_x_preferred":[
        "Burinc\u00eb"
    ],
    "name:sqi_x_variant":[
        "Burinica",
        "Burinic\u00eb"
    ],
    "name:srp_x_preferred":[
        "Burince"
    ],
    "name:srp_x_variant":[
        "\u0411\u0443\u0440\u0438\u043d\u0446\u0435"
    ],
    "name:und_x_variant":[
        "Burinice-a"
    ],
    "wof:name":"Burince",
    "wof:placetype":"locality"
},
  "geometry": {"coordinates":[21.55056,42.39639],"type":"Point"}
}