{
  "type": "Feature",
  "properties": {
    "gn:country":"XK",
    "gn:fcode":"PPLA",
    "gn:pop":11612,
    "iso:country":"XK",
    "name:ara_x_preferred":[
        "\u0623\u0648\u0628\u064a\u0644\u064a\u062a\u0634"
    ],
    "name:ben_x_preferred":[
        "\u0993\u09ac\u09bf\u09b2\u09bf\u0995"
    ],
    "name:bul_x_preferred":[
        "\u041e\u0431\u0438\u043b\u0438\u0447"
    ],
    "name:dan_x_preferred":[
        "Obili\u0107"
    ],
    "name:deu_x_preferred":[
        "Obiliq"
    ],
    "name:ell_x_preferred":[
        "\u038c\u03bc\u03c0\u03b9\u03bb\u03b9\u03c4\u03c2"
    ],
    "name:eng_x_preferred":[
        "Obili\u0107"
    ],
    "name:fas_x_preferred":[
        "\u0627\u0648\u0628\u06cc\u0644\u06cc\u0686"
    ],
    "name:fin_x_preferred":[
        "Obili\u0107"
    ],
    "name:fra_x_preferred":[
        "Obili\u0107"
    ],
    "name:guj_x_preferred":[
        "\u0a93\u0aac\u0abf\u0ab2\u0abf\u0a95"
    ],
    "name:hin_x_preferred":[
        "\u0913\u092c\u093f\u0932\u0940\u0915"
    ],
    "name:hrv_x_preferred":[
        "Obili\u0107"
    ],
    "name:hun_x_preferred":[
        "Obili\u0107"
    ],
    "name:ind_x_preferred":[
        "Obili\u0107"
    ],
    "name:ita_x_preferred":[
        "Obili\u0107"
    ],
    "name:jpn_x_preferred":[
        "\u30aa\u30d3\u30ea\u30c1"
    ],
    "name:kan_x_preferred":[
        "\u0c92\u0cac\u0cbf\u0cb2\u0cbf\u0c95\u0ccd"
    ],
    "name:kor_x_preferred":[
        "\uc624\ube14\ub9ac\uce20"
    ],
    "name:lav_x_preferred":[
        "Obili\u010da"
    ],
    "name:lit_x_preferred":[
        "Obili\u010dius"
    ],
    "name:mar_x_preferred":[
        "\u0913\u092c\u093f\u0932\u093f\u0915"
    ],
    "name:mkd_x_preferred":[
        "\u041e\u0431\u0438\u043b\u0438\u045c"
    ],
    "name:msa_x_preferred":[
        "Obili\u0107"
    ],
    "name:nld_x_preferred":[
        "Obiliq"
    ],
    "name:nob_x_preferred":[
        "Obili\u0107"
    ],
    "name:nor_x_preferred":[
        "Obiliq"
    ],
    "name:pol_x_preferred":[
        "Obili\u0107"
    ],
    "name:por_x_preferred":[
        "Obili\u0107"
    ],
    "name:ron_x_preferred":[
        "Obili\u0107"
    ],
    "name:rus_x_preferred":[
        "\u041e\u0431\u0438\u043b\u0438\u0447"
    ],
    "name:sin_x_preferred":[
        "\u0d94\u0db6\u0dd2\u0dbd\u0dd2\u0d9a\u0dca"
    ],
    "name:spa_x_preferred":[
        "Obili\u0107"
    ],
    "name:sqi_x_preferred":[
        "Kastriot"
    ],
    "name:sqi_x_variant":[
        "Obiliq",
        "Gllaboder",
        "Kastrioti"
    ],
    "name:srp_x_preferred":[
        "Obili\u0107"
    ],
    "name:srp_x_variant":[
        "\u041e\u0431\u0438\u043b\u0438\u045b"
    ],
    "name:swe_x_preferred":[
        "Obiliq"
    ],
    "name:tam_x_preferred":[
        "\u0b92\u0baa\u0bc0\u0bb2\u0bbf\u0b95\u0bcd"
    ],
    "name:tel_x_preferred":[
        "\u0c13\u0c2c\u0c3f\u0c32\u0c3f\u0c15\u0c4d"
    ],
    "name:tha_x_preferred":[
        "\u0e42\u0e2d\u0e1a\u0e34\u0e25\u0e34\u0e04"
    ],
    "name:tur_x_preferred":[
        "Kastriot"
    ],
    "name:ukr_x_preferred":[
        "\u041e\u0431\u0456\u043b\u0456\u0447"
    ],
    "name:unk_x_variant":[
        "Gllaboder"
    ],
    "name:urd_x_preferred":[
        "\u0627\u0648\u0628\u06cc\u0644\u06cc\u06a9"
    ],
    "name:vie_x_preferred":[
        "Obili\u0107"
    ],
    "name:zho_x_preferred":[
        "\u5967\u6bd4\u5229\u5947"
    ],
    "qs:name":"Obiliq",
    "qs:photos_9r":0,
    "qs:photos_sr":0,
    "qs:pop_sr":"6",
    "wd:wordcount":311,
    "wof:name":"Obiliq",
    "wof:placetype":"locality",
    "wof:population":11612
},
  "geometry": {"coordinates":[21.07028,42.68694],"type":"Point"}
}