{
  "type": "Feature",
  "properties": {
    "gn:admin1_code":"10097360.0",
    "gn:admin2_code":"13.0",
    "gn:asciiname":"Velika Dobranja",
    "gn:country_code":"XK",
    "gn:dem":551,
    "gn:feature_class":"P",
    "gn:feature_code":"PPL",
    "gn:name":"Velika Dobranja",
    "gn:population":0,
    "gn:timezone":"Europe/Belgrade",
    "iso:country":"XK",
    "name:sqi_x_preferred":[
        "Dobraja e Madhe"
    ],
    "name:sqi_x_variant":[
        "Dobraj\u00eb e Madhe"
    ],
    "name:srp_x_preferred":[
        "\u0412\u0435\u043b\u0438\u043a\u0430 \u0414\u043e\u0431\u0440\u0430\u045a\u0430"
    ],
    "name:srp_x_variant":[
        "Velika Dobranja"
    ],
    "name:und_x_variant":[
        "Dobraj\u00eb e Madhe",
        "Dobranja"
    ],
    "wof:name":"Velika Dobranja",
    "wof:placetype":"locality"
},
  "geometry": {"coordinates":[21.04417,42.54333],"type":"Point"}
}