{
  "type": "Feature",
  "properties": {
    "gn:admin1_code":"10097358.0",
    "gn:admin2_code":"28.0",
    "gn:asciiname":"Boshlan",
    "gn:country_code":"XK",
    "gn:dem":975,
    "gn:feature_class":"P",
    "gn:feature_code":"PPL",
    "gn:name":"Boshlan",
    "gn:population":0,
    "gn:timezone":"Europe/Belgrade",
    "iso:country":"XK",
    "name:sqi_x_preferred":[
        "Boshlan"
    ],
    "name:srp_x_preferred":[
        "Bo\u0161ljane"
    ],
    "name:srp_x_variant":[
        "\u0411\u043e\u0448\u0459\u0430\u043d\u0435"
    ],
    "wof:name":"Boshlan",
    "wof:placetype":"locality"
},
  "geometry": {"coordinates":[21.01143,42.91367],"type":"Point"}
}