{
  "type": "Feature",
  "properties": {
    "gn:admin1_code":"10097358.0",
    "gn:admin2_code":"30.0",
    "gn:asciiname":"Doljane",
    "gn:country_code":"XK",
    "gn:dem":531,
    "gn:feature_class":"P",
    "gn:feature_code":"PPL",
    "gn:name":"Doljane",
    "gn:population":0,
    "gn:timezone":"Europe/Belgrade",
    "iso:country":"XK",
    "name:ceb_x_preferred":[
        "Doljane"
    ],
    "name:deu_x_preferred":[
        "Doljane"
    ],
    "name:fra_x_preferred":[
        "Doljane"
    ],
    "name:msa_x_preferred":[
        "Doljane"
    ],
    "name:por_x_preferred":[
        "Doljane"
    ],
    "name:slv_x_preferred":[
        "Doljane"
    ],
    "name:sqi_x_preferred":[
        "Dolan\u00eb"
    ],
    "name:sqi_x_variant":[
        "Dolan"
    ],
    "name:srp_x_preferred":[
        "Doljane"
    ],
    "name:srp_x_variant":[
        "\u0414\u043e\u0459\u0430\u043d\u0435"
    ],
    "name:und_x_variant":[
        "Doljani"
    ],
    "wof:name":"Doljane",
    "wof:placetype":"locality"
},
  "geometry": {"coordinates":[20.81056,42.92694],"type":"Point"}
}