{
  "type": "Feature",
  "properties": {
    "gn:admin1_code":"10097361.0",
    "gn:admin2_code":"14.0",
    "gn:asciiname":"Crni Lug",
    "gn:country_code":"XK",
    "gn:dem":560,
    "gn:feature_class":"P",
    "gn:feature_code":"PPLL",
    "gn:name":"Crni Lug",
    "gn:population":0,
    "gn:timezone":"Europe/Belgrade",
    "iso:country":"XK",
    "name:bul_x_preferred":[
        "\u0426\u044a\u0440\u043d\u0438 \u041b\u0443\u0433"
    ],
    "name:ceb_x_preferred":[
        "Crni Lug"
    ],
    "name:fra_x_preferred":[
        "Crni Lug"
    ],
    "name:msa_x_preferred":[
        "Crni Lug"
    ],
    "name:por_x_preferred":[
        "Crni Lug"
    ],
    "name:slv_x_preferred":[
        "Crni Lug"
    ],
    "name:sqi_x_preferred":[
        "Carraluk\u00eb"
    ],
    "name:srp_x_preferred":[
        "\u0426\u0440\u043d\u0438 \u041b\u0443\u0433"
    ],
    "name:srp_x_variant":[
        "Crni Lug"
    ],
    "name:und_x_variant":[
        "Caralug"
    ],
    "wof:name":"Crni Lug",
    "wof:placetype":"locality"
},
  "geometry": {"coordinates":[20.76917000000001,42.51278],"type":"Point"}
}