{
  "type": "Feature",
  "properties": {
    "gn:admin1_code":"10096138.0",
    "gn:admin2_code":"24.0",
    "gn:asciiname":"Muzicane",
    "gn:country_code":"XK",
    "gn:dem":553,
    "gn:feature_class":"P",
    "gn:feature_code":"PPL",
    "gn:name":"Mu\u017ei\u010dane",
    "gn:population":0,
    "gn:timezone":"Europe/Belgrade",
    "iso:country":"XK",
    "name:sqi_x_preferred":[
        "Muzeqin\u00eb"
    ],
    "name:sqi_x_variant":[
        "Muzhi\u00e7an",
        "Muzhi\u00e7ani"
    ],
    "name:srp_x_preferred":[
        "\u041c\u0443\u0436\u0438\u0447\u0430\u043d\u0435"
    ],
    "name:srp_x_variant":[
        "Mu\u017ei\u010dane"
    ],
    "name:und_x_variant":[
        "Muzhi\u00e7ani"
    ],
    "wof:name":"Muzicane",
    "wof:placetype":"locality"
},
  "geometry": {"coordinates":[21.09444,42.45],"type":"Point"}
}