{
  "type": "Feature",
  "properties": {
    "gn:admin1_code":"10097359.0",
    "gn:admin2_code":"18.0",
    "gn:asciiname":"Gjevukaj",
    "gn:country_code":"XK",
    "gn:dem":1227,
    "gn:feature_class":"P",
    "gn:feature_code":"PPL",
    "gn:name":"Gjevukaj",
    "gn:population":0,
    "gn:timezone":"Europe/Belgrade",
    "iso:country":"XK",
    "name:und_x_variant":[
        "Deinikaj"
    ],
    "wof:name":"Gjevukaj",
    "wof:placetype":"locality"
},
  "geometry": {"coordinates":[20.07278,42.69194],"type":"Point"}
}