{
  "type": "Feature",
  "properties": {
    "gn:admin1_code":"10096138.0",
    "gn:admin2_code":"3.0",
    "gn:asciiname":"Kamena Glava",
    "gn:country_code":"XK",
    "gn:dem":562,
    "gn:feature_class":"P",
    "gn:feature_code":"PPLL",
    "gn:name":"Kamena Glava",
    "gn:population":0,
    "gn:timezone":"Europe/Belgrade",
    "iso:country":"XK",
    "name:sqi_x_preferred":[
        "Komogllav\u00eb"
    ],
    "name:srp_x_preferred":[
        "Kamena Glava"
    ],
    "name:srp_x_variant":[
        "\u041a\u0430\u043c\u0435\u043d\u0430 \u0413\u043b\u0430\u0432\u0430"
    ],
    "wof:name":"Kamena Glava",
    "wof:placetype":"locality"
},
  "geometry": {"coordinates":[21.21583,42.34222000000001],"type":"Point"}
}