{
  "type": "Feature",
  "properties": {
    "gn:admin1_code":"10097360.0",
    "gn:admin2_code":"19.0",
    "gn:asciiname":"Sakovica",
    "gn:country_code":"XK",
    "gn:dem":564,
    "gn:feature_class":"P",
    "gn:feature_code":"PPL",
    "gn:name":"\u0160akovica",
    "gn:population":0,
    "gn:timezone":"Europe/Belgrade",
    "iso:country":"XK",
    "name:sqi_x_preferred":[
        "Shakovic\u00eb"
    ],
    "name:sqi_x_variant":[
        "Shajkovic\u00eb",
        "Shejkovic\u00eb",
        "Suk\u00eb"
    ],
    "name:srp_x_preferred":[
        "\u0428\u0430\u043a\u043e\u0432\u0438\u0446\u0430"
    ],
    "name:srp_x_variant":[
        "\u0160akovica",
        "\u0160ukovac"
    ],
    "name:und_x_variant":[
        "Suka",
        "Shakovica"
    ],
    "wof:name":"Sakovica",
    "wof:placetype":"locality"
},
  "geometry": {"coordinates":[21.17,42.81306],"type":"Point"}
}