{
  "type": "Feature",
  "properties": {
    "gn:admin1_code":"10097360.0",
    "gn:admin2_code":"13.0",
    "gn:asciiname":"Oklap",
    "gn:country_code":"XK",
    "gn:dem":641,
    "gn:feature_class":"P",
    "gn:feature_code":"PPLL",
    "gn:name":"Oklap",
    "gn:population":0,
    "gn:timezone":"Europe/Belgrade",
    "iso:country":"XK",
    "name:sqi_x_preferred":[
        "Akllap"
    ],
    "name:srp_x_preferred":[
        "\u041e\u043a\u043b\u0430\u043f"
    ],
    "name:srp_x_variant":[
        "Oklap"
    ],
    "name:und_x_variant":[
        "Akllap"
    ],
    "wof:name":"Oklap",
    "wof:placetype":"locality"
},
  "geometry": {"coordinates":[21.24091,42.54097],"type":"Point"}
}