{
  "type": "Feature",
  "properties": {
    "gn:admin1_code":"10097359.0",
    "gn:admin2_code":"11.0",
    "gn:asciiname":"Dugenjive",
    "gn:country_code":"XK",
    "gn:dem":398,
    "gn:feature_class":"P",
    "gn:feature_code":"PPL",
    "gn:name":"Dugenjive",
    "gn:population":0,
    "gn:timezone":"Europe/Belgrade",
    "iso:country":"XK",
    "name:sqi_x_preferred":[
        "Arat e Gjata"
    ],
    "name:sqi_x_variant":[
        "Dugajev\u00eb",
        "Dukajev\u00eb"
    ],
    "name:srp_x_preferred":[
        "Dugenjive"
    ],
    "name:srp_x_variant":[
        "\u0414\u0443\u0433\u0435\u045a\u0438\u0432\u0435",
        "\u0414\u0443\u0433\u043e\u045a\u0438\u0432\u0435",
        "Dugonjive"
    ],
    "name:und_x_variant":[
        "Duge Njuve",
        "Duganjive",
        "Dukati",
        "Dukat",
        "Dugajeva"
    ],
    "wof:name":"Dugenjive",
    "wof:placetype":"locality"
},
  "geometry": {"coordinates":[20.50472,42.59611],"type":"Point"}
}