{
  "type": "Feature",
  "properties": {
    "gn:admin1_code":"10096859.0",
    "gn:admin2_code":"5.0",
    "gn:asciiname":"Smaq",
    "gn:country_code":"XK",
    "gn:dem":412,
    "gn:feature_class":"P",
    "gn:feature_code":"PPL",
    "gn:name":"Smaq",
    "gn:population":0,
    "gn:timezone":"Europe/Belgrade",
    "iso:country":"XK",
    "name:sqi_x_preferred":[
        "Sma\u00e7\u00eb"
    ],
    "name:sqi_x_variant":[
        "Smaq"
    ],
    "name:srp_x_preferred":[
        "Sma\u0107"
    ],
    "name:srp_x_variant":[
        "\u0421\u043c\u0430\u045b"
    ],
    "wof:name":"Smaq",
    "wof:placetype":"locality"
},
  "geometry": {"coordinates":[20.50472,42.33583],"type":"Point"}
}