{
  "type": "Feature",
  "properties": {
    "gn:admin1_code":"10097360.0",
    "gn:admin2_code":"20.0",
    "gn:asciiname":"Pasovic Mahala",
    "gn:country_code":"XK",
    "gn:dem":888,
    "gn:feature_class":"P",
    "gn:feature_code":"PPL",
    "gn:name":"Pasovi\u0107 Mahala",
    "gn:population":0,
    "gn:timezone":"Europe/Belgrade",
    "iso:country":"XK",
    "name:srp_x_preferred":[
        "Pasovi\u0107 Mahala"
    ],
    "name:srp_x_variant":[
        "Mahala Pasovi\u0107"
    ],
    "name:und_x_variant":[
        "Mahala Pasovi\u0107"
    ],
    "wof:name":"Pasovic Mahala",
    "wof:placetype":"locality"
},
  "geometry": {"coordinates":[21.40389,42.67028],"type":"Point"}
}