{
  "type": "Feature",
  "properties": {
    "gn:admin1_code":"10097361.0",
    "gn:admin2_code":"26.0",
    "gn:asciiname":"Studencane",
    "gn:country_code":"XK",
    "gn:dem":374,
    "gn:feature_class":"P",
    "gn:feature_code":"PPL",
    "gn:name":"Studen\u010dane",
    "gn:population":0,
    "gn:timezone":"Europe/Belgrade",
    "iso:country":"XK",
    "name:sqi_x_preferred":[
        "Studenqan"
    ],
    "name:sqi_x_variant":[
        "Studen\u00e7an",
        "Strude\u00e7ane"
    ],
    "name:srp_x_preferred":[
        "\u0421\u0442\u0443\u0434\u0435\u043d\u0447\u0430\u043d\u0435"
    ],
    "name:srp_x_variant":[
        "Studen\u010dane"
    ],
    "name:und_x_variant":[
        "Strude\u00e7ane",
        "Studen\u00e7an"
    ],
    "wof:name":"Studencane",
    "wof:placetype":"locality"
},
  "geometry": {"coordinates":[20.75861,42.35861],"type":"Point"}
}