{
  "type": "Feature",
  "properties": {
    "gn:admin1_code":"10097361.0",
    "gn:admin2_code":"21.0",
    "gn:asciiname":"Randubrava",
    "gn:country_code":"XK",
    "gn:dem":376,
    "gn:feature_class":"P",
    "gn:feature_code":"PPL",
    "gn:name":"Randubrava",
    "gn:population":0,
    "gn:timezone":"Europe/Belgrade",
    "iso:country":"XK",
    "name:sqi_x_preferred":[
        "Randubrav\u00eb"
    ],
    "name:sqi_x_variant":[
        "Randobrav\u00eb"
    ],
    "name:srp_x_preferred":[
        "Randubrava"
    ],
    "name:srp_x_variant":[
        "\u0420\u0430\u043d\u0434\u0443\u0431\u0440\u0430\u0432\u0430"
    ],
    "wof:name":"Randubrava",
    "wof:placetype":"locality"
},
  "geometry": {"coordinates":[20.67083,42.31944],"type":"Point"}
}