{
  "type": "Feature",
  "properties": {
    "gn:admin1_code":"10096138.0",
    "gn:admin2_code":"3.0",
    "gn:asciiname":"Prorok",
    "gn:country_code":"XK",
    "gn:dem":938,
    "gn:feature_class":"P",
    "gn:feature_code":"PPL",
    "gn:name":"Prorok",
    "gn:population":0,
    "gn:timezone":"Europe/Belgrade",
    "iso:country":"XK",
    "name:srp_x_preferred":[
        "Prorok"
    ],
    "name:und_x_variant":[
        "Prerok"
    ],
    "wof:name":"Prorok",
    "wof:placetype":"locality"
},
  "geometry": {"coordinates":[21.03306,42.37694000000001],"type":"Point"}
}