{
  "type": "Feature",
  "properties": {
    "gn:admin1_code":"10097360.0",
    "gn:admin2_code":"7.0",
    "gn:asciiname":"Gornja Koretica",
    "gn:country_code":"XK",
    "gn:dem":618,
    "gn:feature_class":"P",
    "gn:feature_code":"PPL",
    "gn:name":"Gornja Koretica",
    "gn:population":0,
    "gn:timezone":"Europe/Belgrade",
    "iso:country":"XK",
    "name:ceb_x_preferred":[
        "Gornja Koretica"
    ],
    "name:fra_x_preferred":[
        "Gornja Koretica"
    ],
    "name:sqi_x_preferred":[
        "Koretic\u00eb e Ep\u00ebrme"
    ],
    "name:sqi_x_variant":[
        "Korrotic\u00eb e Ep\u00ebrme",
        "Korotica e Ep\u00ebrme",
        "Korratica e Ep\u00ebrme",
        "Kruembreti",
        "Korrotica e Ep\u00ebrme"
    ],
    "name:srp_x_preferred":[
        "Gornja Koretica"
    ],
    "name:srp_x_variant":[
        "\u0413\u043e\u0440\u045a\u0430 \u041a\u043e\u0440\u0435\u0442\u0438\u0446\u0430",
        "Gornja Korotica",
        "Gornja Koratica"
    ],
    "name:swe_x_preferred":[
        "Gornja Koretica"
    ],
    "name:und_x_variant":[
        "Kruembret",
        "Gornja Koratica",
        "Korratica e Ep\u00ebrme",
        "Gornja Korotica",
        "Korotica e Ep\u00ebrme",
        "Kruembreti",
        "Korrotic\u00eb e Ep\u00ebrme"
    ],
    "wof:name":"Gornja Koretica",
    "wof:placetype":"locality"
},
  "geometry": {"coordinates":[20.93389,42.60444],"type":"Point"}
}