{
  "type": "Feature",
  "properties": {
    "gn:admin1_code":"10097358.0",
    "gn:admin2_code":"25.0",
    "gn:asciiname":"Duska",
    "gn:country_code":"XK",
    "gn:dem":699,
    "gn:feature_class":"P",
    "gn:feature_code":"PPL",
    "gn:name":"Du\u0161ka",
    "gn:population":0,
    "gn:timezone":"Europe/Belgrade",
    "iso:country":"XK",
    "name:srp_x_preferred":[
        "Du\u0161ka"
    ],
    "wof:name":"Duska",
    "wof:placetype":"locality"
},
  "geometry": {"coordinates":[20.87806,42.72639],"type":"Point"}
}