{
  "type": "Feature",
  "properties": {
    "gn:admin1_code":"10097360.0",
    "gn:admin2_code":"13.0",
    "gn:asciiname":"Srpka",
    "gn:country_code":"XK",
    "gn:dem":923,
    "gn:feature_class":"P",
    "gn:feature_code":"PPL",
    "gn:name":"Srpka",
    "gn:population":0,
    "gn:timezone":"Europe/Belgrade",
    "iso:country":"XK",
    "name:srp_x_preferred":[
        "\u0421\u0440\u043f\u043a\u0430"
    ],
    "name:srp_x_variant":[
        "Srpka"
    ],
    "wof:name":"Srpka",
    "wof:placetype":"locality"
},
  "geometry": {"coordinates":[21.3025,42.48389],"type":"Point"}
}