{
  "type": "Feature",
  "properties": {
    "gn:admin1_code":"10097360.0",
    "gn:admin2_code":"19.0",
    "gn:asciiname":"Segasht",
    "gn:country_code":"XK",
    "gn:dem":741,
    "gn:feature_class":"P",
    "gn:feature_code":"PPL",
    "gn:name":"Segasht",
    "gn:population":0,
    "gn:timezone":"Europe/Belgrade",
    "iso:country":"XK",
    "name:sqi_x_preferred":[
        "Segasht"
    ],
    "name:srp_x_preferred":[
        "Sega\u0161"
    ],
    "wof:name":"Segasht",
    "wof:placetype":"locality"
},
  "geometry": {"coordinates":[21.07806,42.91389],"type":"Point"}
}