{
  "type": "Feature",
  "properties": {
    "gn:admin1_code":"10097359.0",
    "gn:admin2_code":"8.0",
    "gn:asciiname":"Llukaci Begut (Begaj)",
    "gn:country_code":"XK",
    "gn:dem":433,
    "gn:feature_class":"P",
    "gn:feature_code":"PPLL",
    "gn:name":"Llukaci Begut (Begaj)",
    "gn:population":0,
    "gn:timezone":"Europe/Belgrade",
    "iso:country":"XK",
    "name:sqi_x_preferred":[
        "Llukavc i Begut"
    ],
    "name:sqi_x_variant":[
        "Llukafc i Begut",
        "Llukaci Begut",
        "Llukafci i Begut"
    ],
    "name:und_x_variant":[
        "Llukafc i Begut",
        "Begaj",
        "Llukaci Begut",
        "Llukafci i Begut"
    ],
    "wof:name":"Llukaci Begut (Begaj)",
    "wof:placetype":"locality"
},
  "geometry": {"coordinates":[20.445,42.7325],"type":"Point"}
}