{
  "type": "Feature",
  "properties": {
    "gn:admin1_code":"10097357.0",
    "gn:admin2_code":"6.0",
    "gn:asciiname":"Kosaca",
    "gn:country_code":"XK",
    "gn:dem":575,
    "gn:feature_class":"P",
    "gn:feature_code":"PPL",
    "gn:name":"Kosa\u010da",
    "gn:population":0,
    "gn:timezone":"Europe/Belgrade",
    "iso:country":"XK",
    "name:sqi_x_preferred":[
        "Kosaq\u00eb"
    ],
    "name:srp_x_preferred":[
        "Kosa\u010da"
    ],
    "name:srp_x_variant":[
        "\u041a\u043e\u0441\u0430\u0447\u0430",
        "Kosace",
        "\u041a\u043e\u0441\u0430\u0446\u0435"
    ],
    "wof:name":"Kosaca",
    "wof:placetype":"locality"
},
  "geometry": {"coordinates":[21.50111,42.50278],"type":"Point"}
}