{
  "type": "Feature",
  "properties": {
    "gn:admin1_code":"10096859.0",
    "gn:admin2_code":"5.0",
    "gn:asciiname":"Bob",
    "gn:country_code":"XK",
    "gn:dem":434,
    "gn:feature_class":"P",
    "gn:feature_code":"PPL",
    "gn:name":"Bob",
    "gn:population":0,
    "gn:timezone":"Europe/Belgrade",
    "iso:country":"XK",
    "name:ces_x_preferred":[
        "Bob"
    ],
    "name:dan_x_preferred":[
        "Bob"
    ],
    "name:deu_x_preferred":[
        "Bob"
    ],
    "name:fra_x_preferred":[
        "Bob"
    ],
    "name:hrv_x_preferred":[
        "Bob"
    ],
    "name:hun_x_preferred":[
        "Bob"
    ],
    "name:hye_x_preferred":[
        "\u0532\u0578\u0562"
    ],
    "name:isl_x_preferred":[
        "Bob"
    ],
    "name:nld_x_preferred":[
        "Bob"
    ],
    "name:nor_x_preferred":[
        "Bob"
    ],
    "name:pol_x_preferred":[
        "Bob"
    ],
    "name:por_x_preferred":[
        "Bob"
    ],
    "name:ron_x_preferred":[
        "Bob"
    ],
    "name:rus_x_preferred":[
        "Bob"
    ],
    "name:slv_x_preferred":[
        "Bob"
    ],
    "name:spa_x_preferred":[
        "Bob"
    ],
    "name:srp_x_preferred":[
        "Bob"
    ],
    "name:swe_x_preferred":[
        "Bob"
    ],
    "name:tel_x_preferred":[
        "\u0c2c\u0c3e\u0c2c\u0c4d"
    ],
    "wof:name":"Bob",
    "wof:placetype":"locality"
},
  "geometry": {"coordinates":[20.34667,42.34722],"type":"Point"}
}