{
  "type": "Feature",
  "properties": {
    "gn:admin1_code":"10096859.0",
    "gn:admin2_code":"5.0",
    "gn:asciiname":"Bob",
    "gn:country_code":"XK",
    "gn:dem":434,
    "gn:feature_class":"P",
    "gn:feature_code":"PPL",
    "gn:name":"Bob",
    "gn:population":0,
    "gn:timezone":"Europe/Belgrade",
    "iso:country":"XK",
    "name:srp_x_preferred":[
        "Bob"
    ],
    "name:swe_x_preferred":[
        "Bob"
    ],
    "name:tel_x_preferred":[
        "\u0c2c\u0c3e\u0c2c\u0c4d"
    ],
    "wof:name":"Bob",
    "wof:placetype":"locality"
},
  "geometry": {"coordinates":[20.34667,42.34722],"type":"Point"}
}