{
  "type": "Feature",
  "properties": {
    "gn:admin1_code":"10097359.0",
    "gn:admin2_code":"18.0",
    "gn:asciiname":"Vranoc",
    "gn:country_code":"XK",
    "gn:dem":453,
    "gn:feature_class":"P",
    "gn:feature_code":"PPL",
    "gn:name":"Vranoc",
    "gn:population":0,
    "gn:timezone":"Europe/Belgrade",
    "iso:country":"XK",
    "name:sqi_x_preferred":[
        "Vranoc"
    ],
    "name:sqi_x_variant":[
        "Uranofc"
    ],
    "name:srp_x_preferred":[
        "Vranovac"
    ],
    "name:srp_x_variant":[
        "\u0412\u0440\u0430\u043d\u043e\u0432\u0430\u0446",
        "Veliki-Vranovac"
    ],
    "wof:name":"Vranoc",
    "wof:placetype":"locality"
},
  "geometry": {"coordinates":[20.41806,42.56139],"type":"Point"}
}