{
  "type": "Feature",
  "properties": {
    "gn:admin1_code":"10096138.0",
    "gn:admin2_code":"24.0",
    "gn:asciiname":"Donje Godance",
    "gn:country_code":"XK",
    "gn:dem":569,
    "gn:feature_class":"P",
    "gn:feature_code":"PPL",
    "gn:name":"Donje Godance",
    "gn:population":0,
    "gn:timezone":"Europe/Belgrade",
    "iso:country":"XK",
    "name:sqi_x_preferred":[
        "Godanc i Posht\u00ebm"
    ],
    "name:sqi_x_variant":[
        "Godanci i Posht\u00ebm"
    ],
    "name:srp_x_preferred":[
        "\u0414\u043e\u045a\u0435 \u0413\u043e\u0434\u0430\u043d\u0446\u0435"
    ],
    "name:srp_x_variant":[
        "Donje Godance",
        "Donje Gadance"
    ],
    "wof:name":"Donje Godance",
    "wof:placetype":"locality"
},
  "geometry": {"coordinates":[21.0475,42.45806],"type":"Point"}
}