{
  "type": "Feature",
  "properties": {
    "gn:admin1_code":"10097360.0",
    "gn:admin2_code":"13.0",
    "gn:asciiname":"Llugagji",
    "gn:country_code":"XK",
    "gn:dem":561,
    "gn:feature_class":"P",
    "gn:feature_code":"PPL",
    "gn:name":"Llugagji",
    "gn:population":0,
    "gn:timezone":"Europe/Belgrade",
    "iso:country":"XK",
    "name:sqi_x_preferred":[
        "Llugaxhi"
    ],
    "name:sqi_x_variant":[
        "Llugagji",
        "Lugaxhi"
    ],
    "name:srp_x_preferred":[
        "Lugad\u017eija"
    ],
    "name:srp_x_variant":[
        "\u041b\u0443\u0433\u0430\u045f\u0438\u0458\u0430",
        "Luga\u0111ija"
    ],
    "name:und_x_variant":[
        "Luga\u0111ija",
        "Lugaxhi"
    ],
    "wof:name":"Llugagji",
    "wof:placetype":"locality"
},
  "geometry": {"coordinates":[21.17306,42.48861],"type":"Point"}
}