{
  "type": "Feature",
  "properties": {
    "gn:admin1_code":"10097358.0",
    "gn:admin2_code":"25.0",
    "gn:asciiname":"Novo Poljance",
    "gn:country_code":"XK",
    "gn:dem":643,
    "gn:feature_class":"P",
    "gn:feature_code":"PPL",
    "gn:name":"Novo Poljance",
    "gn:population":0,
    "gn:timezone":"Europe/Belgrade",
    "iso:country":"XK",
    "name:sqi_x_preferred":[
        "Polac i Ri"
    ],
    "name:sqi_x_variant":[
        "Polac"
    ],
    "name:srp_x_preferred":[
        "\u041d\u043e\u0432\u043e \u041f\u043e\u0459\u0430\u043d\u0446\u0435"
    ],
    "name:srp_x_variant":[
        "Novo Poljance"
    ],
    "name:und_x_variant":[
        "Poljance"
    ],
    "wof:name":"Novo Poljance",
    "wof:placetype":"locality"
},
  "geometry": {"coordinates":[20.83472,42.71222],"type":"Point"}
}