{
  "type": "Feature",
  "properties": {
    "gn:admin1_code":"10097361.0",
    "gn:admin2_code":"21.0",
    "gn:asciiname":"Malesi e Re",
    "gn:country_code":"XK",
    "gn:dem":400,
    "gn:feature_class":"P",
    "gn:feature_code":"PPL",
    "gn:name":"Mal\u00ebsi e Re",
    "gn:population":0,
    "gn:timezone":"Europe/Belgrade",
    "iso:country":"XK",
    "name:sqi_x_preferred":[
        "Mal\u00ebsi e Re"
    ],
    "name:srp_x_preferred":[
        "Nova \u0160umadija"
    ],
    "name:srp_x_variant":[
        "\u041d\u043e\u0432\u0430 \u0428\u0443\u043c\u0430\u0434\u0438\u0458\u0430"
    ],
    "wof:name":"Malesi e Re",
    "wof:placetype":"locality"
},
  "geometry": {"coordinates":[20.79472,42.28417],"type":"Point"}
}