{
  "type": "Feature",
  "properties": {
    "gn:admin1_code":"10097357.0",
    "gn:admin2_code":"6.0",
    "gn:asciiname":"Muhadziri",
    "gn:country_code":"XK",
    "gn:dem":557,
    "gn:feature_class":"P",
    "gn:feature_code":"PPL",
    "gn:name":"Muhad\u017eiri",
    "gn:population":0,
    "gn:timezone":"Europe/Belgrade",
    "iso:country":"XK",
    "name:srp_x_preferred":[
        "Muhad\u017eiri"
    ],
    "wof:name":"Muhadziri",
    "wof:placetype":"locality"
},
  "geometry": {"coordinates":[21.54667,42.46972],"type":"Point"}
}