{
  "type": "Feature",
  "properties": {
    "gn:admin1_code":"10096138.0",
    "gn:admin2_code":"24.0",
    "gn:asciiname":"Vokovic Mahala",
    "gn:country_code":"XK",
    "gn:dem":1060,
    "gn:feature_class":"P",
    "gn:feature_code":"PPL",
    "gn:name":"Vokovi\u0107 Mahala",
    "gn:population":0,
    "gn:timezone":"Europe/Belgrade",
    "iso:country":"XK",
    "name:srp_x_preferred":[
        "Vokovi\u0107 Mahala"
    ],
    "wof:name":"Vokovic Mahala",
    "wof:placetype":"locality"
},
  "geometry": {"coordinates":[20.9775,42.40889],"type":"Point"}
}