{
  "type": "Feature",
  "properties": {
    "gn:admin1_code":"10097361.0",
    "gn:admin2_code":"26.0",
    "gn:asciiname":"Blace",
    "gn:country_code":"XK",
    "gn:dem":649,
    "gn:feature_class":"P",
    "gn:feature_code":"PPLL",
    "gn:name":"Blace",
    "gn:population":0,
    "gn:timezone":"Europe/Belgrade",
    "iso:country":"XK",
    "name:fra_x_preferred":[
        "Blace"
    ],
    "name:sqi_x_preferred":[
        "Bllac\u00eb"
    ],
    "name:sqi_x_variant":[
        "Bllaca"
    ],
    "name:srp_x_preferred":[
        "\u0411\u043b\u0430\u0446\u0435"
    ],
    "name:srp_x_variant":[
        "Blace"
    ],
    "name:und_x_variant":[
        "Bllac\u00eb"
    ],
    "wof:name":"Blace",
    "wof:placetype":"locality"
},
  "geometry": {"coordinates":[20.8625,42.42306],"type":"Point"}
}