{
  "type": "Feature",
  "properties": {
    "gn:admin1_code":"10097357.0",
    "gn:admin2_code":"6.0",
    "gn:asciiname":"Vrsavica Mahala",
    "gn:country_code":"XK",
    "gn:dem":580,
    "gn:feature_class":"P",
    "gn:feature_code":"PPL",
    "gn:name":"Vr\u0161avica Mahala",
    "gn:population":0,
    "gn:timezone":"Europe/Belgrade",
    "iso:country":"XK",
    "name:srp_x_preferred":[
        "Vr\u0161avica Mahala"
    ],
    "wof:name":"Vrsavica Mahala",
    "wof:placetype":"locality"
},
  "geometry": {"coordinates":[21.51361,42.32694],"type":"Point"}
}