{
  "type": "Feature",
  "properties": {
    "gn:admin1_code":"10097360.0",
    "gn:admin2_code":"19.0",
    "gn:asciiname":"Budzhak",
    "gn:country_code":"XK",
    "gn:dem":641,
    "gn:feature_class":"P",
    "gn:feature_code":"PPLL",
    "gn:name":"Budzhak",
    "gn:population":0,
    "gn:timezone":"Europe/Belgrade",
    "iso:country":"XK",
    "name:sqi_x_preferred":[
        "Budzhak"
    ],
    "name:srp_x_preferred":[
        "Bud\u017eak"
    ],
    "wof:name":"Budzhak",
    "wof:placetype":"locality"
},
  "geometry": {"coordinates":[21.19718,42.9629],"type":"Point"}
}