{
  "type": "Feature",
  "properties": {
    "gn:admin1_code":"10097361.0",
    "gn:admin2_code":"14.0",
    "gn:asciiname":"Balovic Mahala",
    "gn:country_code":"XK",
    "gn:dem":560,
    "gn:feature_class":"P",
    "gn:feature_code":"PPL",
    "gn:name":"Balovi\u0107 Mahala",
    "gn:population":0,
    "gn:timezone":"Europe/Belgrade",
    "iso:country":"XK",
    "name:srp_x_preferred":[
        "\u0411\u0430\u043b\u043e\u0432\u0438\u045b \u041c\u0430\u0445\u0430\u043b\u0430"
    ],
    "name:srp_x_variant":[
        "Balovi\u0107 Mahala"
    ],
    "wof:name":"Balovic Mahala",
    "wof:placetype":"locality"
},
  "geometry": {"coordinates":[20.76083,42.51278],"type":"Point"}
}