{
  "type": "Feature",
  "properties": {
    "gn:admin1_code":"10097358.0",
    "gn:admin2_code":"29.0",
    "gn:asciiname":"Kobilja Glava",
    "gn:country_code":"XK",
    "gn:dem":1047,
    "gn:feature_class":"P",
    "gn:feature_code":"PPL",
    "gn:name":"Kobilja Glava",
    "gn:population":0,
    "gn:timezone":"Europe/Belgrade",
    "iso:country":"XK",
    "name:sqi_x_preferred":[
        "Kobillogllav\u00eb"
    ],
    "name:srp_x_preferred":[
        "Kobilja Glava"
    ],
    "name:srp_x_variant":[
        "\u041a\u043e\u0431\u0438\u0459\u0430 \u0413\u043b\u0430\u0432\u0430"
    ],
    "wof:name":"Kobilja Glava",
    "wof:placetype":"locality"
},
  "geometry": {"coordinates":[20.70222,42.94861],"type":"Point"}
}