{
  "type": "Feature",
  "properties": {
    "gn:admin1_code":"10097361.0",
    "gn:admin2_code":"14.0",
    "gn:asciiname":"Skorashnik",
    "gn:country_code":"XK",
    "gn:dem":615,
    "gn:feature_class":"P",
    "gn:feature_code":"PPL",
    "gn:name":"Skorashnik",
    "gn:population":0,
    "gn:timezone":"Europe/Belgrade",
    "iso:country":"XK",
    "name:sqi_x_preferred":[
        "Skorashnik"
    ],
    "name:sqi_x_variant":[
        "Shkarashnik",
        "Shkorashnik",
        "Skarashnik"
    ],
    "name:srp_x_preferred":[
        "\u0421\u043a\u043e\u0440\u043e\u0448\u043d\u0438\u043a"
    ],
    "name:srp_x_variant":[
        "Skoro\u0161nik"
    ],
    "name:und_x_variant":[
        "Shkorashnik",
        "Skarashnik"
    ],
    "wof:name":"Skorashnik",
    "wof:placetype":"locality"
},
  "geometry": {"coordinates":[20.77694,42.52472],"type":"Point"}
}