{
  "type": "Feature",
  "properties": {
    "gn:admin1_code":"10097358.0",
    "gn:admin2_code":"28.0",
    "gn:asciiname":"Stitarica",
    "gn:country_code":"XK",
    "gn:dem":531,
    "gn:feature_class":"P",
    "gn:feature_code":"PPL",
    "gn:name":"\u0160titarica",
    "gn:population":0,
    "gn:timezone":"Europe/Belgrade",
    "iso:country":"XK",
    "name:sqi_x_preferred":[
        "Shtitatric\u00eb"
    ],
    "name:sqi_x_variant":[
        "Shtitaric\u00eb",
        "Shataric\u00eb"
    ],
    "name:srp_x_preferred":[
        "\u0160titarica"
    ],
    "name:srp_x_variant":[
        "\u0428\u0442\u0438\u0442\u0430\u0440\u0438\u0446\u0430"
    ],
    "wof:name":"Stitarica",
    "wof:placetype":"locality"
},
  "geometry": {"coordinates":[20.93194,42.82611],"type":"Point"}
}