{
  "type": "Feature",
  "properties": {
    "gn:admin1_code":"10097360.0",
    "gn:admin2_code":"7.0",
    "gn:asciiname":"Dzamijska Mahala",
    "gn:country_code":"XK",
    "gn:dem":716,
    "gn:feature_class":"P",
    "gn:feature_code":"PPL",
    "gn:name":"D\u017eamijska Mahala",
    "gn:population":0,
    "gn:timezone":"Europe/Belgrade",
    "iso:country":"XK",
    "name:srp_x_preferred":[
        "D\u017eamijska Mahala"
    ],
    "wof:name":"Dzamijska Mahala",
    "wof:placetype":"locality"
},
  "geometry": {"coordinates":[20.83278,42.54556],"type":"Point"}
}