{
  "type": "Feature",
  "properties": {
    "gn:admin1_code":"10097359.0",
    "gn:admin2_code":"18.0",
    "gn:asciiname":"Lekaj",
    "gn:country_code":"XK",
    "gn:dem":1241,
    "gn:feature_class":"P",
    "gn:feature_code":"PPL",
    "gn:name":"Lekaj",
    "gn:population":0,
    "gn:timezone":"Europe/Belgrade",
    "iso:country":"XK",
    "name:srp_x_preferred":[
        "Lekaj"
    ],
    "wof:name":"Lekaj",
    "wof:placetype":"locality"
},
  "geometry": {"coordinates":[20.04889,42.70778],"type":"Point"}
}