{
  "type": "Feature",
  "properties": {
    "gn:admin1_code":"10097357.0",
    "gn:admin2_code":"6.0",
    "gn:asciiname":"Donji Makres",
    "gn:country_code":"XK",
    "gn:dem":747,
    "gn:feature_class":"P",
    "gn:feature_code":"PPL",
    "gn:name":"Donji Makre\u0161",
    "gn:population":0,
    "gn:timezone":"Europe/Belgrade",
    "iso:country":"XK",
    "name:sqi_x_preferred":[
        "Makresh i Posht\u00ebm"
    ],
    "name:sqi_x_variant":[
        "Makresh i Ult\u00eb",
        "Makresh i Ul\u00ebt",
        "Makreshi i Posht\u00ebm"
    ],
    "name:srp_x_preferred":[
        "\u0414\u043e\u045a\u0438 \u041c\u0430\u043a\u0440\u0435\u0448"
    ],
    "name:srp_x_variant":[
        "Donji Makre\u0161"
    ],
    "name:und_x_variant":[
        "Makreshi i Posht\u00ebm"
    ],
    "wof:name":"Donji Makres",
    "wof:placetype":"locality"
},
  "geometry": {"coordinates":[21.48056,42.56194],"type":"Point"}
}