{
  "type": "Feature",
  "properties": {
    "gn:admin1_code":"10097359.0",
    "gn:admin2_code":"8.0",
    "gn:asciiname":"Rakosh",
    "gn:country_code":"XK",
    "gn:dem":565,
    "gn:feature_class":"P",
    "gn:feature_code":"PPL",
    "gn:name":"Rakosh",
    "gn:population":0,
    "gn:timezone":"Europe/Belgrade",
    "iso:country":"XK",
    "name:sqi_x_preferred":[
        "Rakosh"
    ],
    "name:sqi_x_variant":[
        "Rakoshi"
    ],
    "name:srp_x_preferred":[
        "Rako\u0161"
    ],
    "name:srp_x_variant":[
        "\u0420\u0430\u043a\u043e\u0448"
    ],
    "name:und_x_variant":[
        "Rakoshi"
    ],
    "wof:name":"Rakosh",
    "wof:placetype":"locality"
},
  "geometry": {"coordinates":[20.60472,42.78611],"type":"Point"}
}