{
  "type": "Feature",
  "properties": {
    "gn:admin1_code":"10097359.0",
    "gn:admin2_code":"8.0",
    "gn:asciiname":"Gornji Dragoljevac",
    "gn:country_code":"XK",
    "gn:dem":490,
    "gn:feature_class":"P",
    "gn:feature_code":"PPL",
    "gn:name":"Gornji Dragoljevac",
    "gn:population":0,
    "gn:timezone":"Europe/Belgrade",
    "iso:country":"XK",
    "wof:name":"Gornji Dragoljevac",
    "wof:placetype":"locality"
},
  "geometry": {"coordinates":[20.51556,42.77222],"type":"Point"}
}