{
  "type": "Feature",
  "properties": {
    "gn:admin1_code":"10097359.0",
    "gn:admin2_code":"11.0",
    "gn:asciiname":"Prlina",
    "gn:country_code":"XK",
    "gn:dem":376,
    "gn:feature_class":"P",
    "gn:feature_code":"PPL",
    "gn:name":"Prlina",
    "gn:population":0,
    "gn:timezone":"Europe/Belgrade",
    "iso:country":"XK",
    "name:srp_x_preferred":[
        "Prlina"
    ],
    "wof:name":"Prlina",
    "wof:placetype":"locality"
},
  "geometry": {"coordinates":[20.57528,42.60694],"type":"Point"}
}