{
  "type": "Feature",
  "properties": {
    "gn:admin1_code":"10097359.0",
    "gn:admin2_code":"18.0",
    "gn:asciiname":"Lekiqi",
    "gn:country_code":"XK",
    "gn:dem":1470,
    "gn:feature_class":"P",
    "gn:feature_code":"PPL",
    "gn:name":"Lekiqi",
    "gn:population":0,
    "gn:timezone":"Europe/Belgrade",
    "iso:country":"XK",
    "wof:name":"Lekiqi",
    "wof:placetype":"locality"
},
  "geometry": {"coordinates":[20.10583,42.74528],"type":"Point"}
}