{
  "type": "Feature",
  "properties": {
    "gn:admin1_code":"10097361.0",
    "gn:admin2_code":"26.0",
    "gn:asciiname":"Dragaqine",
    "gn:country_code":"XK",
    "gn:dem":652,
    "gn:feature_class":"P",
    "gn:feature_code":"PPL",
    "gn:name":"Dragaqin\u00eb",
    "gn:population":0,
    "gn:timezone":"Europe/Belgrade",
    "iso:country":"XK",
    "name:sqi_x_preferred":[
        "Dragaqin\u00eb"
    ],
    "name:srp_x_preferred":[
        "Draga\u010dina"
    ],
    "name:srp_x_variant":[
        "\u0414\u0440\u0430\u0433\u0430\u0447\u0438\u043d\u0430"
    ],
    "wof:name":"Dragaqine",
    "wof:placetype":"locality"
},
  "geometry": {"coordinates":[20.90083,42.3975],"type":"Point"}
}