{
  "type": "Feature",
  "properties": {
    "gn:admin1_code":"10096138.0",
    "gn:admin2_code":"9.0",
    "gn:asciiname":"Kuc Mahala",
    "gn:country_code":"XK",
    "gn:dem":692,
    "gn:feature_class":"P",
    "gn:feature_code":"PPL",
    "gn:name":"Ku\u010d Mahala",
    "gn:population":0,
    "gn:timezone":"Europe/Belgrade",
    "iso:country":"XK",
    "name:srp_x_preferred":[
        "Ku\u010d Mahala"
    ],
    "wof:name":"Kuc Mahala",
    "wof:placetype":"locality"
},
  "geometry": {"coordinates":[21.21917,42.17333],"type":"Point"}
}