{
  "type": "Feature",
  "properties": {
    "gn:admin1_code":"10097360.0",
    "gn:admin2_code":"20.0",
    "gn:asciiname":"Vrani Do",
    "gn:country_code":"XK",
    "gn:dem":578,
    "gn:feature_class":"P",
    "gn:feature_code":"PPL",
    "gn:name":"Vrani Do",
    "gn:population":0,
    "gn:timezone":"Europe/Belgrade",
    "iso:country":"XK",
    "name:sqi_x_preferred":[
        "Vranidoll"
    ],
    "name:srp_x_preferred":[
        "\u0412\u0440\u0430\u043d\u0438 \u0414\u043e"
    ],
    "name:srp_x_variant":[
        "Vrani Do"
    ],
    "name:und_x_variant":[
        "Vranidoll",
        "Vrani Dol"
    ],
    "wof:name":"Vrani Do",
    "wof:placetype":"locality"
},
  "geometry": {"coordinates":[21.15278,42.76694000000001],"type":"Point"}
}