{
  "type": "Feature",
  "properties": {
    "gn:admin1_code":"10097358.0",
    "gn:admin2_code":"30.0",
    "gn:asciiname":"Zerovnica",
    "gn:country_code":"XK",
    "gn:dem":547,
    "gn:feature_class":"P",
    "gn:feature_code":"PPL",
    "gn:name":"\u017derovnica",
    "gn:population":0,
    "gn:timezone":"Europe/Belgrade",
    "iso:country":"XK",
    "name:sqi_x_preferred":[
        "Zherovnic\u00eb"
    ],
    "name:sqi_x_variant":[
        "Zheravice"
    ],
    "name:srp_x_preferred":[
        "\u017derovnica"
    ],
    "name:srp_x_variant":[
        "\u0416\u0435\u0440\u043e\u0432\u043d\u0438\u0446\u0430"
    ],
    "name:und_x_variant":[
        "Zheravice"
    ],
    "wof:name":"Zerovnica",
    "wof:placetype":"locality"
},
  "geometry": {"coordinates":[20.80667,42.93194],"type":"Point"}
}