{
  "type": "Feature",
  "properties": {
    "gn:admin1_code":"10097357.0",
    "gn:admin2_code":"10.0",
    "gn:asciiname":"Gornje Recane",
    "gn:country_code":"XK",
    "gn:dem":498,
    "gn:feature_class":"P",
    "gn:feature_code":"PPL",
    "gn:name":"Gornje Re\u010dane",
    "gn:population":0,
    "gn:timezone":"Europe/Belgrade",
    "iso:country":"XK",
    "name:srp_x_preferred":[
        "Gornje Re\u010dane"
    ],
    "name:srp_x_variant":[
        "Donje Ajnovce"
    ],
    "wof:name":"Gornje Recane",
    "wof:placetype":"locality"
},
  "geometry": {"coordinates":[21.55361,42.61083],"type":"Point"}
}