{
  "type": "Feature",
  "properties": {
    "gn:admin1_code":"10097361.0",
    "gn:admin2_code":"2.0",
    "gn:asciiname":"Bellobrad",
    "gn:country_code":"XK",
    "gn:dem":1007,
    "gn:feature_class":"P",
    "gn:feature_code":"PPL",
    "gn:name":"Bellobrad",
    "gn:population":0,
    "gn:timezone":"Europe/Belgrade",
    "iso:country":"XK",
    "name:sqi_x_preferred":[
        "Bellobrod"
    ],
    "name:sqi_x_variant":[
        "Bellobrad",
        "Bellobrat",
        "Bellabrad"
    ],
    "name:srp_x_preferred":[
        "\u0411\u0435\u043b\u043e\u0431\u0440\u043e\u0434"
    ],
    "name:srp_x_variant":[
        "Belobrad",
        "\u0411\u0435\u043b\u043e\u0431\u0440\u0430\u0434",
        "Belobrod"
    ],
    "name:und_x_variant":[
        "Delobrad",
        "Bellobrat",
        "Belobrod",
        "Bellabrad"
    ],
    "wof:name":"Bellobrad",
    "wof:placetype":"locality"
},
  "geometry": {"coordinates":[20.68333,42.11833],"type":"Point"}
}