{
  "type": "Feature",
  "properties": {
    "gn:admin1_code":"10097357.0",
    "gn:admin2_code":"10.0",
    "gn:asciiname":"Lestar",
    "gn:country_code":"XK",
    "gn:dem":652,
    "gn:feature_class":"P",
    "gn:feature_code":"PPL",
    "gn:name":"Le\u0161tar",
    "gn:population":0,
    "gn:timezone":"Europe/Belgrade",
    "iso:country":"XK",
    "name:sqi_x_preferred":[
        "Leshtar"
    ],
    "name:sqi_x_variant":[
        "Leshtari"
    ],
    "name:srp_x_preferred":[
        "Le\u0161tar"
    ],
    "name:und_x_variant":[
        "Leshtar",
        "Leshtari"
    ],
    "wof:name":"Lestar",
    "wof:placetype":"locality"
},
  "geometry": {"coordinates":[21.48667,42.64583],"type":"Point"}
}