{
  "type": "Feature",
  "properties": {
    "gn:admin1_code":"10097361.0",
    "gn:admin2_code":"26.0",
    "gn:asciiname":"Buzalja",
    "gn:country_code":"XK",
    "gn:dem":681,
    "gn:feature_class":"P",
    "gn:feature_code":"PPL",
    "gn:name":"Bu\u017ealja",
    "gn:population":0,
    "gn:timezone":"Europe/Belgrade",
    "iso:country":"XK",
    "name:srp_x_preferred":[
        "Bu\u017ealja"
    ],
    "name:srp_x_variant":[
        "Bu\u017ean"
    ],
    "name:und_x_variant":[
        "Bu\u017ean"
    ],
    "wof:name":"Buzalja",
    "wof:placetype":"locality"
},
  "geometry": {"coordinates":[20.92417,42.33944],"type":"Point"}
}