{
  "type": "Feature",
  "properties": {
    "gn:admin1_code":"10096859.0",
    "gn:admin2_code":"1.0",
    "gn:asciiname":"Papiq",
    "gn:country_code":"XK",
    "gn:dem":537,
    "gn:feature_class":"P",
    "gn:feature_code":"PPL",
    "gn:name":"Papiq",
    "gn:population":0,
    "gn:timezone":"Europe/Belgrade",
    "iso:country":"XK",
    "name:sqi_x_preferred":[
        "Papiq"
    ],
    "name:sqi_x_variant":[
        "Papiqi"
    ],
    "name:srp_x_preferred":[
        "Papic"
    ],
    "name:srp_x_variant":[
        "Papi\u0107",
        "\u041f\u0430\u043f\u0438\u045b"
    ],
    "name:und_x_variant":[
        "Papiqi",
        "Papaj"
    ],
    "wof:name":"Papiq",
    "wof:placetype":"locality"
},
  "geometry": {"coordinates":[20.34417,42.55556],"type":"Point"}
}