{
  "type": "Feature",
  "properties": {
    "gn:admin1_code":"10097360.0",
    "gn:admin2_code":"17.0",
    "gn:asciiname":"Breznica",
    "gn:country_code":"XK",
    "gn:dem":573,
    "gn:feature_class":"P",
    "gn:feature_code":"PPLL",
    "gn:name":"Breznica",
    "gn:population":0,
    "gn:timezone":"Europe/Belgrade",
    "iso:country":"XK",
    "name:ita_x_preferred":[
        "Breznica"
    ],
    "name:sqi_x_preferred":[
        "Breznic\u00eb"
    ],
    "name:srp_x_preferred":[
        "\u0411\u0440\u0435\u0437\u043d\u0438\u0446\u0430"
    ],
    "name:srp_x_variant":[
        "Breznica"
    ],
    "name:swe_x_preferred":[
        "Breznica"
    ],
    "name:ukr_x_preferred":[
        "\u0411\u0440\u0435\u0437\u043d\u0438\u0446\u044f"
    ],
    "name:und_x_variant":[
        "Breznic\u00eb"
    ],
    "wof:name":"Breznica",
    "wof:placetype":"locality"
},
  "geometry": {"coordinates":[21.08256,42.77718],"type":"Point"}
}