{
  "type": "Feature",
  "properties": {
    "gn:admin1_code":"10097358.0",
    "gn:admin2_code":"29.0",
    "gn:asciiname":"Vitakovo",
    "gn:country_code":"XK",
    "gn:dem":952,
    "gn:feature_class":"P",
    "gn:feature_code":"PPL",
    "gn:name":"Vitakovo",
    "gn:population":0,
    "gn:timezone":"Europe/Belgrade",
    "iso:country":"XK",
    "name:sqi_x_preferred":[
        "Vitakov\u00eb"
    ],
    "name:srp_x_preferred":[
        "Vitakovo"
    ],
    "name:srp_x_variant":[
        "\u0412\u0438\u0442\u0430\u043a\u043e\u0432\u043e"
    ],
    "wof:name":"Vitakovo",
    "wof:placetype":"locality"
},
  "geometry": {"coordinates":[20.59111,42.99583],"type":"Point"}
}