{
  "type": "Feature",
  "properties": {
    "gn:admin1_code":"10097359.0",
    "gn:admin2_code":"11.0",
    "gn:asciiname":"Gjurgjevik i Madh",
    "gn:country_code":"XK",
    "gn:dem":500,
    "gn:feature_class":"P",
    "gn:feature_code":"PPL",
    "gn:name":"Gjurgjevik i Madh",
    "gn:population":0,
    "gn:timezone":"Europe/Belgrade",
    "iso:country":"XK",
    "name:sqi_x_preferred":[
        "Gjurgjevik i Madh"
    ],
    "name:sqi_x_variant":[
        "Gjurgjevik",
        "Gjurxhevik",
        "Gjurgjevici i Madh",
        "Gjyrgjeviku i Madh"
    ],
    "name:srp_x_preferred":[
        "Veliki \u00d0ur\u0111evik"
    ],
    "name:srp_x_variant":[
        "\u0412\u0435\u043b\u0438\u043a\u0438 \u0402\u0443\u0440\u0452\u0435\u0432\u0438\u043a",
        "\u0402\u0443\u0440\u0452\u0435\u0432\u0438\u043a",
        "\u00d0ur\u0111evi\u0107",
        "\u00d0ur\u0111evik"
    ],
    "name:und_x_variant":[
        "Martiras",
        "Martirasi"
    ],
    "wof:name":"Gjurgjevik i Madh",
    "wof:placetype":"locality"
},
  "geometry": {"coordinates":[20.65778,42.61278],"type":"Point"}
}