{
  "type": "Feature",
  "properties": {
    "gn:admin1_code":"10097357.0",
    "gn:admin2_code":"10.0",
    "gn:asciiname":"Kranidel",
    "gn:country_code":"XK",
    "gn:dem":947,
    "gn:feature_class":"P",
    "gn:feature_code":"PPLL",
    "gn:name":"Kranidel",
    "gn:population":0,
    "gn:timezone":"Europe/Belgrade",
    "iso:country":"XK",
    "name:sqi_x_preferred":[
        "Kranidell"
    ],
    "name:sqi_x_variant":[
        "Kranidel",
        "Kranidelli",
        "Temali"
    ],
    "name:srp_x_preferred":[
        "Krajni Del"
    ],
    "name:srp_x_variant":[
        "\u041a\u0440\u0430\u0458\u043d\u0438 \u0414\u0435\u043b",
        "\u041a\u0440\u0430\u0458\u043d\u0438\u0434\u043e\u043b",
        "\u041a\u0440\u0430\u0458\u043d\u0438\u0434\u0435\u043b",
        "Krajnidel",
        "Krajnidoll"
    ],
    "name:und_x_variant":[
        "Temali",
        "Krajnidoll",
        "Temal",
        "Kranidelli",
        "Krajindel"
    ],
    "wof:name":"Kranidel",
    "wof:placetype":"locality"
},
  "geometry": {"coordinates":[21.70639,42.60583],"type":"Point"}
}