{
  "type": "Feature",
  "properties": {
    "gn:admin1_code":"10097358.0",
    "gn:admin2_code":"28.0",
    "gn:asciiname":"Viljance",
    "gn:country_code":"XK",
    "gn:dem":549,
    "gn:feature_class":"P",
    "gn:feature_code":"PPL",
    "gn:name":"Viljance",
    "gn:population":0,
    "gn:timezone":"Europe/Belgrade",
    "iso:country":"XK",
    "name:sqi_x_preferred":[
        "Vilanc\u00eb"
    ],
    "name:sqi_x_variant":[
        "Viqanc\u00eb",
        "Viljanc\u00eb",
        "Vilanc",
        "Vllanic\u00eb"
    ],
    "name:srp_x_preferred":[
        "Viljance"
    ],
    "name:srp_x_variant":[
        "\u0412\u0438\u0459\u0430\u043d\u0446\u0435",
        "Vi\u0107ance",
        "\u0412\u0438\u045b\u0430\u043d\u0446\u0435"
    ],
    "name:und_x_variant":[
        "Vllanic\u00eb"
    ],
    "wof:name":"Viljance",
    "wof:placetype":"locality"
},
  "geometry": {"coordinates":[21.02933,42.79641],"type":"Point"}
}