{
  "type": "Feature",
  "properties": {
    "gn:admin1_code":"10097360.0",
    "gn:admin2_code":"13.0",
    "gn:asciiname":"Bukovica",
    "gn:country_code":"XK",
    "gn:dem":878,
    "gn:feature_class":"P",
    "gn:feature_code":"PPL",
    "gn:name":"Bukovica",
    "gn:population":0,
    "gn:timezone":"Europe/Belgrade",
    "iso:country":"XK",
    "name:sqi_x_preferred":[
        "Bukovic\u00eb"
    ],
    "name:srp_x_preferred":[
        "Bukovica"
    ],
    "name:srp_x_variant":[
        "\u0411\u0443\u043a\u043e\u0432\u0438\u0446\u0430"
    ],
    "name:und_x_variant":[
        "Bukavica"
    ],
    "wof:name":"Bukovica",
    "wof:placetype":"locality"
},
  "geometry": {"coordinates":[21.26491,42.57611],"type":"Point"}
}