{
  "type": "Feature",
  "properties": {
    "gn:admin1_code":"10097357.0",
    "gn:admin2_code":"27.0",
    "gn:asciiname":"Stublla e Poshtme",
    "gn:country_code":"XK",
    "gn:dem":669,
    "gn:feature_class":"P",
    "gn:feature_code":"PPL",
    "gn:name":"Stublla e Poshtme",
    "gn:population":0,
    "gn:timezone":"Europe/Belgrade",
    "iso:country":"XK",
    "name:sqi_x_preferred":[
        "Stub\u00ebll e Poshtme"
    ],
    "name:sqi_x_variant":[
        "Stublla e Poshtme",
        "Stublla e Posht\u00ebme"
    ],
    "name:srp_x_preferred":[
        "Donja Stubla"
    ],
    "name:srp_x_variant":[
        "\u0414\u043e\u045a\u0430 \u0421\u0442\u0443\u0431\u043b\u0430"
    ],
    "name:und_x_variant":[
        "Stublla e Posht\u00ebme"
    ],
    "wof:name":"Stublla e Poshtme",
    "wof:placetype":"locality"
},
  "geometry": {"coordinates":[21.4525,42.33806],"type":"Point"}
}