{
  "type": "Feature",
  "properties": {
    "gn:admin1_code":"10096859.0",
    "gn:admin2_code":"22.0",
    "gn:asciiname":"Radoste",
    "gn:country_code":"XK",
    "gn:dem":330,
    "gn:feature_class":"P",
    "gn:feature_code":"PPL",
    "gn:name":"Radoste",
    "gn:population":0,
    "gn:timezone":"Europe/Belgrade",
    "iso:country":"XK",
    "name:sqi_x_preferred":[
        "Radost\u00eb"
    ],
    "name:srp_x_preferred":[
        "\u0420\u0430\u0434\u043e\u0441\u0442\u0435"
    ],
    "name:srp_x_variant":[
        "Radoste"
    ],
    "name:und_x_variant":[
        "Radosti"
    ],
    "wof:name":"Radoste",
    "wof:placetype":"locality"
},
  "geometry": {"coordinates":[20.53722,42.38694],"type":"Point"}
}