{
  "type": "Feature",
  "properties": {
    "gn:admin1_code":"10097358.0",
    "gn:admin2_code":"15.0",
    "gn:asciiname":"Trstena",
    "gn:country_code":"XK",
    "gn:dem":880,
    "gn:feature_class":"P",
    "gn:feature_code":"PPLL",
    "gn:name":"Trstena",
    "gn:population":0,
    "gn:timezone":"Europe/Belgrade",
    "iso:country":"XK",
    "name:sqi_x_preferred":[
        "T\u00ebrsten\u00eb"
    ],
    "name:srp_x_preferred":[
        "\u0422\u0440\u0441\u0442\u0435\u043d\u0430"
    ],
    "name:srp_x_variant":[
        "Trstena"
    ],
    "name:und_x_variant":[
        "T\u00ebrsten\u00eb"
    ],
    "wof:name":"Trstena",
    "wof:placetype":"locality"
},
  "geometry": {"coordinates":[20.9725,42.91389],"type":"Point"}
}