{
  "type": "Feature",
  "properties": {
    "gn:admin1_code":"10097358.0",
    "gn:admin2_code":"15.0",
    "gn:asciiname":"Vlahinje",
    "gn:country_code":"XK",
    "gn:dem":920,
    "gn:feature_class":"P",
    "gn:feature_code":"PPLL",
    "gn:name":"Vlahinje",
    "gn:population":0,
    "gn:timezone":"Europe/Belgrade",
    "iso:country":"XK",
    "name:bos_x_preferred":[
        "Vlahinje"
    ],
    "name:fra_x_preferred":[
        "Vlahinje"
    ],
    "name:sqi_x_preferred":[
        "Vllahi"
    ],
    "name:sqi_x_variant":[
        "Vllahij\u00eb"
    ],
    "name:srp_x_preferred":[
        "\u0412\u043b\u0430\u0445\u0438\u045a\u0435"
    ],
    "name:srp_x_variant":[
        "Vlahinje"
    ],
    "name:und_x_variant":[
        "Vlahinja"
    ],
    "wof:name":"Vlahinje",
    "wof:placetype":"locality"
},
  "geometry": {"coordinates":[20.87389,42.96861],"type":"Point"}
}