{
  "type": "Feature",
  "properties": {
    "gn:admin1_code":"10097359.0",
    "gn:admin2_code":"11.0",
    "gn:asciiname":"Lugadzija",
    "gn:country_code":"XK",
    "gn:dem":401,
    "gn:feature_class":"P",
    "gn:feature_code":"PPL",
    "gn:name":"Lugad\u017eija",
    "gn:population":0,
    "gn:timezone":"Europe/Belgrade",
    "iso:country":"XK",
    "name:srp_x_preferred":[
        "Lugad\u017eija"
    ],
    "name:srp_x_variant":[
        "Lugu Pa\u0161i\u0107"
    ],
    "name:und_x_variant":[
        "Lugu Pa\u0161i\u0107"
    ],
    "wof:name":"Lugadzija",
    "wof:placetype":"locality"
},
  "geometry": {"coordinates":[20.51667,42.66944],"type":"Point"}
}