{
  "type": "Feature",
  "properties": {
    "gn:admin1_code":"10097359.0",
    "gn:admin2_code":"18.0",
    "gn:asciiname":"Kastra",
    "gn:country_code":"XK",
    "gn:dem":482,
    "gn:feature_class":"P",
    "gn:feature_code":"PPL",
    "gn:name":"Kastra",
    "gn:population":0,
    "gn:timezone":"Europe/Belgrade",
    "iso:country":"XK",
    "name:srp_x_preferred":[
        "Kastra"
    ],
    "wof:name":"Kastra",
    "wof:placetype":"locality"
},
  "geometry": {"coordinates":[20.38472,42.61028],"type":"Point"}
}