{
  "type": "Feature",
  "properties": {
    "gn:admin1_code":"10097360.0",
    "gn:admin2_code":"19.0",
    "gn:asciiname":"Lausa",
    "gn:country_code":"XK",
    "gn:dem":661,
    "gn:feature_class":"P",
    "gn:feature_code":"PPLL",
    "gn:name":"Lau\u0161a",
    "gn:population":0,
    "gn:timezone":"Europe/Belgrade",
    "iso:country":"XK",
    "name:sqi_x_preferred":[
        "Llaush\u00eb"
    ],
    "name:sqi_x_variant":[
        "Llausa",
        "Llausha"
    ],
    "name:srp_x_preferred":[
        "\u041b\u0430\u0443\u0448\u0430"
    ],
    "name:srp_x_variant":[
        "Lau\u0161a"
    ],
    "name:und_x_variant":[
        "Llausa",
        "Llausha",
        "Llaush\u00eb"
    ],
    "wof:name":"Lausa",
    "wof:placetype":"locality"
},
  "geometry": {"coordinates":[21.19241,42.97734000000001],"type":"Point"}
}