{
  "type": "Feature",
  "properties": {
    "gn:admin1_code":"10097357.0",
    "gn:admin2_code":"10.0",
    "gn:asciiname":"Svirce",
    "gn:country_code":"XK",
    "gn:dem":936,
    "gn:feature_class":"P",
    "gn:feature_code":"PPLL",
    "gn:name":"Svirce",
    "gn:population":0,
    "gn:timezone":"Europe/Belgrade",
    "iso:country":"XK",
    "name:fra_x_preferred":[
        "Svirce"
    ],
    "name:hrv_x_preferred":[
        "Svirce"
    ],
    "name:slv_x_preferred":[
        "Svirce"
    ],
    "name:sqi_x_preferred":[
        "Svirc\u00eb"
    ],
    "name:srp_x_preferred":[
        "\u0421\u0432\u0438\u0440\u0446\u0435"
    ],
    "name:srp_x_variant":[
        "Svirce"
    ],
    "wof:name":"Svirce",
    "wof:placetype":"locality"
},
  "geometry": {"coordinates":[21.57417,42.71611],"type":"Point"}
}