{
  "type": "Feature",
  "properties": {
    "gn:admin1_code":"10097358.0",
    "gn:admin2_code":"25.0",
    "gn:asciiname":"Hodic Mahala",
    "gn:country_code":"XK",
    "gn:dem":619,
    "gn:feature_class":"P",
    "gn:feature_code":"PPL",
    "gn:name":"Hodi\u0107 Mahala",
    "gn:population":0,
    "gn:timezone":"Europe/Belgrade",
    "iso:country":"XK",
    "name:srp_x_preferred":[
        "Hodi\u0107 Mahala"
    ],
    "wof:name":"Hodic Mahala",
    "wof:placetype":"locality"
},
  "geometry": {"coordinates":[20.79333,42.77139],"type":"Point"}
}