{
  "type": "Feature",
  "properties": {
    "gn:admin1_code":"10097360.0",
    "gn:admin2_code":"7.0",
    "gn:asciiname":"Ljugit",
    "gn:country_code":"XK",
    "gn:dem":637,
    "gn:feature_class":"P",
    "gn:feature_code":"PPL",
    "gn:name":"Ljugit",
    "gn:population":0,
    "gn:timezone":"Europe/Belgrade",
    "iso:country":"XK",
    "name:srp_x_preferred":[
        "Mahala Ljugit"
    ],
    "name:srp_x_variant":[
        "Ljugit"
    ],
    "wof:name":"Ljugit",
    "wof:placetype":"locality"
},
  "geometry": {"coordinates":[20.89222,42.54028],"type":"Point"}
}