{
  "type": "Feature",
  "properties": {
    "gn:admin1_code":"10097358.0",
    "gn:admin2_code":"25.0",
    "gn:asciiname":"Bezenic",
    "gn:country_code":"XK",
    "gn:dem":660,
    "gn:feature_class":"P",
    "gn:feature_code":"PPL",
    "gn:name":"Be\u017eeni\u0107",
    "gn:population":0,
    "gn:timezone":"Europe/Belgrade",
    "iso:country":"XK",
    "name:srp_x_preferred":[
        "Be\u017eeni\u0107"
    ],
    "wof:name":"Bezenic",
    "wof:placetype":"locality"
},
  "geometry": {"coordinates":[20.80556,42.66583],"type":"Point"}
}