{
  "type": "Feature",
  "properties": {
    "gn:admin1_code":"10096859.0",
    "gn:admin2_code":"5.0",
    "gn:asciiname":"Bardosan",
    "gn:country_code":"XK",
    "gn:dem":364,
    "gn:feature_class":"P",
    "gn:feature_code":"PPL",
    "gn:name":"Bardosan",
    "gn:population":0,
    "gn:timezone":"Europe/Belgrade",
    "iso:country":"XK",
    "name:sqi_x_preferred":[
        "Bardhasan"
    ],
    "name:sqi_x_variant":[
        "Bardosan\u00eb"
    ],
    "name:srp_x_preferred":[
        "\u0411\u0430\u0440\u0434\u043e\u0441\u0430\u043d"
    ],
    "name:srp_x_variant":[
        "Bardosan"
    ],
    "name:und_x_variant":[
        "Brdasan",
        "Bardusan",
        "Brdosan",
        "Berdosan"
    ],
    "wof:name":"Bardosan",
    "wof:placetype":"locality"
},
  "geometry": {"coordinates":[20.50472,42.40417],"type":"Point"}
}