{
  "type": "Feature",
  "properties": {
    "gn:admin1_code":"10097360.0",
    "gn:admin2_code":"19.0",
    "gn:asciiname":"Glavnik",
    "gn:country_code":"XK",
    "gn:dem":594,
    "gn:feature_class":"P",
    "gn:feature_code":"PPL",
    "gn:name":"Glavnik",
    "gn:population":0,
    "gn:timezone":"Europe/Belgrade",
    "iso:country":"XK",
    "name:sqi_x_preferred":[
        "Gllavnik"
    ],
    "name:sqi_x_variant":[
        "Gllamnik",
        "Gllamniku",
        "Vendenisi"
    ],
    "name:srp_x_preferred":[
        "\u0413\u043b\u0430\u0432\u043d\u0438\u043a"
    ],
    "name:srp_x_variant":[
        "Glavnik"
    ],
    "name:und_x_variant":[
        "Vendenisi",
        "Gllamnik",
        "Vendenis",
        "Gllamniku"
    ],
    "wof:name":"Glavnik",
    "wof:placetype":"locality"
},
  "geometry": {"coordinates":[21.18537,42.8713],"type":"Point"}
}