{
  "type": "Feature",
  "properties": {
    "gn:admin1_code":"10097360.0",
    "gn:admin2_code":"19.0",
    "gn:asciiname":"Mahalla Derisholska",
    "gn:country_code":"XK",
    "gn:dem":722,
    "gn:feature_class":"P",
    "gn:feature_code":"PPL",
    "gn:name":"Mahalla Derisholska",
    "gn:population":0,
    "gn:timezone":"Europe/Belgrade",
    "iso:country":"XK",
    "name:sqi_x_preferred":[
        "Mahalla Derisholska"
    ],
    "name:srp_x_preferred":[
        "Deryi\u0161olska Mahala"
    ],
    "wof:name":"Mahalla Derisholska",
    "wof:placetype":"locality"
},
  "geometry": {"coordinates":[21.12139,42.96778],"type":"Point"}
}