{
  "type": "Feature",
  "properties": {
    "gn:admin1_code":"10097360.0",
    "gn:admin2_code":"31.0",
    "gn:asciiname":"Lepi",
    "gn:country_code":"XK",
    "gn:dem":540,
    "gn:feature_class":"P",
    "gn:feature_code":"PPL",
    "gn:name":"Lepi",
    "gn:population":0,
    "gn:timezone":"Europe/Belgrade",
    "iso:country":"XK",
    "name:sqi_x_preferred":[
        "Lepi"
    ],
    "name:sqi_x_variant":[
        "Lepin\u00eb"
    ],
    "name:srp_x_preferred":[
        "Lepina"
    ],
    "name:srp_x_variant":[
        "\u041b\u0435\u043f\u0438\u043d\u0430"
    ],
    "name:und_x_variant":[
        "Lepin\u00eb"
    ],
    "wof:name":"Lepi",
    "wof:placetype":"locality"
},
  "geometry": {"coordinates":[21.07092,42.56891],"type":"Point"}
}