{
  "type": "Feature",
  "properties": {
    "gn:admin1_code":"10097360.0",
    "gn:admin2_code":"4.0",
    "gn:asciiname":"Tresnjevo",
    "gn:country_code":"XK",
    "gn:dem":574,
    "gn:feature_class":"P",
    "gn:feature_code":"PPL",
    "gn:name":"Tre\u0161njevo",
    "gn:population":0,
    "gn:timezone":"Europe/Belgrade",
    "iso:country":"XK",
    "name:srp_x_preferred":[
        "Tre\u0161njevo"
    ],
    "wof:name":"Tresnjevo",
    "wof:placetype":"locality"
},
  "geometry": {"coordinates":[21.00982,42.5949],"type":"Point"}
}