{
  "type": "Feature",
  "properties": {
    "gn:admin1_code":"10096138.0",
    "gn:admin2_code":"23.0",
    "gn:asciiname":"Rucuceva Mahala",
    "gn:country_code":"XK",
    "gn:dem":1103,
    "gn:feature_class":"P",
    "gn:feature_code":"PPL",
    "gn:name":"Ru\u010du\u0107eva Mahala",
    "gn:population":0,
    "gn:timezone":"Europe/Belgrade",
    "iso:country":"XK",
    "name:srp_x_preferred":[
        "Ru\u010du\u0107eva Mahala"
    ],
    "name:srp_x_variant":[
        "Ne\u0161ma"
    ],
    "wof:name":"Rucuceva Mahala",
    "wof:placetype":"locality"
},
  "geometry": {"coordinates":[21.06889,42.28833],"type":"Point"}
}