{
  "type": "Feature",
  "properties": {
    "gn:admin1_code":"10097357.0",
    "gn:admin2_code":"10.0",
    "gn:asciiname":"Lisacka",
    "gn:country_code":"XK",
    "gn:dem":862,
    "gn:feature_class":"P",
    "gn:feature_code":"PPLL",
    "gn:name":"Lisacka",
    "gn:population":0,
    "gn:timezone":"Europe/Belgrade",
    "iso:country":"XK",
    "name:sqi_x_preferred":[
        "Lisock\u00eb"
    ],
    "name:sqi_x_variant":[
        "Lesock\u00eb",
        "Lisori"
    ],
    "name:srp_x_preferred":[
        "Lisacka"
    ],
    "name:srp_x_variant":[
        "\u041b\u0438\u0441\u0430\u0446\u043a\u0430"
    ],
    "name:und_x_variant":[
        "Lisor",
        "Lisocka",
        "Lisoca"
    ],
    "wof:name":"Lisacka",
    "wof:placetype":"locality"
},
  "geometry": {"coordinates":[21.64806,42.66278],"type":"Point"}
}