{
  "type": "Feature",
  "properties": {
    "gn:admin1_code":"10097358.0",
    "gn:admin2_code":"12.0",
    "gn:asciiname":"Dratnica",
    "gn:country_code":"XK",
    "gn:dem":1044,
    "gn:feature_class":"P",
    "gn:feature_code":"PPL",
    "gn:name":"Dratnica",
    "gn:population":0,
    "gn:timezone":"Europe/Belgrade",
    "iso:country":"XK",
    "name:srp_x_preferred":[
        "Dratnica"
    ],
    "wof:name":"Dratnica",
    "wof:placetype":"locality"
},
  "geometry": {"coordinates":[20.89667,43.04694],"type":"Point"}
}