{
  "type": "Feature",
  "properties": {
    "gn:admin1_code":"10097358.0",
    "gn:admin2_code":"12.0",
    "gn:asciiname":"Zavrata",
    "gn:country_code":"XK",
    "gn:dem":942,
    "gn:feature_class":"P",
    "gn:feature_code":"PPL",
    "gn:name":"Zavrata",
    "gn:population":0,
    "gn:timezone":"Europe/Belgrade",
    "iso:country":"XK",
    "name:sqi_x_preferred":[
        "Zavrat\u00eb"
    ],
    "name:srp_x_preferred":[
        "Zavrata"
    ],
    "name:srp_x_variant":[
        "\u0417\u0430\u0432\u0440\u0430\u0442\u0430"
    ],
    "wof:name":"Zavrata",
    "wof:placetype":"locality"
},
  "geometry": {"coordinates":[20.87389,43.13194],"type":"Point"}
}