{
  "type": "Feature",
  "properties": {
    "gn:admin1_code":"10097359.0",
    "gn:admin2_code":"8.0",
    "gn:asciiname":"Kovrace (Krasniqaj)",
    "gn:country_code":"XK",
    "gn:dem":468,
    "gn:feature_class":"P",
    "gn:feature_code":"PPL",
    "gn:name":"Kovra\u00e7\u00eb (Krasniqaj)",
    "gn:population":0,
    "gn:timezone":"Europe/Belgrade",
    "iso:country":"XK",
    "name:sqi_x_preferred":[
        "Kovrag\u00eb"
    ],
    "name:sqi_x_variant":[
        "Kovra\u00e7\u00eb",
        "Krasniqaj"
    ],
    "name:und_x_variant":[
        "Kovraga"
    ],
    "wof:name":"Kovrace (Krasniqaj)",
    "wof:placetype":"locality"
},
  "geometry": {"coordinates":[20.50417,42.74833],"type":"Point"}
}