{
  "type": "Feature",
  "properties": {
    "gn:admin1_code":"10097361.0",
    "gn:admin2_code":"14.0",
    "gn:asciiname":"Zez Mahala",
    "gn:country_code":"XK",
    "gn:dem":579,
    "gn:feature_class":"P",
    "gn:feature_code":"PPL",
    "gn:name":"Zez Mahala",
    "gn:population":0,
    "gn:timezone":"Europe/Belgrade",
    "iso:country":"XK",
    "name:srp_x_preferred":[
        "\u0417\u0435\u0437 \u041c\u0430\u0445\u0430\u043b\u0430"
    ],
    "name:srp_x_variant":[
        "Zez Mahala"
    ],
    "wof:name":"Zez Mahala",
    "wof:placetype":"locality"
},
  "geometry": {"coordinates":[20.75056,42.52306],"type":"Point"}
}