{
  "type": "Feature",
  "properties": {
    "gn:admin1_code":"10097358.0",
    "gn:admin2_code":"28.0",
    "gn:asciiname":"Doljak",
    "gn:country_code":"XK",
    "gn:dem":588,
    "gn:feature_class":"P",
    "gn:feature_code":"PPL",
    "gn:name":"Doljak",
    "gn:population":0,
    "gn:timezone":"Europe/Belgrade",
    "iso:country":"XK",
    "name:sqi_x_preferred":[
        "Dalak"
    ],
    "name:sqi_x_variant":[
        "Dolak"
    ],
    "name:srp_x_preferred":[
        "\u0414\u043e\u0459\u0430\u043a"
    ],
    "name:srp_x_variant":[
        "Doljak"
    ],
    "name:und_x_variant":[
        "Dolak"
    ],
    "wof:name":"Doljak",
    "wof:placetype":"locality"
},
  "geometry": {"coordinates":[20.9275,42.81667],"type":"Point"}
}