{
  "type": "Feature",
  "properties": {
    "gn:admin1_code":"10097360.0",
    "gn:admin2_code":"7.0",
    "gn:asciiname":"Vukovce",
    "gn:country_code":"XK",
    "gn:dem":593,
    "gn:feature_class":"P",
    "gn:feature_code":"PPL",
    "gn:name":"Vukovce",
    "gn:population":0,
    "gn:timezone":"Europe/Belgrade",
    "iso:country":"XK",
    "name:sqi_x_preferred":[
        "Valmiri"
    ],
    "name:sqi_x_variant":[
        "Vukofci"
    ],
    "name:srp_x_preferred":[
        "Vukovce"
    ],
    "name:und_x_variant":[
        "Valmir",
        "Vukovcje"
    ],
    "wof:name":"Vukovce",
    "wof:placetype":"locality"
},
  "geometry": {"coordinates":[20.88361,42.57944000000001],"type":"Point"}
}