{
  "type": "Feature",
  "properties": {
    "gn:admin1_code":"10097360.0",
    "gn:admin2_code":"19.0",
    "gn:asciiname":"Surdula",
    "gn:country_code":"XK",
    "gn:dem":839,
    "gn:feature_class":"P",
    "gn:feature_code":"PPL",
    "gn:name":"Surdula",
    "gn:population":0,
    "gn:timezone":"Europe/Belgrade",
    "iso:country":"XK",
    "name:sqi_x_preferred":[
        "Surdull"
    ],
    "name:sqi_x_variant":[
        "Surthil",
        "Surdulli"
    ],
    "name:srp_x_preferred":[
        "\u0421\u0443\u0440\u0434\u0443\u043b\u0430"
    ],
    "name:srp_x_variant":[
        "Surdula"
    ],
    "name:und_x_variant":[
        "Surdulli",
        "Surdul",
        "Surthil",
        "Surdull"
    ],
    "wof:name":"Surdula",
    "wof:placetype":"locality"
},
  "geometry": {"coordinates":[21.28806,42.84944],"type":"Point"}
}