{
  "type": "Feature",
  "properties": {
    "gn:admin1_code":"10097360.0",
    "gn:admin2_code":"19.0",
    "gn:asciiname":"Poljanica",
    "gn:country_code":"XK",
    "gn:dem":597,
    "gn:feature_class":"P",
    "gn:feature_code":"PPL",
    "gn:name":"Poljanica",
    "gn:population":0,
    "gn:timezone":"Europe/Belgrade",
    "iso:country":"XK",
    "name:srp_x_preferred":[
        "Poljanica"
    ],
    "wof:name":"Poljanica",
    "wof:placetype":"locality"
},
  "geometry": {"coordinates":[21.1942,42.88816],"type":"Point"}
}