{
  "type": "Feature",
  "properties": {
    "gn:admin1_code":"10097360.0",
    "gn:admin2_code":"31.0",
    "gn:asciiname":"Badovac",
    "gn:country_code":"XK",
    "gn:dem":610,
    "gn:feature_class":"P",
    "gn:feature_code":"PPL",
    "gn:name":"Badovac",
    "gn:population":0,
    "gn:timezone":"Europe/Belgrade",
    "iso:country":"XK",
    "name:sqi_x_preferred":[
        "Badoc"
    ],
    "name:sqi_x_variant":[
        "Badovc",
        "Badofc"
    ],
    "name:srp_x_preferred":[
        "\u0411\u0430\u0434\u043e\u0432\u0430\u0446"
    ],
    "name:srp_x_variant":[
        "Badovac"
    ],
    "name:und_x_variant":[
        "Badofc"
    ],
    "wof:name":"Badovac",
    "wof:placetype":"locality"
},
  "geometry": {"coordinates":[21.2225,42.60972],"type":"Point"}
}