{
  "type": "Feature",
  "properties": {
    "gn:admin1_code":"10097360.0",
    "gn:admin2_code":"19.0",
    "gn:asciiname":"Poterovic Mahala",
    "gn:country_code":"XK",
    "gn:dem":811,
    "gn:feature_class":"P",
    "gn:feature_code":"PPL",
    "gn:name":"Poterovi\u0107 Mahala",
    "gn:population":0,
    "gn:timezone":"Europe/Belgrade",
    "iso:country":"XK",
    "name:sqi_x_preferred":[
        "Mahalla Peteroviq"
    ],
    "name:srp_x_preferred":[
        "Poterovi\u0107 Mahala"
    ],
    "wof:name":"Poterovic Mahala",
    "wof:placetype":"locality"
},
  "geometry": {"coordinates":[21.11615,42.87101],"type":"Point"}
}