{
  "type": "Feature",
  "properties": {
    "gn:admin1_code":"10097361.0",
    "gn:admin2_code":"2.0",
    "gn:asciiname":"Mali Krstac",
    "gn:country_code":"XK",
    "gn:dem":1063,
    "gn:feature_class":"P",
    "gn:feature_code":"PPL",
    "gn:name":"Mali Krstac",
    "gn:population":0,
    "gn:timezone":"Europe/Belgrade",
    "iso:country":"XK",
    "name:srp_x_preferred":[
        "Mali Krstac"
    ],
    "wof:name":"Mali Krstac",
    "wof:placetype":"locality"
},
  "geometry": {"coordinates":[20.60639,42.07278],"type":"Point"}
}