{
  "type": "Feature",
  "properties": {
    "gn:admin1_code":"10097358.0",
    "gn:admin2_code":"29.0",
    "gn:asciiname":"Ceceve",
    "gn:country_code":"XK",
    "gn:dem":954,
    "gn:feature_class":"P",
    "gn:feature_code":"PPLL",
    "gn:name":"\u00c7e\u00e7ev\u00eb",
    "gn:population":0,
    "gn:timezone":"Europe/Belgrade",
    "iso:country":"XK",
    "name:sqi_x_preferred":[
        "\u00c7eqev\u00eb"
    ],
    "name:sqi_x_variant":[
        "\u00c7e\u00e7ev\u00eb",
        "\u00c7eqov\u00eb"
    ],
    "name:srp_x_preferred":[
        "\u010ce\u010devo"
    ],
    "name:srp_x_variant":[
        "\u0427\u0435\u0447\u0435\u0432\u043e"
    ],
    "name:und_x_variant":[
        "\u00c7eqov\u00eb"
    ],
    "wof:name":"Ceceve",
    "wof:placetype":"locality"
},
  "geometry": {"coordinates":[20.60667,42.91889000000001],"type":"Point"}
}