{
  "type": "Feature",
  "properties": {
    "gn:admin1_code":"10097361.0",
    "gn:admin2_code":"2.0",
    "gn:asciiname":"Donja Rapca",
    "gn:country_code":"XK",
    "gn:dem":957,
    "gn:feature_class":"P",
    "gn:feature_code":"PPL",
    "gn:name":"Donja Rap\u010da",
    "gn:population":0,
    "gn:timezone":"Europe/Belgrade",
    "iso:country":"XK",
    "name:srp_x_preferred":[
        "Donja Rap\u010da"
    ],
    "wof:name":"Donja Rapca",
    "wof:placetype":"locality"
},
  "geometry": {"coordinates":[20.61833,42.08306],"type":"Point"}
}