{
  "type": "Feature",
  "properties": {
    "gn:admin1_code":"10097360.0",
    "gn:admin2_code":"7.0",
    "gn:asciiname":"Mujovic",
    "gn:country_code":"XK",
    "gn:dem":772,
    "gn:feature_class":"P",
    "gn:feature_code":"PPL",
    "gn:name":"Mujovi\u0107",
    "gn:population":0,
    "gn:timezone":"Europe/Belgrade",
    "iso:country":"XK",
    "name:srp_x_preferred":[
        "Mujovi\u0107"
    ],
    "wof:name":"Mujovic",
    "wof:placetype":"locality"
},
  "geometry": {"coordinates":[20.9325,42.70889],"type":"Point"}
}