{
  "type": "Feature",
  "properties": {
    "gn:admin1_code":"10096138.0",
    "gn:admin2_code":"23.0",
    "gn:asciiname":"Firaja",
    "gn:country_code":"XK",
    "gn:dem":894,
    "gn:feature_class":"P",
    "gn:feature_code":"PPL",
    "gn:name":"Firaja",
    "gn:population":0,
    "gn:timezone":"Europe/Belgrade",
    "iso:country":"XK",
    "name:sqi_x_preferred":[
        "Firaj\u00eb"
    ],
    "name:srp_x_preferred":[
        "Firaja"
    ],
    "name:srp_x_variant":[
        "\u0424\u0438\u0440\u0430\u0458\u0430"
    ],
    "wof:name":"Firaja",
    "wof:placetype":"locality"
},
  "geometry": {"coordinates":[21.09833,42.25],"type":"Point"}
}