{
  "type": "Feature",
  "properties": {
    "gn:admin1_code":"10097360.0",
    "gn:admin2_code":"19.0",
    "gn:asciiname":"Canoga",
    "gn:country_code":"XK",
    "gn:dem":799,
    "gn:feature_class":"P",
    "gn:feature_code":"PPL",
    "gn:name":"\u010canoga",
    "gn:population":0,
    "gn:timezone":"Europe/Belgrade",
    "iso:country":"XK",
    "name:srp_x_preferred":[
        "\u010canoga"
    ],
    "wof:name":"Canoga",
    "wof:placetype":"locality"
},
  "geometry": {"coordinates":[21.1025,43.01056],"type":"Point"}
}